Workbook

Sheet Summary (2)
B1: LIST INVESTASI
C3: Close
C4: Delivered
C5: Partial Delivery
C6: Open
E7: =Detail!E2 -> 4 | G7: =Detail!F2 -> 5 | H7: =Detail!G2 -> 6 | I7: =Detail!H2 -> 7 | K7: =Detail!I2 -> 8
A8: NO | B8: No. PO | C8: Date | D8: Nama Barang | E8: =Detail!E3 -> Qty | F8: Harga Beli (only added if Margin is set) | G8: =Detail!F3 -> Harga | H8: Total PO | I8: Modal | J8: Margin Per Unit | K8: =Detail!I3 -> Margin | L8: Add Margin | M8: Total Margin | N8: Invoice /DO | U8: DO Total | V8: DO Outstanding | W8: Margin | X8: AR MARGIN | Y8: Del Time | Z8: Invoice date | AA8: Initial Payment Date | AB8: adjusting TOP 60 Days | AC8: Status | AD8: Notes
N9: Jul | O9: Aug | P9: Sep | Q9: Oct | R9: Nov | S9: Dec | T9: Add Margin (by Agreement) | AD9: Notes
A10: 1 | B10: 5200954145 | C10: =VLOOKUP($B10,Detail!$B$4:$Q$21,2,0) -> 45839 | D10: Top Frame 800 | E10: =SUMIF(Detail!$B$4:$B$21,'Summary (2)'!$B10,Detail!$E$4:$E$21) -> 2 | G10: =VLOOKUP($B10,Detail!$B$4:$Q$21,5,0) -> 225000000 | H10: =E10*G10 -> 450000000 | I10: =SUMIF(Detail!$B$4:$B$21,'Summary (2)'!B10,Detail!$H$4:$H$21) -> 225000000 | J10: =(I10*20%)/E10 -> 22500000 | K10: =I10*20% -> 45000000 | M10: =SUM(K10:L10) -> 45000000 | N10: =E10 -> 2 | U10: =SUM(N10:S10) -> 2 | V10: =E10-U10 -> 0 | W10: =J10*U10 -> 45000000 | X10: =K10-W10 -> 0 | Y10: 45861 | Z10: 45863 | AA10: 45894 | AC10: Close
A11: 2 | B11: 5200954149 | C11: =VLOOKUP($B11,Detail!$B$4:$Q$21,2,0) -> 45839 | D11: Top Frame 800 | E11: =SUMIF(Detail!$B$4:$B$21,'Summary (2)'!$B11,Detail!$E$4:$E$21) -> 3 | G11: =VLOOKUP($B11,Detail!$B$4:$Q$21,5,0) -> 225000000 | H11: =E11*G11 -> 675000000 | I11: =SUMIF(Detail!$B$4:$B$21,'Summary (2)'!B11,Detail!$H$4:$H$21) -> 337500000 | J11: =(I11*20%)/E11 -> 22500000 | K11: =I11*20% -> 67500000 | M11: =SUM(K11:L11) -> 67500000 | N11: =E11 -> 3 | U11: =SUM(N11:S11) -> 3 | V11: =E11-U11 -> 0 | W11: =J11*U11 -> 67500000 | X11: =K11-W11 -> 0 | Y11: 45861 | Z11: 45863 | AA11: 45894 | AC11: Close
A12: 3 | B12: 5200954160 | C12: =VLOOKUP($B12,Detail!$B$4:$Q$21,2,0) -> 45839 | D12: Top Frame 800 | E12: =SUMIF(Detail!$B$4:$B$21,'Summary (2)'!$B12,Detail!$E$4:$E$21) -> 3 | G12: =VLOOKUP($B12,Detail!$B$4:$Q$21,5,0) -> 225000000 | H12: =E12*G12 -> 675000000 | I12: =SUMIF(Detail!$B$4:$B$21,'Summary (2)'!B12,Detail!$H$4:$H$21) -> 337500000 | J12: =(I12*20%)/E12 -> 22500000 | K12: =I12*20% -> 67500000 | M12: =SUM(K12:L12) -> 67500000 | N12: =E12 -> 3 | U12: =SUM(N12:S12) -> 3 | V12: =E12-U12 -> 0 | W12: =J12*U12 -> 67500000 | X12: =K12-W12 -> 0 | Y12: 45861 | Z12: 45863 | AA12: 45894 | AC12: Close
A13: 4 | B13: 5200954165 | C13: =VLOOKUP($B13,Detail!$B$4:$Q$21,2,0) -> 45870 | D13: Top Frame 800 | E13: =SUMIF(Detail!$B$4:$B$21,'Summary (2)'!$B13,Detail!$E$4:$E$21) -> 3 | G13: =VLOOKUP($B13,Detail!$B$4:$Q$21,5,0) -> 225000000 | H13: =E13*G13 -> 675000000 | I13: =SUMIF(Detail!$B$4:$B$21,'Summary (2)'!B13,Detail!$H$4:$H$21) -> 337500000 | J13: =(I13*20%)/E13 -> 22500000 | K13: =I13*20% -> 67500000 | M13: =SUM(K13:L13) -> 67500000 | O13: =E13 -> 3 | U13: =SUM(N13:S13) -> 3 | V13: =E13-U13 -> 0 | W13: =J13*U13 -> 67500000 | X13: =K13-W13 -> 0 | Y13: 45868 | Z13: 45873 | AA13: 45904 | AC13: Close
A14: 5 | B14: 5200954167 | C14: =VLOOKUP($B14,Detail!$B$4:$Q$21,2,0) -> 45870 | D14: Top Frame 800 | E14: =SUMIF(Detail!$B$4:$B$21,'Summary (2)'!$B14,Detail!$E$4:$E$21) -> 3 | G14: =VLOOKUP($B14,Detail!$B$4:$Q$21,5,0) -> 225000000 | H14: =E14*G14 -> 675000000 | I14: =SUMIF(Detail!$B$4:$B$21,'Summary (2)'!B14,Detail!$H$4:$H$21) -> 337500000 | J14: =(I14*20%)/E14 -> 22500000 | K14: =I14*20% -> 67500000 | M14: =SUM(K14:L14) -> 67500000 | O14: =E14 -> 3 | U14: =SUM(N14:S14) -> 3 | V14: =E14-U14 -> 0 | W14: =J14*U14 -> 67500000 | X14: =K14-W14 -> 0 | Y14: 45868 | Z14: 45873 | AA14: 45904 | AC14: Close
A15: 6 | B15: 5200954168 | C15: =VLOOKUP($B15,Detail!$B$4:$Q$21,2,0) -> 45870 | D15: Top Frame 800 | E15: =SUMIF(Detail!$B$4:$B$21,'Summary (2)'!$B15,Detail!$E$4:$E$21) -> 2 | G15: =VLOOKUP($B15,Detail!$B$4:$Q$21,5,0) -> 225000000 | H15: =E15*G15 -> 450000000 | I15: =SUMIF(Detail!$B$4:$B$21,'Summary (2)'!B15,Detail!$H$4:$H$21) -> 225000000 | J15: =(I15*20%)/E15 -> 22500000 | K15: =I15*20% -> 45000000 | M15: =SUM(K15:L15) -> 45000000 | O15: =E15 -> 2 | U15: =SUM(N15:S15) -> 2 | V15: =E15-U15 -> 0 | W15: =J15*U15 -> 45000000 | X15: =K15-W15 -> 0 | Y15: 45868 | Z15: 45873 | AA15: 45904 | AC15: Close
A16: 7 | B16: 5200954169 | C16: =VLOOKUP($B16,Detail!$B$4:$Q$21,2,0) -> 45870 | D16: Top Frame 800 | E16: =SUMIF(Detail!$B$4:$B$21,'Summary (2)'!$B16,Detail!$E$4:$E$21) -> 2 | G16: =VLOOKUP($B16,Detail!$B$4:$Q$21,5,0) -> 225000000 | H16: =E16*G16 -> 450000000 | I16: =SUMIF(Detail!$B$4:$B$21,'Summary (2)'!B16,Detail!$H$4:$H$21) -> 225000000 | J16: =(I16*20%)/E16 -> 22500000 | K16: =I16*20% -> 45000000 | M16: =SUM(K16:L16) -> 45000000 | O16: =E16 -> 2 | U16: =SUM(N16:S16) -> 2 | V16: =E16-U16 -> 0 | W16: =J16*U16 -> 45000000 | X16: =K16-W16 -> 0 | Y16: 45868 | Z16: 45873 | AA16: 45904 | AC16: Close
A17: 8 | B17: 5200777098 | C17: =VLOOKUP($B17,Detail!$B$4:$Q$25,2,0) -> 45877 | D17: DVAR 3771-B0-20D-PPC Statcom Steel Support | E17: =SUMIF(Detail!$B$4:$B$25,'Summary (2)'!$B17,Detail!$E$4:$E$25) -> 1 | G17: =VLOOKUP($B17,Detail!$B$4:$Q$25,5,0) -> 1149199000 | H17: =E17*G17 -> 1149199000 | I17: =SUMIF(Detail!$B$4:$B$25,'Summary (2)'!B17,Detail!$H$4:$H$25) -> 574599500 | J17: =(I17*20%)/E17 -> 114919900 | K17: =I17*20% -> 114919900 | M17: =SUM(K17:L17) -> 114919900 | O17: 0 | P17: 1 | U17: =SUM(N17:S17) -> 1 | V17: =E17-U17 -> 0 | W17: =J17*U17 -> 114919900 | X17: =K17-W17 -> 0 | Y17: 45930 | Z17: =Y17+7 -> 45937 | AA17: =Z17+30 -> 45967 | AB17: =Z17+60 -> 45997 | AC17: Delivered
A18: 9 | B18: 5200776987 | C18: =VLOOKUP($B18,Detail!$B$4:$Q$25,2,0) -> 45877 | D18: Top Frame 800 | E18: =SUMIF(Detail!$B$4:$B$25,'Summary (2)'!$B18,Detail!$E$4:$E$25) -> 2 | G18: =VLOOKUP($B18,Detail!$B$4:$Q$25,5,0) -> 225000000 | H18: =E18*G18 -> 450000000 | I18: =SUMIF(Detail!$B$4:$B$25,'Summary (2)'!B18,Detail!$H$4:$H$25) -> 225000000 | J18: =(I18*20%)/E18 -> 22500000 | K18: =I18*20% -> 45000000 | M18: =SUM(K18:L18) -> 45000000 | O18: 0 | P18: 2 | U18: =SUM(N18:S18) -> 2 | V18: =E18-U18 -> 0 | W18: =J18*U18 -> 45000000 | X18: =K18-W18 -> 0 | Y18: 45923 | Z18: =Y18+7 -> 45930 | AA18: =Z18+30 -> 45960 | AB18: =Z18+60 -> 45990 | AC18: Delivered
A19: 10 | B19: 5200777132 | C19: =VLOOKUP($B19,Detail!$B$4:$Q$110,2,0) -> 45880 | D19: Leser Barrier MK 01-F3004973 | E19: 20 | G19: =VLOOKUP($B19,Detail!$B$4:$Q$25,5,0) -> 40457500 | H19: =E19*G19 -> 809150000 | I19: =H19*50% -> 404575000 | J19: =(I19*13%)/E19 -> 2629737.5 | K19: =I19*13% -> 52594750 | M19: =SUM(K19:L19) -> 52594750 | O19: 0 | U19: =SUM(N19:S19) -> 0 | V19: =E19-U19 -> 20 | W19: =J19*U19 -> 0 | X19: =K19-W19 -> 52594750 | Y19: 45922 | Z19: =Y19+7 -> 45929 | AA19: =Z19+30 -> 45959 | AB19: =Z19+60 -> 45989 | AC19: Open
A20: 11 | B20: =Detail!$B$45 -> 5200972695 | C20: =Detail!$C$45 -> 45891 | D20: Tangki | E20: 8 | F20: 75000000 | G20: 100500000 | H20: =E20*G20 -> 804000000 | I20: =H20*50% -> 402000000 | J20: 12750000 | K20: =E20*J20 -> 102000000 | M20: =SUM(K20:L20) -> 102000000 | O20: 0 | P20: 8 | T20: Margin was arranged 25mil/ea | U20: =SUM(N20:S20) -> 8 | V20: =E20-U20 -> 0 | W20: =J20*U20 -> 102000000 | X20: =K20-W20 -> 0 | Y20: 45925 | Z20: =Y20+7 -> 45932 | AA20: =Z20+30 -> 45962 | AB20: =Z20+60 -> 45992 | AC20: Delivered
A21: 12 | B21: =Detail!B53 -> 5200777558 | C21: 45901 | D21: Top Frame 2630 | E21: 1 | G21: =Detail!F53 -> 685000000 | H21: =E21*G21 -> 685000000 | I21: =H21*50% -> 342500000 | J21: =(I21*20%)/E21 -> 68500000 | K21: =I21*20% -> 68500000 | M21: =SUM(K21:L21) -> 68500000 | P21: 1 | U21: =SUM(N21:S21) -> 1 | V21: =E21-U21 -> 0 | W21: =J21*U21 -> 68500000 | X21: =K21-W21 -> 0 | Y21: 45923 | Z21: =Y21+7 -> 45930 | AA21: =Z21+30 -> 45960 | AB21: =Z21+60 -> 45990 | AC21: Delivered
A22: 13 | B22: =Detail!B54 -> 5200777559 | C22: 45901 | D22: Top Frame 800 | E22: 2 | G22: =Detail!F54 -> 225000000 | H22: =E22*G22 -> 450000000 | I22: =H22*50% -> 225000000 | J22: =(I22*20%)/E22 -> 22500000 | K22: =I22*20% -> 45000000 | M22: =SUM(K22:L22) -> 45000000 | P22: 2 | U22: =SUM(N22:S22) -> 2 | V22: =E22-U22 -> 0 | W22: =J22*U22 -> 45000000 | X22: =K22-W22 -> 0 | Y22: 45925 | Z22: =Y22+7 -> 45932 | AA22: =Z22+30 -> 45962 | AB22: =Z22+60 -> 45992 | AC22: Delivered
A23: 14 | B23: =Detail!$B$56 -> 5200777758 | C23: 45909 | D23: Pipe Spool | E23: 1 | G23: =Detail!F56 -> 2231048200 | H23: =E23*G23 -> 2231048200 | I23: =H23*50% -> 1115524100 | J23: =(I23*20%)/E23 -> 223104820 | K23: =I23*20% -> 223104820 | M23: =SUM(K23:L23) -> 223104820 | P23: 1 | U23: =SUM(N23:S23) -> 1 | V23: =E23-U23 -> 0 | W23: =J23*U23 -> 223104820 | X23: =K23-W23 -> 0 | Y23: 45930 | Z23: =Y23+7 -> 45937 | AA23: =Z23+30 -> 45967 | AB23: =Z23+60 -> 45997 | AC23: Delivered
A24: 15 | B24: =Detail!$B$58 -> 5200778319 | C24: 45909 | D24: =Detail!$D$58 -> Top Frame 800 | E24: 2 | G24: =Detail!$F$58 -> 225000000 | H24: =E24*G24 -> 450000000 | I24: =H24*50% -> 225000000 | J24: =(I24*20%)/E24 -> 22500000 | K24: =I24*20% -> 45000000 | M24: =SUM(K24:L24) -> 45000000 | P24: 2 | U24: =SUM(N24:S24) -> 2 | V24: =E24-U24 -> 0 | W24: =J24*U24 -> 45000000 | X24: =K24-W24 -> 0 | Y24: 45940 | Z24: =Y24+7 -> 45947 | AA24: =Z24+30 -> 45977 | AB24: =Z24+60 -> 46007 | AC24: Delivered
A25: 16 | B25: 5200778328 | C25: 45915 | D25: Top Frame 2630 | E25: 1 | G25: =Detail!F59 -> 685000000 | H25: =E25*G25 -> 685000000 | I25: =H25*50% -> 342500000 | J25: =(I25*20%)/E25 -> 68500000 | K25: =(I25*20%)+F25 -> 68500000 | L25: 66261000 | M25: =SUM(K25:L25) -> 134761000 | P25: 1 | U25: =SUM(N25:S25) -> 1 | V25: =E25-U25 -> 0 | W25: =J25*U25+L25 -> 134761000 | X25: =K25+L25-W25 -> 0 | Y25: 45940 | Z25: =Y25+7 -> 45947 | AA25: =Z25+30 -> 45977 | AB25: =Z25+60 -> 46007 | AC25: Delivered
B27: TOTAL MARGIN | I27: =SUM(I10:I26) -> 5881698600 | K27: =SUM(K10:K26) -> 1169619470 | L27: =SUM(L10:L26) -> 66261000 | M27: =SUM(M10:M26) -> 1235880470 | W27: =SUM(W10:W25) -> 1183285720 | X27: =SUM(X10:X25) -> 52594750
X28: =W27+X27-H40 -> 0
E29: A | G29: B | H29: C | I29: D | J29: E | K29: F=A+B+C-D-E
E30: TGL | F30: Modal Setor Awal | G30: Margin | H30: Pencairan Modal | I30: Modal PO Baru | J30: Penarikan Margin | K30: Dana Tersedia
E31: 45839 | F31: =SUM(I10:I12) -> 900000000 | G31: =SUM(W10:W12) -> 180000000 | K31: =F31+G31 -> 1080000000
E32: 45870 | F32: =SUM(I13:I16) -> 1125000000 | G32: =SUM(W13:W16) -> 225000000 | I32: =SUM(I17:I20) -> 1606174500 | K32: =K31+F32+G32+H32-I32-J32 -> 823825500
E33: 45901 | F33: 1426698600 | I33: =SUM(I21:I25) -> 2250524100 | K33: =K32+F33+G33+H33-I33-J33 -> 0
E34: 45931 | G34: =SUM(W17:X25) -> 830880470 | I34: =-I32-I33 -> -3856698600 | K34: =K33+F34+G34+H34-I34-J34 -> 4687579070
E35: 45962 | K35: =K34+F35+G35+H35-I35-J35 -> 4687579070
E36: 45992 | K36: =K35+F36+G36+H36-I36-J36 -> 4687579070
F37: =SUM(F31:F36) -> 3451698600 | G37: =SUM(G31:G36) -> 1235880470 | H37: =SUM(H31:H36) -> 0 | I37: =SUM(I31:I36) -> 0 | K37: =F37+G37+H37-I37 -> 4687579070
E39: Setor Modal | H39: =F37 -> 3451698600 | I39: A
E40: Margin | H40: =W27+X27 -> 1235880470 | I40: B
H41: 0
E42: Dana Tersedia | H42: =SUM(H39:H41) -> 4687579070 | I42: C=A+B
E43: Modal Yosi Ditempatkan | H43: -3000000000 | I43: D
B44: Total Margin Awal | C44: =G37 -> 1235880470 | E44: Modal dtarik | H44: =H42+H43 -> 1687579070 | I44: E=C-D
B45: Margin PO 3,8 | C45: =SUM(W17:X25) -> 830880470
B46: Total Margin | C46: =SUM(C44:C45) -> 2066760940
B47: Margin Yosi | C47: -300000000
B48: Total Margin | C48: =C46+C47 -> 1766760940
B50: Margin Blm cair | C50: =C48-C44 -> 530880470

Sheet Asumsi Summary V.4 (3)
B1: LIST INVESTASI
C3: Close
C4: Delivered
C5: Partial Delivery
C6: Open
C7: Margin Selisih | E7: =Detail!E2 -> 4 | G7: =Detail!F2 -> 5 | H7: =Detail!G2 -> 6 | I7: =Detail!H2 -> 7 | K7: =Detail!I2 -> 8
C8: Tidak aada di PO Tari
A10: NO | B10: No. PO | C10: Date | D10: Nama Barang | E10: =Detail!E3 -> Qty | F10: Harga Beli (only added if Margin is set) | G10: =Detail!F3 -> Harga | H10: Total PO | I10: Modal | J10: Margin Per Unit | K10: =Detail!I3 -> Margin | L10: Add Margin | M10: Total Margin | N10: Invoice /DO | U10: DO Total | V10: DO Outstanding | W10: Margin | X10: AR MARGIN | Y10: Del Time | Z10: Invoice date | AA10: Initial Payment Date | AB10: adjusting TOP 60 Days | AC10: Status | AD10: Notes | AF10: Tari | AG10: Total Margin TARI | AH10: Selisih
N11: Jul | O11: Aug | P11: Sep | Q11: Oct | R11: Nov | S11: Dec | T11: Add Margin (by Agreement) | AD11: Notes
A12: 1 | B12: 5200954145 | C12: =VLOOKUP($B12,Detail!$B$4:$Q$21,2,0) -> 45839 | D12: Top Frame 800 | E12: =SUMIF(Detail!$B$4:$B$21,'Asumsi Summary V.4 (3)'!$B12,Detail!$E$4:$E$21) -> 2 | G12: =VLOOKUP($B12,Detail!$B$4:$Q$21,5,0) -> 225000000 | H12: =E12*G12 -> 450000000 | I12: =SUMIF(Detail!$B$4:$B$21,'Asumsi Summary V.4 (3)'!B12,Detail!$H$4:$H$21) -> 225000000 | J12: =(I12*20%)/E12 -> 22500000 | K12: =I12*20% -> 45000000 | M12: =SUM(K12:L12) -> 45000000 | N12: =E12 -> 2 | U12: =SUM(N12:S12) -> 2 | V12: =E12-U12 -> 0 | W12: =J12*U12 -> 45000000 | X12: =K12-W12 -> 0 | Y12: 45861 | Z12: 45863 | AA12: 45894 | AC12: Close | AF12: =VLOOKUP(B12,investasi!$B$5:$G$18,6,0) -> 45000000 | AG12: =M12 -> 45000000 | AH12: =AF12-AG12 -> 0
A13: 2 | B13: 5200954149 | C13: =VLOOKUP($B13,Detail!$B$4:$Q$21,2,0) -> 45839 | D13: Top Frame 800 | E13: =SUMIF(Detail!$B$4:$B$21,'Asumsi Summary V.4 (3)'!$B13,Detail!$E$4:$E$21) -> 3 | G13: =VLOOKUP($B13,Detail!$B$4:$Q$21,5,0) -> 225000000 | H13: =E13*G13 -> 675000000 | I13: =SUMIF(Detail!$B$4:$B$21,'Asumsi Summary V.4 (3)'!B13,Detail!$H$4:$H$21) -> 337500000 | J13: =(I13*20%)/E13 -> 22500000 | K13: =I13*20% -> 67500000 | M13: =SUM(K13:L13) -> 67500000 | N13: =E13 -> 3 | U13: =SUM(N13:S13) -> 3 | V13: =E13-U13 -> 0 | W13: =J13*U13 -> 67500000 | X13: =K13-W13 -> 0 | Y13: 45861 | Z13: 45863 | AA13: 45894 | AC13: Close | AF13: =VLOOKUP(B13,investasi!$B$5:$G$18,6,0) -> 67500000 | AG13: =M13 -> 67500000 | AH13: =AF13-AG13 -> 0
A14: 3 | B14: 5200954160 | C14: =VLOOKUP($B14,Detail!$B$4:$Q$21,2,0) -> 45839 | D14: Top Frame 800 | E14: =SUMIF(Detail!$B$4:$B$21,'Asumsi Summary V.4 (3)'!$B14,Detail!$E$4:$E$21) -> 3 | G14: =VLOOKUP($B14,Detail!$B$4:$Q$21,5,0) -> 225000000 | H14: =E14*G14 -> 675000000 | I14: =SUMIF(Detail!$B$4:$B$21,'Asumsi Summary V.4 (3)'!B14,Detail!$H$4:$H$21) -> 337500000 | J14: =(I14*20%)/E14 -> 22500000 | K14: =I14*20% -> 67500000 | M14: =SUM(K14:L14) -> 67500000 | N14: =E14 -> 3 | U14: =SUM(N14:S14) -> 3 | V14: =E14-U14 -> 0 | W14: =J14*U14 -> 67500000 | X14: =K14-W14 -> 0 | Y14: 45861 | Z14: 45863 | AA14: 45894 | AC14: Close | AF14: =VLOOKUP(B14,investasi!$B$5:$G$18,6,0) -> 67500000 | AG14: =M14 -> 67500000 | AH14: =AF14-AG14 -> 0
A15: 4 | B15: 5200954165 | C15: =VLOOKUP($B15,Detail!$B$4:$Q$21,2,0) -> 45870 | D15: Top Frame 800 | E15: =SUMIF(Detail!$B$4:$B$21,'Asumsi Summary V.4 (3)'!$B15,Detail!$E$4:$E$21) -> 3 | G15: =VLOOKUP($B15,Detail!$B$4:$Q$21,5,0) -> 225000000 | H15: =E15*G15 -> 675000000 | I15: =SUMIF(Detail!$B$4:$B$21,'Asumsi Summary V.4 (3)'!B15,Detail!$H$4:$H$21) -> 337500000 | J15: =(I15*20%)/E15 -> 22500000 | K15: =I15*20% -> 67500000 | M15: =SUM(K15:L15) -> 67500000 | O15: =E15 -> 3 | U15: =SUM(N15:S15) -> 3 | V15: =E15-U15 -> 0 | W15: =J15*U15 -> 67500000 | X15: =K15-W15 -> 0 | Y15: 45868 | Z15: 45873 | AA15: 45904 | AC15: Close | AF15: =VLOOKUP(B15,investasi!$B$5:$G$18,6,0) -> 67500000 | AG15: =M15 -> 67500000 | AH15: =AF15-AG15 -> 0
A16: 5 | B16: 5200954167 | C16: =VLOOKUP($B16,Detail!$B$4:$Q$21,2,0) -> 45870 | D16: Top Frame 800 | E16: =SUMIF(Detail!$B$4:$B$21,'Asumsi Summary V.4 (3)'!$B16,Detail!$E$4:$E$21) -> 3 | G16: =VLOOKUP($B16,Detail!$B$4:$Q$21,5,0) -> 225000000 | H16: =E16*G16 -> 675000000 | I16: =SUMIF(Detail!$B$4:$B$21,'Asumsi Summary V.4 (3)'!B16,Detail!$H$4:$H$21) -> 337500000 | J16: =(I16*20%)/E16 -> 22500000 | K16: =I16*20% -> 67500000 | M16: =SUM(K16:L16) -> 67500000 | O16: =E16 -> 3 | U16: =SUM(N16:S16) -> 3 | V16: =E16-U16 -> 0 | W16: =J16*U16 -> 67500000 | X16: =K16-W16 -> 0 | Y16: 45868 | Z16: 45873 | AA16: 45904 | AC16: Close | AF16: =VLOOKUP(B16,investasi!$B$5:$G$18,6,0) -> 67500000 | AG16: =M16 -> 67500000 | AH16: =AF16-AG16 -> 0
A17: 6 | B17: 5200954168 | C17: =VLOOKUP($B17,Detail!$B$4:$Q$21,2,0) -> 45870 | D17: Top Frame 800 | E17: =SUMIF(Detail!$B$4:$B$21,'Asumsi Summary V.4 (3)'!$B17,Detail!$E$4:$E$21) -> 2 | G17: =VLOOKUP($B17,Detail!$B$4:$Q$21,5,0) -> 225000000 | H17: =E17*G17 -> 450000000 | I17: =SUMIF(Detail!$B$4:$B$21,'Asumsi Summary V.4 (3)'!B17,Detail!$H$4:$H$21) -> 225000000 | J17: =(I17*20%)/E17 -> 22500000 | K17: =I17*20% -> 45000000 | M17: =SUM(K17:L17) -> 45000000 | O17: =E17 -> 2 | U17: =SUM(N17:S17) -> 2 | V17: =E17-U17 -> 0 | W17: =J17*U17 -> 45000000 | X17: =K17-W17 -> 0 | Y17: 45868 | Z17: 45873 | AA17: 45904 | AC17: Close | AF17: =VLOOKUP(B17,investasi!$B$5:$G$18,6,0) -> 45000000 | AG17: =M17 -> 45000000 | AH17: =AF17-AG17 -> 0
A18: 7 | B18: 5200954169 | C18: =VLOOKUP($B18,Detail!$B$4:$Q$21,2,0) -> 45870 | D18: Top Frame 800 | E18: =SUMIF(Detail!$B$4:$B$21,'Asumsi Summary V.4 (3)'!$B18,Detail!$E$4:$E$21) -> 2 | G18: =VLOOKUP($B18,Detail!$B$4:$Q$21,5,0) -> 225000000 | H18: =E18*G18 -> 450000000 | I18: =SUMIF(Detail!$B$4:$B$21,'Asumsi Summary V.4 (3)'!B18,Detail!$H$4:$H$21) -> 225000000 | J18: =(I18*20%)/E18 -> 22500000 | K18: =I18*20% -> 45000000 | M18: =SUM(K18:L18) -> 45000000 | O18: =E18 -> 2 | U18: =SUM(N18:S18) -> 2 | V18: =E18-U18 -> 0 | W18: =J18*U18 -> 45000000 | X18: =K18-W18 -> 0 | Y18: 45868 | Z18: 45873 | AA18: 45904 | AC18: Close | AF18: =VLOOKUP(B18,investasi!$B$5:$G$18,6,0) -> 45000000 | AG18: =M18 -> 45000000 | AH18: =AF18-AG18 -> 0
A19: 8 | B19: 5200777098 | C19: =VLOOKUP($B19,Detail!$B$4:$Q$25,2,0) -> 45877 | D19: DVAR 3771-B0-20D-PPC Statcom Steel Support | E19: =SUMIF(Detail!$B$4:$B$25,'Asumsi Summary V.4 (3)'!$B19,Detail!$E$4:$E$25) -> 1 | G19: =VLOOKUP($B19,Detail!$B$4:$Q$25,5,0) -> 1149199000 | H19: =E19*G19 -> 1149199000 | I19: =SUMIF(Detail!$B$4:$B$25,'Asumsi Summary V.4 (3)'!B19,Detail!$H$4:$H$25) -> 574599500 | J19: =(I19*20%)/E19 -> 114919900 | K19: =I19*20% -> 114919900 | M19: =SUM(K19:L19) -> 114919900 | O19: 0 | P19: 1 | U19: =SUM(N19:S19) -> 1 | V19: =E19-U19 -> 0 | W19: =J19*U19 -> 114919900 | X19: =K19-W19 -> 0 | Y19: 45930 | Z19: =Y19+7 -> 45937 | AA19: =Z19+30 -> 45967 | AB19: =Z19+60 -> 45997 | AC19: Close | AF19: =VLOOKUP(B19,investasi!$B$5:$G$18,6,0) -> 57248700 | AG19: =M19 -> 114919900 | AH19: =AF19-AG19 -> -57671200 | AI19: Selisih di unit Qty, di catatan pak mushafa 2 unit(1 sudah terbayar , 1 unit belum terbayar ), dicatatan TARI 1 Unit
A20: 9 | B20: 5200776987 | C20: =VLOOKUP($B20,Detail!$B$4:$Q$25,2,0) -> 45877 | D20: Top Frame 800 | E20: =SUMIF(Detail!$B$4:$B$25,'Asumsi Summary V.4 (3)'!$B20,Detail!$E$4:$E$25) -> 2 | G20: =VLOOKUP($B20,Detail!$B$4:$Q$25,5,0) -> 225000000 | H20: =E20*G20 -> 450000000 | I20: =SUMIF(Detail!$B$4:$B$25,'Asumsi Summary V.4 (3)'!B20,Detail!$H$4:$H$25) -> 225000000 | J20: =(I20*20%)/E20 -> 22500000 | K20: =I20*20% -> 45000000 | M20: =SUM(K20:L20) -> 45000000 | O20: 0 | P20: 2 | U20: =SUM(N20:S20) -> 2 | V20: =E20-U20 -> 0 | W20: =J20*U20 -> 45000000 | X20: =K20-W20 -> 0 | Y20: 45923 | Z20: =Y20+7 -> 45930 | AA20: =Z20+30 -> 45960 | AB20: =Z20+60 -> 45990 | AC20: Close | AF20: =VLOOKUP(B20,investasi!$B$5:$G$18,6,0) -> 45000000 | AG20: =M20 -> 45000000 | AH20: =AF20-AG20 -> 0
A21: 10 | B21: 5200777132 | C21: =VLOOKUP($B21,Detail!$B$4:$Q$110,2,0) -> 45880 | D21: Leser Barrier MK 01-F3004973 | E21: 20 | G21: =VLOOKUP($B21,Detail!$B$4:$Q$25,5,0) -> 40457500 | H21: =E21*G21 -> 809150000 | I21: =H21*50% -> 404575000 | J21: =(I21*13%)/E21 -> 2629737.5 | K21: =I21*13% -> 52594750 | M21: =SUM(K21:L21) -> 52594750 | O21: 0 | Q21: 20 | U21: =SUM(N21:S21) -> 20 | V21: =E21-U21 -> 0 | W21: =J21*U21 -> 52594750 | X21: =K21-W21 -> 0 | Y21: 45922 | Z21: =Y21+7 -> 45929 | AA21: =Z21+30 -> 45959 | AB21: =Z21+60 -> 45989 | AC21: Close | AF21: =VLOOKUP(B21,investasi!$B$5:$G$18,6,0) -> 52594750 | AG21: =M21 -> 52594750 | AH21: =AF21-AG21 -> 0
A22: 11 | B22: =Detail!$B$45 -> 5200972695 | C22: =Detail!$C$45 -> 45891 | D22: Tangki | E22: 8 | F22: 75000000 | G22: 100500000 | H22: =E22*G22 -> 804000000 | I22: =H22*50% -> 402000000 | J22: 12750000 | K22: =E22*J22 -> 102000000 | M22: =SUM(K22:L22) -> 102000000 | O22: 0 | P22: 8 | T22: Margin was arranged 25mil/ea | U22: =SUM(N22:S22) -> 8 | V22: =E22-U22 -> 0 | W22: =J22*U22 -> 102000000 | X22: =K22-W22 -> 0 | Y22: 45925 | Z22: =Y22+7 -> 45932 | AA22: =Z22+30 -> 45962 | AB22: =Z22+60 -> 45992 | AC22: Close | AF22: =VLOOKUP(B22,investasi!$B$5:$G$18,6,0) -> 80400000 | AG22: =M22 -> 102000000 | AH22: =AF22-AG22 -> -21600000 | AI22: Selisih margin
A23: 12 | B23: =Detail!B53 -> 5200777558 | C23: 45897 | D23: Top Frame 2630 | E23: 1 | G23: =Detail!F53 -> 685000000 | H23: =E23*G23 -> 685000000 | I23: =H23*50% -> 342500000 | J23: =(I23*20%)/E23 -> 68500000 | K23: =I23*20% -> 68500000 | M23: =SUM(K23:L23) -> 68500000 | P23: 1 | U23: =SUM(N23:S23) -> 1 | V23: =E23-U23 -> 0 | W23: =J23*U23 -> 68500000 | X23: =K23-W23 -> 0 | Y23: 45923 | Z23: =Y23+7 -> 45930 | AA23: =Z23+30 -> 45960 | AB23: =Z23+60 -> 45990 | AC23: Close | AF23: =VLOOKUP(B23,investasi!$B$5:$G$18,6,0) -> 68500000 | AG23: =M23 -> 68500000 | AH23: =AF23-AG23 -> 0
A24: 13 | B24: =Detail!B54 -> 5200777559 | C24: 45901 | D24: Top Frame 800 | E24: 2 | G24: =Detail!F54 -> 225000000 | H24: =E24*G24 -> 450000000 | I24: =H24*50% -> 225000000 | J24: =(I24*20%)/E24 -> 22500000 | K24: =I24*20% -> 45000000 | M24: =SUM(K24:L24) -> 45000000 | P24: 2 | U24: =SUM(N24:S24) -> 2 | V24: =E24-U24 -> 0 | W24: =J24*U24 -> 45000000 | X24: =K24-W24 -> 0 | Y24: 45925 | Z24: =Y24+7 -> 45932 | AA24: =Z24+30 -> 45962 | AB24: =Z24+60 -> 45992 | AC24: Close | AF24: =VLOOKUP(B24,investasi!$B$5:$G$18,6,0) -> 45000000 | AG24: =M24 -> 45000000 | AH24: =AF24-AG24 -> 0
A25: 14 | B25: =Detail!$B$56 -> 5200777758 | C25: 45909 | D25: Pipe Spool | E25: 1 | G25: =Detail!F56 -> 2231048200 | H25: =E25*G25 -> 2231048200 | I25: =H25*50% -> 1115524100 | J25: =(I25*20%)/E25 -> 223104820 | K25: =I25*20% -> 223104820 | M25: =SUM(K25:L25) -> 223104820 | P25: 1 | U25: =SUM(N25:S25) -> 1 | V25: =E25-U25 -> 0 | W25: =J25*U25 -> 223104820 | X25: =K25-W25 -> 0 | Y25: 45930 | Z25: =Y25+7 -> 45937 | AA25: =Z25+30 -> 45967 | AB25: =Z25+60 -> 45997 | AC25: Close | AF25: =VLOOKUP(B25,investasi!$B$5:$G$18,6,0) -> 223104820 | AG25: =M25 -> 223104820 | AH25: =AF25-AG25 -> 0
A26: 15 | B26: =Detail!$B$58 -> 5200778319 | C26: 45909 | D26: =Detail!$D$58 -> Top Frame 800 | E26: 2 | G26: =Detail!$F$58 -> 225000000 | H26: =E26*G26 -> 450000000 | I26: =H26*50% -> 225000000 | J26: =(I26*20%)/E26 -> 22500000 | K26: =I26*20% -> 45000000 | M26: =SUM(K26:L26) -> 45000000 | P26: 2 | U26: =SUM(N26:S26) -> 2 | V26: =E26-U26 -> 0 | W26: =J26*U26 -> 45000000 | X26: =K26-W26 -> 0 | Y26: 45940 | Z26: =Y26+7 -> 45947 | AA26: =Z26+30 -> 45977 | AB26: =Z26+60 -> 46007 | AC26: Close | AF26: =VLOOKUP(B26,investasi!$B$23:$G$26,6,0) -> 45000000 | AG26: =M26 -> 45000000 | AH26: =AF26-AG26 -> 0
A27: 16 | B27: 5200778328 | C27: 45915 | D27: Top Frame 2630 | E27: 1 | G27: =Detail!F59 -> 685000000 | H27: =E27*G27 -> 685000000 | I27: =H27*50% -> 342500000 | J27: =(I27*20%)/E27 -> 68500000 | K27: =(I27*20%)+F27 -> 68500000 | L27: 66261000 | M27: =SUM(K27:L27) -> 134761000 | P27: 1 | U27: =SUM(N27:S27) -> 1 | V27: =E27-U27 -> 0 | W27: =J27*U27+L27 -> 134761000 | X27: =K27+L27-W27 -> 0 | Y27: 45940 | Z27: =Y27+7 -> 45947 | AA27: =Z27+30 -> 45977 | AB27: =Z27+60 -> 46007 | AC27: Close | AF27: =VLOOKUP(B27,investasi!$B$23:$G$26,6,0)+investasi!I24 -> 134761000 | AG27: =M27 -> 134761000 | AH27: =AF27-AG27 -> 0
U28: =SUM(N28:S28) -> 0 | AC28: Close
A29: 18 | B29: =Detail!B60 -> 5200779815 | C29: 45965 | D29: Top Frame 2630 | E29: 1 | G29: =Detail!F60 -> 685000000 | H29: =E29*G29 -> 685000000 | I29: =H29*50% -> 342500000 | J29: =(I29*20%)/E29 -> 68500000 | K29: =(I29*20%)+F29 -> 68500000 | L29: 66261000 | M29: =SUM(K29:L29) -> 134761000 | R29: 1 | U29: =SUM(N29:S29) -> 1 | V29: =E29-U29 -> 0 | W29: =J29*U29+L29 -> 134761000 | X29: =K29+L29-W29 -> 0 | Y29: 45989 | Z29: =Y29+3 -> 45992 | AA29: =Z29+30 -> 46022 | AB29: =Z29+60 -> 46052 | AC29: Delivered | AF29: =VLOOKUP(B29,investasi!$B$23:$G$26,6,0)+investasi!I26 -> 134761000 | AG29: =M29 -> 134761000 | AH29: =AF29-AG29 -> 0
A30: =A29+1 -> 19 | B30: 5200988854 | C30: 45977 | D30: Trench Grade | E30: 150 | G30: 4990500 | H30: =E30*G30 -> 748575000 | I30: =H30*50% -> 374287500 | J30: =(I30*20%)/E30 -> 499050 | K30: =(I30*20%)+F30 -> 74857500 | M30: =SUM(K30:L30) -> 74857500 | R30: 150 | U30: =SUM(N30:S30) -> 150 | V30: =E30-U30 -> 0 | W30: =J30*U30+L30 -> 74857500 | X30: =K30+L30-W30 -> 0 | Y30: 45989 | Z30: =Y30+3 -> 45992 | AA30: =Z30+30 -> 46022 | AB30: =Z30+60 -> 46052 | AC30: Delivered
A31: =A30+1 -> 20 | B31: 5200989664 | C31: 45977 | D31: Grating Ditch | E31: 100 | G31: 21100000 | H31: =E31*G31 -> 2110000000 | I31: =H31*50% -> 1055000000 | J31: =(I31*20%)/E31 -> 2110000 | K31: =(I31*20%)+F31 -> 211000000 | M31: =SUM(K31:L31) -> 211000000 | U31: =SUM(N31:S31) -> 0 | X31: =K31+L31-W31 -> 211000000 | AC31: Open
A32: =A31+1 -> 21 | B32: 5200989665 | C32: 45977 | D32: Grating Ditch | E32: 100 | G32: 21100000 | H32: =E32*G32 -> 2110000000 | I32: =H32*50% -> 1055000000 | J32: =(I32*20%)/E32 -> 2110000 | K32: =(I32*20%)+F32 -> 211000000 | M32: =SUM(K32:L32) -> 211000000 | U32: =SUM(N32:S32) -> 0 | X32: =K32+L32-W32 -> 211000000 | AC32: Open
A33: =A32+1 -> 22 | B33: 5200989666 | C33: 45977 | D33: Grating Ditch | E33: 110 | G33: 21100000 | H33: =E33*G33 -> 2321000000 | I33: =H33*50% -> 1160500000 | J33: =(I33*20%)/E33 -> 2110000 | K33: =(I33*20%)+F33 -> 232100000 | M33: =SUM(K33:L33) -> 232100000 | U33: =SUM(N33:S33) -> 0 | X33: =K33+L33-W33 -> 232100000 | AC33: Open
A34: =A33+1 -> 23 | B34: 5200992759 | C34: 45981 | D34: Tanki | E34: 6 | G34: 100500000 | H34: =E34*G34 -> 603000000 | I34: =H34*50% -> 301500000 | J34: 12750000 | K34: =J34*E34 -> 76500000 | M34: =SUM(K34:L34) -> 76500000 | U34: =SUM(N34:S34) -> 0 | X34: =K34+L34-W34 -> 76500000 | AC34: Open
A35: =A34+1 -> 24 | B35: 5200991260 | C35: 45985 | D35: Trench Grade | E35: 150 | G35: 4990500 | H35: =E35*G35 -> 748575000 | I35: =H35*50% -> 374287500 | J35: =(I35*20%)/E35 -> 499050 | K35: =(I35*20%)+F35 -> 74857500 | M35: =SUM(K35:L35) -> 74857500 | U35: =SUM(N35:S35) -> 0 | X35: =K35+L35-W35 -> 74857500 | Y35: =C35+14 -> 45999 | Z35: =Y35+7 -> 46006 | AA35: =Z35+30 -> 46036 | AB35: =Z35+60 -> 46066 | AC35: Open
A36: =A35+1 -> 25 | B36: 5200991264 | C36: 45985 | D36: Trench Grade | E36: 150 | G36: 4990500 | H36: =E36*G36 -> 748575000 | I36: =H36*50% -> 374287500 | J36: =(I36*20%)/E36 -> 499050 | K36: =(I36*20%)+F36 -> 74857500 | M36: =SUM(K36:L36) -> 74857500 | U36: =SUM(N36:S36) -> 0 | X36: =K36+L36-W36 -> 74857500 | Y36: =C36+21 -> 46006 | Z36: =Y36+7 -> 46013 | AA36: =Z36+30 -> 46043 | AB36: =Z36+60 -> 46073 | AC36: Open
A37: =A36+1 -> 26 | B37: 5200991456 | C37: 45986 | D37: Trench Grade | E37: 150 | G37: 4990500 | H37: =E37*G37 -> 748575000 | I37: =H37*50% -> 374287500 | J37: =(I37*20%)/E37 -> 499050 | K37: =(I37*20%)+F37 -> 74857500 | M37: =SUM(K37:L37) -> 74857500 | U37: =SUM(N37:S37) -> 0 | X37: =K37+L37-W37 -> 74857500 | Y37: =C37+21 -> 46007 | Z37: =Y37+7 -> 46014 | AA37: =Z37+30 -> 46044 | AB37: =Z37+60 -> 46074 | AC37: Open
A38: =A37+1 -> 27 | B38: 5200991458 | C38: 45986 | D38: Trench Grade | E38: 150 | G38: 4990500 | H38: =E38*G38 -> 748575000 | I38: =H38*50% -> 374287500 | J38: =(I38*20%)/E38 -> 499050 | K38: =(I38*20%)+F38 -> 74857500 | M38: =SUM(K38:L38) -> 74857500 | U38: =SUM(N38:S38) -> 0 | X38: =K38+L38-W38 -> 74857500 | Y38: =C38+21 -> 46007 | Z38: =Y38+7 -> 46014 | AA38: =Z38+30 -> 46044 | AB38: =Z38+60 -> 46074 | AC38: Open
A39: =A38+1 -> 28 | B39: 5200991502 | C39: 45986 | D39: Trench Grade | E39: 150 | G39: 4990500 | H39: =E39*G39 -> 748575000 | I39: =H39*50% -> 374287500 | J39: =(I39*20%)/E39 -> 499050 | K39: =(I39*20%)+F39 -> 74857500 | M39: =SUM(K39:L39) -> 74857500 | U39: =SUM(N39:S39) -> 0 | X39: =K39+L39-W39 -> 74857500 | Y39: =C39+21 -> 46007 | Z39: =Y39+7 -> 46014 | AA39: =Z39+30 -> 46044 | AB39: =Z39+60 -> 46074 | AC39: Open
A40: =A39+1 -> 29 | B40: 5200991502 | C40: 45986 | D40: Trench Grade | E40: 150 | G40: 4990500 | H40: =E40*G40 -> 748575000 | I40: =H40*50% -> 374287500 | J40: =(I40*20%)/E40 -> 499050 | K40: =(I40*20%)+F40 -> 74857500 | M40: =SUM(K40:L40) -> 74857500 | U40: =SUM(N40:S40) -> 0 | X40: =K40+L40-W40 -> 74857500 | Y40: =C40+21 -> 46007 | Z40: =Y40+7 -> 46014 | AA40: =Z40+30 -> 46044 | AB40: =Z40+60 -> 46074 | AC40: Open
A41: =A40+1 -> 30 | B41: 5200991502 | C41: 45986 | D41: Trench Grade | E41: 50 | G41: 4990500 | H41: =E41*G41 -> 249525000 | I41: =H41*50% -> 124762500 | J41: =(I41*20%)/E41 -> 499050 | K41: =(I41*20%)+F41 -> 24952500 | M41: =SUM(K41:L41) -> 24952500 | U41: =SUM(N41:S41) -> 0 | X41: =K41+L41-W41 -> 24952500 | Y41: =C41+21 -> 46007 | Z41: =Y41+7 -> 46014 | AA41: =Z41+30 -> 46044 | AB41: =Z41+60 -> 46074 | AC41: Open
B43: TOTAL MARGIN | H43: =SUM(H12:H41) -> 25081947200 | I43: =SUM(I12:I41) -> 12540973600 | K43: =SUM(K12:K41) -> 2517674470 | L43: =SUM(L12:L34) -> 132522000 | M43: =SUM(M12:M41) -> 2650196470 | W43: =SUM(W12:W40) -> 1445498970 | X43: =SUM(X12:X40) -> 1179745000
X44: =W43+X43-H56 -> 2625243970
E45: A | G45: B | H45: C | I45: D | J45: E | K45: F=A+B+C-D-E
E46: TGL | F46: Modal Setor Awal | G46: Margin | H46: Pencairan Modal | I46: Modal PO Baru | J46: Penarikan | K46: Dana Tersedia
E47: 45839 | F47: =SUM(I12:I14) -> 900000000 | G47: =SUM(W12:W14) -> 180000000 | K47: =F47+G47 -> 1080000000 | X47: =SUM(I26:I29,AG26:AG29) -> 1224522000
E48: 45870 | F48: =SUM(I15:I18) -> 1125000000 | G48: =SUM(W15:W18) -> 225000000 | I48: =SUM(I19:I22) -> 1606174500 | K48: =K47+F48+G48+H48-I48-J48 -> 823825500
E49: 45901 | F49: 1426698600 | I49: =SUM(I23:I27) -> 2250524100 | K49: =K48+F49+G49+H49-I49 -> 0
E50: 45931 | I50: =I29+I28 -> 342500000 | K50: =K49+F50+G50+H50-I50 -> -342500000
E51: 45962 | G51: =SUM(M19:M28) -> 830880470 | I51: =-SUM(I19:I28)+SUM(I30:I40) -> 2335313900 | J51: 1105000000 | K51: =K50+F51+G51+H51-I51-J51 -> -2951933430
E52: 45992 | F52: =2951933430+124762500 -> 3076695930 | G52: =SUM(M29:M41) -> 1414316000 | I52: =-SUM(I29:I40) -> -6534512500 | K52: =K51+F52+G52+H52-I52-J52 -> 8073591000
F53: =SUM(F47:F52) -> 6528394530 | G53: =SUM(G47:G52) -> 2650196470 | H53: =SUM(H47:H52) -> 0 | I53: =SUM(I47:I52) -> 0 | J53: =SUM(J47:J52) -> 1105000000 | K53: =F53+G53+H53-I53-J53 -> 8073591000
E55: Setor Modal Awal | F55: =F53 -> 6528394530 | I55: Asumsi
E56: Margin | F56: =SUM(M12:M27) -> 1235880470 | I56: Setor Modal | J56: =F53 -> 6528394530
E57: Modal PO baru | F57: =-I53 -> 0 | G57: Baris 18-29 | I57: Margin | J57: =M43 -> 2650196470
E58: Penarikan | F58: =-J51 -> -1105000000 | I58: Penarikan Margin | J58: =-J51 -> -1105000000
E59: Dana Tersedia/Kurang | F59: =F55+F56+F57+F58 -> 6659275000 | I59: Sisa | J59: =J56+J57+J58 -> 8073591000
E61: PO & margin akan cair | F61: =SUM(I29:I40,M29:M40) -> 7923876000 | G61: Baris 18-29

Sheet Summary V.4 (6)
C1: LIST INVESTASI
H7: =Detail!E2 -> 4 | J7: =Detail!F2 -> 5 | K7: =Detail!G2 -> 6 | L7: =Detail!H2 -> 7 | N7: =Detail!I2 -> 8
A10: NO | B10: Date | C10: No. PO | D10: Status | E10: Margin Diterima | F10: Modal Di terima | G10: Nama Barang | H10: =Detail!E3 -> Qty | I10: Harga Beli (only added if Margin is set) | J10: =Detail!F3 -> Harga | K10: Total PO | L10: Modal | M10: Margin Per Unit | N10: =Detail!I3 -> Margin | O10: Add Margin | P10: Total Margin | Q10: Invoice /DO | Y10: DO Total | Z10: DO Outstanding | AA10: Margin | AB10: Margin ditahan | AC10: MODAL DITAHAN | AD10: Del Time | AE10: Invoice date | AF10: adjusting TOP 30 Days | AG10: adjusting TOP 60 Days | AH10: Payment Date | AI10: Status | AJ10: Notes | AK10: Tari | AL10: Total Margin TARI | AM10: Selisih
Q11: Jul | R11: Aug | S11: Sep | T11: Oct | U11: Nov | V11: Dec | W11: Jan | X11: Add Margin (by Agreement) | AJ11: Notes
A12: 1 | B12: =VLOOKUP($C12,Detail!$B$4:$Q$21,2,0) -> 45839 | C12: 5200954145 | D12: Close | E12: =P12-AB12 -> 45000000 | F12: =L12-AC12 -> 225000000 | G12: Top Frame 800 | H12: =SUMIF(Detail!$B$4:$B$21,'Summary V.4 (6)'!$C12,Detail!$E$4:$E$21) -> 2 | J12: =VLOOKUP($C12,Detail!$B$4:$Q$21,5,0) -> 225000000 | K12: =H12*J12 -> 450000000 | L12: =SUMIF(Detail!$B$4:$B$21,'Summary V.4 (6)'!C12,Detail!$H$4:$H$21) -> 225000000 | M12: =(L12*20%)/H12 -> 22500000 | N12: =L12*20% -> 45000000 | P12: =SUM(N12:O12) -> 45000000 | Q12: =H12 -> 2 | Y12: =SUM(Q12:V12) -> 2 | Z12: =H12-Y12 -> 0 | AA12: =P12 -> 45000000 | AB12: =N12-AA12 -> 0 | AD12: 45861 | AE12: 45863 | AF12: 45894 | AI12: Close | AK12: =VLOOKUP(C12,investasi!$B$5:$G$18,6,0) -> 45000000 | AL12: =P12 -> 45000000 | AM12: =AK12-AL12 -> 0
A13: 2 | B13: =VLOOKUP($C13,Detail!$B$4:$Q$21,2,0) -> 45839 | C13: 5200954149 | D13: Close | E13: =P13-AB13 -> 67500000 | F13: =L13-AC13 -> 337500000 | G13: Top Frame 800 | H13: =SUMIF(Detail!$B$4:$B$21,'Summary V.4 (6)'!$C13,Detail!$E$4:$E$21) -> 3 | J13: =VLOOKUP($C13,Detail!$B$4:$Q$21,5,0) -> 225000000 | K13: =H13*J13 -> 675000000 | L13: =SUMIF(Detail!$B$4:$B$21,'Summary V.4 (6)'!C13,Detail!$H$4:$H$21) -> 337500000 | M13: =(L13*20%)/H13 -> 22500000 | N13: =L13*20% -> 67500000 | P13: =SUM(N13:O13) -> 67500000 | Q13: =H13 -> 3 | Y13: =SUM(Q13:V13) -> 3 | Z13: =H13-Y13 -> 0 | AA13: =P13 -> 67500000 | AB13: =N13-AA13 -> 0 | AD13: 45861 | AE13: 45863 | AF13: 45894 | AI13: Close | AK13: =VLOOKUP(C13,investasi!$B$5:$G$18,6,0) -> 67500000 | AL13: =P13 -> 67500000 | AM13: =AK13-AL13 -> 0
A14: 3 | B14: =VLOOKUP($C14,Detail!$B$4:$Q$21,2,0) -> 45839 | C14: 5200954160 | D14: Close | E14: =P14-AB14 -> 67500000 | F14: =L14-AC14 -> 337500000 | G14: Top Frame 800 | H14: =SUMIF(Detail!$B$4:$B$21,'Summary V.4 (6)'!$C14,Detail!$E$4:$E$21) -> 3 | J14: =VLOOKUP($C14,Detail!$B$4:$Q$21,5,0) -> 225000000 | K14: =H14*J14 -> 675000000 | L14: =SUMIF(Detail!$B$4:$B$21,'Summary V.4 (6)'!C14,Detail!$H$4:$H$21) -> 337500000 | M14: =(L14*20%)/H14 -> 22500000 | N14: =L14*20% -> 67500000 | P14: =SUM(N14:O14) -> 67500000 | Q14: =H14 -> 3 | Y14: =SUM(Q14:V14) -> 3 | Z14: =H14-Y14 -> 0 | AA14: =P14 -> 67500000 | AB14: =N14-AA14 -> 0 | AD14: 45861 | AE14: 45863 | AF14: 45894 | AI14: Close | AK14: =VLOOKUP(C14,investasi!$B$5:$G$18,6,0) -> 67500000 | AL14: =P14 -> 67500000 | AM14: =AK14-AL14 -> 0
A15: 4 | B15: =VLOOKUP($C15,Detail!$B$4:$Q$21,2,0) -> 45870 | C15: 5200954165 | D15: Close | E15: =P15-AB15 -> 67500000 | F15: =L15-AC15 -> 337500000 | G15: Top Frame 800 | H15: =SUMIF(Detail!$B$4:$B$21,'Summary V.4 (6)'!$C15,Detail!$E$4:$E$21) -> 3 | J15: =VLOOKUP($C15,Detail!$B$4:$Q$21,5,0) -> 225000000 | K15: =H15*J15 -> 675000000 | L15: =SUMIF(Detail!$B$4:$B$21,'Summary V.4 (6)'!C15,Detail!$H$4:$H$21) -> 337500000 | M15: =(L15*20%)/H15 -> 22500000 | N15: =L15*20% -> 67500000 | P15: =SUM(N15:O15) -> 67500000 | R15: =H15 -> 3 | Y15: =SUM(Q15:V15) -> 3 | Z15: =H15-Y15 -> 0 | AA15: =P15 -> 67500000 | AB15: =N15-AA15 -> 0 | AD15: 45868 | AE15: 45873 | AF15: 45904 | AI15: Close | AK15: =VLOOKUP(C15,investasi!$B$5:$G$18,6,0) -> 67500000 | AL15: =P15 -> 67500000 | AM15: =AK15-AL15 -> 0
A16: 5 | B16: =VLOOKUP($C16,Detail!$B$4:$Q$21,2,0) -> 45870 | C16: 5200954167 | D16: Close | E16: =P16-AB16 -> 67500000 | F16: =L16-AC16 -> 337500000 | G16: Top Frame 800 | H16: =SUMIF(Detail!$B$4:$B$21,'Summary V.4 (6)'!$C16,Detail!$E$4:$E$21) -> 3 | J16: =VLOOKUP($C16,Detail!$B$4:$Q$21,5,0) -> 225000000 | K16: =H16*J16 -> 675000000 | L16: =SUMIF(Detail!$B$4:$B$21,'Summary V.4 (6)'!C16,Detail!$H$4:$H$21) -> 337500000 | M16: =(L16*20%)/H16 -> 22500000 | N16: =L16*20% -> 67500000 | P16: =SUM(N16:O16) -> 67500000 | R16: =H16 -> 3 | Y16: =SUM(Q16:V16) -> 3 | Z16: =H16-Y16 -> 0 | AA16: =P16 -> 67500000 | AB16: =N16-AA16 -> 0 | AD16: 45868 | AE16: 45873 | AF16: 45904 | AI16: Close | AK16: =VLOOKUP(C16,investasi!$B$5:$G$18,6,0) -> 67500000 | AL16: =P16 -> 67500000 | AM16: =AK16-AL16 -> 0
A17: 6 | B17: =VLOOKUP($C17,Detail!$B$4:$Q$21,2,0) -> 45870 | C17: 5200954168 | D17: Close | E17: =P17-AB17 -> 45000000 | F17: =L17-AC17 -> 225000000 | G17: Top Frame 800 | H17: =SUMIF(Detail!$B$4:$B$21,'Summary V.4 (6)'!$C17,Detail!$E$4:$E$21) -> 2 | J17: =VLOOKUP($C17,Detail!$B$4:$Q$21,5,0) -> 225000000 | K17: =H17*J17 -> 450000000 | L17: =SUMIF(Detail!$B$4:$B$21,'Summary V.4 (6)'!C17,Detail!$H$4:$H$21) -> 225000000 | M17: =(L17*20%)/H17 -> 22500000 | N17: =L17*20% -> 45000000 | P17: =SUM(N17:O17) -> 45000000 | R17: =H17 -> 2 | Y17: =SUM(Q17:V17) -> 2 | Z17: =H17-Y17 -> 0 | AA17: =P17 -> 45000000 | AB17: =N17-AA17 -> 0 | AD17: 45868 | AE17: 45873 | AF17: 45904 | AI17: Close | AK17: =VLOOKUP(C17,investasi!$B$5:$G$18,6,0) -> 45000000 | AL17: =P17 -> 45000000 | AM17: =AK17-AL17 -> 0
A18: 7 | B18: =VLOOKUP($C18,Detail!$B$4:$Q$21,2,0) -> 45870 | C18: 5200954169 | D18: Close | E18: =P18-AB18 -> 45000000 | F18: =L18-AC18 -> 225000000 | G18: Top Frame 800 | H18: =SUMIF(Detail!$B$4:$B$21,'Summary V.4 (6)'!$C18,Detail!$E$4:$E$21) -> 2 | J18: =VLOOKUP($C18,Detail!$B$4:$Q$21,5,0) -> 225000000 | K18: =H18*J18 -> 450000000 | L18: =SUMIF(Detail!$B$4:$B$21,'Summary V.4 (6)'!C18,Detail!$H$4:$H$21) -> 225000000 | M18: =(L18*20%)/H18 -> 22500000 | N18: =L18*20% -> 45000000 | P18: =SUM(N18:O18) -> 45000000 | R18: =H18 -> 2 | Y18: =SUM(Q18:V18) -> 2 | Z18: =H18-Y18 -> 0 | AA18: =P18 -> 45000000 | AB18: =N18-AA18 -> 0 | AD18: 45868 | AE18: 45873 | AF18: 45904 | AI18: Close | AK18: =VLOOKUP(C18,investasi!$B$5:$G$18,6,0) -> 45000000 | AL18: =P18 -> 45000000 | AM18: =AK18-AL18 -> 0
A19: 8 | B19: =VLOOKUP($C19,Detail!$B$4:$Q$25,2,0) -> 45877 | C19: 5200777098 | D19: Close | E19: =P19-AB19 -> 114919900 | F19: =L19-AC19 -> 574599500 | G19: DVAR 3771-B0-20D-PPC Statcom Steel Support | H19: =SUMIF(Detail!$B$4:$B$25,'Summary V.4 (6)'!$C19,Detail!$E$4:$E$25) -> 1 | J19: =VLOOKUP($C19,Detail!$B$4:$Q$25,5,0) -> 1149199000 | K19: =H19*J19 -> 1149199000 | L19: =SUMIF(Detail!$B$4:$B$25,'Summary V.4 (6)'!C19,Detail!$H$4:$H$25) -> 574599500 | M19: =(L19*20%)/H19 -> 114919900 | N19: =L19*20% -> 114919900 | P19: =SUM(N19:O19) -> 114919900 | R19: 0 | S19: 1 | Y19: =SUM(Q19:V19) -> 1 | Z19: =H19-Y19 -> 0 | AA19: =P19 -> 114919900 | AB19: =N19-AA19 -> 0 | AD19: 45930 | AE19: =AD19+7 -> 45937 | AF19: =AE19+30 -> 45967 | AG19: =AE19+60 -> 45997 | AI19: Close | AK19: =VLOOKUP(C19,investasi!$B$5:$G$18,6,0) -> 57248700 | AL19: =P19 -> 114919900 | AM19: =AK19-AL19 -> -57671200 | AN19: Selisih di unit Qty, di catatan pak mushafa 2 unit(1 sudah terbayar , 1 unit belum terbayar ), dicatatan TARI 1 Unit
A20: 9 | B20: =VLOOKUP($C20,Detail!$B$4:$Q$25,2,0) -> 45877 | C20: 5200776987 | D20: Close | E20: =P20-AB20 -> 45000000 | F20: =L20-AC20 -> 225000000 | G20: Top Frame 800 | H20: =SUMIF(Detail!$B$4:$B$25,'Summary V.4 (6)'!$C20,Detail!$E$4:$E$25) -> 2 | J20: =VLOOKUP($C20,Detail!$B$4:$Q$25,5,0) -> 225000000 | K20: =H20*J20 -> 450000000 | L20: =SUMIF(Detail!$B$4:$B$25,'Summary V.4 (6)'!C20,Detail!$H$4:$H$25) -> 225000000 | M20: =(L20*20%)/H20 -> 22500000 | N20: =L20*20% -> 45000000 | P20: =SUM(N20:O20) -> 45000000 | R20: 0 | S20: 2 | Y20: =SUM(Q20:V20) -> 2 | Z20: =H20-Y20 -> 0 | AA20: =P20 -> 45000000 | AB20: =N20-AA20 -> 0 | AD20: 45923 | AE20: =AD20+7 -> 45930 | AF20: =AE20+30 -> 45960 | AG20: =AE20+60 -> 45990 | AI20: Close | AK20: =VLOOKUP(C20,investasi!$B$5:$G$18,6,0) -> 45000000 | AL20: =P20 -> 45000000 | AM20: =AK20-AL20 -> 0
A21: 10 | B21: =VLOOKUP($C21,Detail!$B$4:$Q$110,2,0) -> 45880 | C21: 5200777132 | D21: Close | E21: =P21-AB21 -> 52594750 | F21: =L21-AC21 -> 404575000 | G21: Leser Barrier MK 01-F3004973 | H21: 20 | J21: =VLOOKUP($C21,Detail!$B$4:$Q$25,5,0) -> 40457500 | K21: =H21*J21 -> 809150000 | L21: =K21*50% -> 404575000 | M21: =(L21*13%)/H21 -> 2629737.5 | N21: =L21*13% -> 52594750 | P21: =SUM(N21:O21) -> 52594750 | R21: 0 | T21: 20 | Y21: =SUM(Q21:V21) -> 20 | Z21: =H21-Y21 -> 0 | AA21: =P21 -> 52594750 | AB21: =N21-AA21 -> 0 | AD21: 45922 | AE21: =AD21+7 -> 45929 | AF21: =AE21+30 -> 45959 | AG21: =AE21+60 -> 45989 | AI21: Close | AK21: =VLOOKUP(C21,investasi!$B$5:$G$18,6,0) -> 52594750 | AL21: =P21 -> 52594750 | AM21: =AK21-AL21 -> 0
A22: 11 | B22: =Detail!$C$45 -> 45891 | C22: =Detail!$B$45 -> 5200972695 | D22: Close | E22: =P22-AB22 -> 102000000 | F22: =L22-AC22 -> 402000000 | G22: Tangki | H22: 8 | I22: 75000000 | J22: 100500000 | K22: =H22*J22 -> 804000000 | L22: =K22*50% -> 402000000 | M22: 12750000 | N22: =H22*M22 -> 102000000 | P22: =SUM(N22:O22) -> 102000000 | R22: 0 | S22: 8 | X22: Margin was arranged 25mil/ea | Y22: =SUM(Q22:V22) -> 8 | Z22: =H22-Y22 -> 0 | AA22: =P22 -> 102000000 | AB22: =N22-AA22 -> 0 | AD22: 45925 | AE22: =AD22+7 -> 45932 | AF22: =AE22+30 -> 45962 | AG22: =AE22+60 -> 45992 | AI22: Close | AK22: =VLOOKUP(C22,investasi!$B$5:$G$18,6,0) -> 80400000 | AL22: =P22 -> 102000000 | AM22: =AK22-AL22 -> -21600000 | AN22: Selisih margin | AP22: 21600000
A23: 12 | B23: 45897 | C23: =Detail!B53 -> 5200777558 | D23: Close | E23: =P23-AB23 -> 68500000 | F23: =L23-AC23 -> 342500000 | G23: Top Frame 2630 | H23: 1 | J23: =Detail!F53 -> 685000000 | K23: =H23*J23 -> 685000000 | L23: =K23*50% -> 342500000 | M23: =(L23*20%)/H23 -> 68500000 | N23: =L23*20% -> 68500000 | P23: =SUM(N23:O23) -> 68500000 | S23: 1 | Y23: =SUM(Q23:V23) -> 1 | Z23: =H23-Y23 -> 0 | AA23: =P23 -> 68500000 | AB23: =N23-AA23 -> 0 | AD23: 45923 | AE23: =AD23+7 -> 45930 | AF23: =AE23+30 -> 45960 | AG23: =AE23+60 -> 45990 | AI23: Close | AK23: =VLOOKUP(C23,investasi!$B$5:$G$18,6,0) -> 68500000 | AL23: =P23 -> 68500000 | AM23: =AK23-AL23 -> 0
A24: 13 | B24: 45901 | C24: =Detail!B54 -> 5200777559 | D24: Close | E24: =P24-AB24 -> 45000000 | F24: =L24-AC24 -> 225000000 | G24: Top Frame 800 | H24: 2 | J24: =Detail!F54 -> 225000000 | K24: =H24*J24 -> 450000000 | L24: =K24*50% -> 225000000 | M24: =(L24*20%)/H24 -> 22500000 | N24: =L24*20% -> 45000000 | P24: =SUM(N24:O24) -> 45000000 | S24: 2 | Y24: =SUM(Q24:V24) -> 2 | Z24: =H24-Y24 -> 0 | AA24: =P24 -> 45000000 | AB24: =N24-AA24 -> 0 | AD24: 45925 | AE24: =AD24+7 -> 45932 | AF24: =AE24+30 -> 45962 | AG24: =AE24+60 -> 45992 | AI24: Close | AK24: =VLOOKUP(C24,investasi!$B$5:$G$18,6,0) -> 45000000 | AL24: =P24 -> 45000000 | AM24: =AK24-AL24 -> 0
A25: 14 | B25: 45909 | C25: =Detail!$B$56 -> 5200777758 | D25: Close | E25: =P25-AB25 -> 223104820 | F25: =L25-AC25 -> 1115524100 | G25: Pipe Spool | H25: 1 | J25: =Detail!F56 -> 2231048200 | K25: =H25*J25 -> 2231048200 | L25: =K25*50% -> 1115524100 | M25: =(L25*20%)/H25 -> 223104820 | N25: =L25*20% -> 223104820 | P25: =SUM(N25:O25) -> 223104820 | S25: 1 | Y25: =SUM(Q25:V25) -> 1 | Z25: =H25-Y25 -> 0 | AA25: =P25 -> 223104820 | AB25: =N25-AA25 -> 0 | AD25: 45930 | AE25: =AD25+7 -> 45937 | AF25: =AE25+30 -> 45967 | AG25: =AE25+60 -> 45997 | AI25: Close | AK25: =VLOOKUP(C25,investasi!$B$5:$G$18,6,0) -> 223104820 | AL25: =P25 -> 223104820 | AM25: =AK25-AL25 -> 0
A26: 15 | B26: 45909 | C26: =Detail!$B$58 -> 5200778319 | D26: Close | E26: =P26-AB26 -> 45000000 | F26: =L26-AC26 -> 225000000 | G26: =Detail!$D$58 -> Top Frame 800 | H26: 2 | J26: =Detail!$F$58 -> 225000000 | K26: =H26*J26 -> 450000000 | L26: =K26*50% -> 225000000 | M26: =(L26*20%)/H26 -> 22500000 | N26: =L26*20% -> 45000000 | P26: =SUM(N26:O26) -> 45000000 | S26: 2 | Y26: =SUM(Q26:V26) -> 2 | Z26: =H26-Y26 -> 0 | AA26: =P26 -> 45000000 | AB26: =N26-AA26 -> 0 | AD26: 45940 | AE26: =AD26+7 -> 45947 | AF26: =AE26+30 -> 45977 | AG26: =AE26+60 -> 46007 | AI26: Close | AK26: =VLOOKUP(C26,investasi!$B$23:$G$26,6,0) -> 45000000 | AL26: =P26 -> 45000000 | AM26: =AK26-AL26 -> 0
A27: 16 | B27: 45915 | C27: 5200778328 | D27: Close | E27: =P27-AB27 -> 134761000 | F27: =L27-AC27 -> 342500000 | G27: Top Frame 2630 | H27: 1 | J27: =Detail!F59 -> 685000000 | K27: =H27*J27 -> 685000000 | L27: =K27*50% -> 342500000 | M27: =(L27*20%)/H27 -> 68500000 | N27: =(L27*20%)+I27 -> 68500000 | O27: 66261000 | P27: =SUM(N27:O27) -> 134761000 | S27: 1 | Y27: =SUM(Q27:V27) -> 1 | Z27: =H27-Y27 -> 0 | AA27: =P27 -> 134761000 | AB27: =N27+O27-AA27 -> 0 | AD27: 45940 | AE27: =AD27+7 -> 45947 | AF27: =AE27+30 -> 45977 | AG27: =AE27+60 -> 46007 | AI27: Close | AK27: =VLOOKUP(C27,investasi!$B$23:$G$26,6,0)+investasi!I24 -> 134761000 | AL27: =P27 -> 134761000 | AM27: =AK27-AL27 -> 0
D28: Close | E28: =P28-AB28 -> 0 | F28: =L28-AC28 -> 0 | Y28: =SUM(Q28:V28) -> 0 | AA28: =P28 -> 0 | AI28: Close
A29: 18 | B29: 45965 | C29: =Detail!B60 -> 5200779815 | D29: Close | E29: =P29-AB29 -> 134761000 | F29: =L29-AC29 -> 342500000 | G29: Top Frame 2630 | H29: 1 | J29: =Detail!F60 -> 685000000 | K29: =H29*J29 -> 685000000 | L29: =K29*50% -> 342500000 | M29: =(L29*20%)/H29 -> 68500000 | N29: =(L29*20%)+I29 -> 68500000 | O29: 66261000 | P29: =SUM(N29:O29) -> 134761000 | U29: 1 | Y29: =SUM(Q29:V29) -> 1 | Z29: =H29-Y29 -> 0 | AA29: =P29 -> 134761000 | AB29: =N29+O29-AA29 -> 0 | AD29: 45989 | AE29: 46008 | AF29: 46034 | AG29: =AE29+30 -> 46038 | AH29: 46034 | AI29: Close | AJ29: Payment 12 Jan 2026 | AK29: =VLOOKUP(C29,investasi!$B$23:$G$26,6,0)+investasi!I26 -> 134761000 | AL29: =P29 -> 134761000 | AM29: =AK29-AL29 -> 0
A30: =A29+1 -> 19 | B30: 45977 | C30: 5200988854 | D30: Close | E30: =P30-AB30 -> 74857500 | F30: =L30-AC30 -> 374287500 | G30: Trench Grade | H30: 150 | J30: 4990500 | K30: =H30*J30 -> 748575000 | L30: =K30*50% -> 374287500 | M30: =(L30*20%)/H30 -> 499050 | N30: =(L30*20%)+I30 -> 74857500 | P30: =SUM(N30:O30) -> 74857500 | U30: 150 | Y30: =SUM(Q30:V30) -> 150 | Z30: =H30-Y30 -> 0 | AA30: =P30 -> 74857500 | AB30: =N30+O30-AA30 -> 0 | AD30: 45989 | AE30: 46008 | AF30: 46034 | AG30: =AE30+30 -> 46038 | AH30: 46034 | AI30: Close | AJ30: Payment 12 Jan 2026 | AN30: Tanki
A31: =A30+1 -> 20 | B31: 45977 | C31: 5200989664 | D31: Close | E31: =P31-AB31 -> 0 | F31: =L31-AC31 -> 0 | G31: Grating Ditch | H31: 50 | J31: 21100000 | K31: =H31*J31 -> 1055000000 | L31: =K31*50% -> 527500000 | M31: =(L31*20%)/H31 -> 2110000 | N31: =(L31*20%) -> 105500000 | P31: =SUM(N31:O31) -> 105500000 | V31: 50 | Y31: =SUM(Q31:V31) -> 50 | Z31: =H31-Y31 -> 0 | AA31: =P31 -> 105500000 | AB31: =AA31 -> 105500000 | AC31: =L31 -> 527500000 | AD31: 46031 | AE31: 46031 | AF31: =AD31+30 -> 46061 | AI31: Delivered
D32: Open | E32: =P32-AB32 -> 0 | F32: =L32-AC32 -> 0 | G32: Grating Ditch | H32: 50 | J32: 21100000 | K32: =H32*J32 -> 1055000000 | L32: =K32*50% -> 527500000 | M32: =(L32*20%)/H32 -> 2110000 | N32: =(L32*20%)+I32 -> 105500000 | P32: =SUM(N32:O32) -> 105500000 | W32: 50 | Y32: =SUM(Q32:V32) -> 0 | Z32: =H32-Y32 -> 50 | AA32: =P32 -> 105500000 | AB32: =AA32 -> 105500000 | AC32: =L32 -> 527500000 | AD32: 46031 | AE32: 46031 | AF32: =AD32+30 -> 46061 | AI32: Delivered
A33: =A31+1 -> 21 | B33: 45977 | C33: 5200989665 | D33: Delivered | E33: =P33-AB33 -> 0 | F33: =L33-AC33 -> 0 | G33: Grating Ditch | H33: 50 | J33: 21100000 | K33: =H33*J33 -> 1055000000 | L33: =K33*50% -> 527500000 | M33: =(L33*20%)/H33 -> 2110000 | N33: =(L33*20%)+I33 -> 105500000 | P33: =SUM(N33:O33) -> 105500000 | W33: 50 | Y33: =SUM(Q33:W33) -> 50 | Z33: =H33-Y33 -> 0 | AA33: =P33 -> 105500000 | AB33: =AA33 -> 105500000 | AC33: =L33 -> 527500000 | AD33: 46030 | AE33: 46030 | AF33: =AD33+30 -> 46060 | AI33: Delivered
A34: =A32+1 -> 1 | B34: 45977 | C34: 5200989665 | D34: Delivered | E34: =P34-AB34 -> 0 | F34: =L34-AC34 -> 527500000 | G34: Grating Ditch | H34: 50 | J34: 21100000 | K34: =H34*J34 -> 1055000000 | L34: =K34*50% -> 527500000 | M34: =(L34*20%)/H34 -> 2110000 | N34: =(L34*20%)+I34 -> 105500000 | P34: =SUM(N34:O34) -> 105500000 | Y34: =SUM(Q34:W34) -> 0 | Z34: =H34-Y34 -> 50 | AA34: =P34 -> 105500000 | AB34: =AA34 -> 105500000 | AD34: 46030 | AE34: 46030 | AF34: =AD34+30 -> 46060 | AI34: Delivered
A35: =A33+1 -> 22 | B35: 45977 | C35: 5200989666 | D35: Close | E35: =P35-AB35 -> 232100000 | F35: =L35-AC35 -> 1160500000 | G35: Grating Ditch | H35: 110 | J35: 21100000 | K35: =H35*J35 -> 2321000000 | L35: =K35*50% -> 1160500000 | M35: =(L35*20%)/H35 -> 2110000 | N35: =(L35*20%)+I35 -> 232100000 | P35: =SUM(N35:O35) -> 232100000 | W35: 110 | Y35: =SUM(Q35:W35) -> 110 | Z35: 0 | AA35: =P35 -> 232100000 | AD35: 46027 | AE35: 45676 | AF35: =AE35+30 -> 45706 | AI35: Delivered | AJ35: Partial Deliv 55 ea
A36: =A35+1 -> 23 | B36: 45981 | C36: 5200992759 | D36: Open | E36: =P36-AB36 -> 0 | F36: =L36-AC36 -> 0 | G36: Tanki | H36: 6 | J36: 100500000 | K36: =H36*J36 -> 603000000 | L36: =K36*50% -> 301500000 | M36: 10050000 | N36: =M36*H36 -> 60300000 | P36: =SUM(N36:O36) -> 60300000 | W36: 6 | Y36: =SUM(Q36:W36) -> 6 | Z36: =H36-Y36 -> 0 | AA36: =P36 -> 60300000 | AB36: =AA36 -> 60300000 | AC36: =L36 -> 301500000 | AD36: 46048 | AE36: 46048 | AF36: =AE36+30 -> 46078 | AI36: Delivered | AJ36: ada kenaikan harga material
A37: =A36+1 -> 24 | B37: 45985 | C37: 5200991260 | D37: Open | E37: =P37-AB37 -> 0 | F37: =L37-AC37 -> 0 | G37: Trench Grade | H37: 150 | J37: 4990500 | K37: =H37*J37 -> 748575000 | L37: =K37*50% -> 374287500 | M37: =(L37*20%)/H37 -> 499050 | N37: =(L37*20%)+I37 -> 74857500 | P37: =SUM(N37:O37) -> 74857500 | W37: =H37 -> 150 | Y37: =SUM(Q37:W37) -> 150 | Z37: =H37-Y37 -> 0 | AA37: =P37 -> 74857500 | AB37: =AA37 -> 74857500 | AC37: =L37 -> 374287500 | AD37: 46041 | AE37: 46041 | AG37: =AD37+60 -> 46101 | AI37: Delivered | AJ37: Terkirim
A38: =A37+1 -> 25 | B38: 45985 | C38: 5200991264 | D38: Open | E38: =P38-AB38 -> 0 | F38: =L38-AC38 -> 0 | G38: Trench Grade | H38: 150 | J38: 4990500 | K38: =H38*J38 -> 748575000 | L38: =K38*50% -> 374287500 | M38: =(L38*20%)/H38 -> 499050 | N38: =(L38*20%)+I38 -> 74857500 | P38: =SUM(N38:O38) -> 74857500 | W38: =H38 -> 150 | Y38: =SUM(Q38:W38) -> 150 | Z38: =H38-Y38 -> 0 | AA38: =P38 -> 74857500 | AB38: =AA38 -> 74857500 | AC38: =L38 -> 374287500 | AD38: 46041 | AE38: 46041 | AG38: =AD38+60 -> 46101 | AI38: Delivered | AJ38: Terkirim
A39: =A38+1 -> 26 | B39: 45986 | C39: 5200991456 | D39: Open | E39: =P39-AB39 -> 0 | F39: =L39-AC39 -> 0 | G39: Trench Grade | H39: 150 | J39: 4990500 | K39: =H39*J39 -> 748575000 | L39: =K39*50% -> 374287500 | M39: =(L39*20%)/H39 -> 499050 | N39: =(L39*20%)+I39 -> 74857500 | P39: =SUM(N39:O39) -> 74857500 | V39: =H39 -> 150 | Y39: =SUM(Q39:V39) -> 150 | Z39: =H39-Y39 -> 0 | AA39: =P39 -> 74857500 | AB39: =AA39 -> 74857500 | AC39: =L39 -> 374287500 | AD39: 46036 | AE39: 46036 | AG39: =AD39+60 -> 46096 | AI39: Delivered
A40: =A39+1 -> 27 | B40: 45986 | C40: 5200991458 | D40: Open | E40: =P40-AB40 -> 0 | F40: =L40-AC40 -> 0 | G40: Trench Grade | H40: 150 | J40: 4990500 | K40: =H40*J40 -> 748575000 | L40: =K40*50% -> 374287500 | M40: =(L40*20%)/H40 -> 499050 | N40: =(L40*20%)+I40 -> 74857500 | P40: =SUM(N40:O40) -> 74857500 | V40: =H40 -> 150 | Y40: =SUM(Q40:V40) -> 150 | Z40: =H40-Y40 -> 0 | AA40: =P40 -> 74857500 | AB40: =AA40 -> 74857500 | AC40: =L40 -> 374287500 | AD40: 46036 | AE40: 46036 | AG40: =AD40+60 -> 46096 | AI40: Delivered
A41: =A40+1 -> 28 | B41: 45986 | C41: 5200991502 | D41: Open | E41: =P41-AB41 -> 0 | F41: =L41-AC41 -> 0 | G41: Trench Grade | H41: 150 | J41: 4990500 | K41: =H41*J41 -> 748575000 | L41: =K41*50% -> 374287500 | M41: =(L41*20%)/H41 -> 499050 | N41: =(L41*20%)+I41 -> 74857500 | P41: =SUM(N41:O41) -> 74857500 | V41: =H41 -> 150 | Y41: =SUM(Q41:V41) -> 150 | Z41: =H41-Y41 -> 0 | AA41: =P41 -> 74857500 | AB41: =AA41 -> 74857500 | AC41: =L41 -> 374287500 | AD41: 46030 | AE41: 46030 | AG41: =AD41+60 -> 46090 | AI41: Delivered
A42: =A41+1 -> 29 | B42: 45986 | C42: 5200991503 | D42: Open | E42: =P42-AB42 -> 0 | F42: =L42-AC42 -> 0 | G42: Trench Grade | H42: 150 | J42: 4990500 | K42: =H42*J42 -> 748575000 | L42: =K42*50% -> 374287500 | M42: =(L42*20%)/H42 -> 499050 | N42: =(L42*20%)+I42 -> 74857500 | P42: =SUM(N42:O42) -> 74857500 | V42: =H42 -> 150 | Y42: =SUM(Q42:V42) -> 150 | Z42: =H42-Y42 -> 0 | AA42: =P42 -> 74857500 | AB42: =AA42 -> 74857500 | AC42: =L42 -> 374287500 | AD42: 46030 | AE42: 46030 | AG42: =AD42+60 -> 46090 | AI42: Delivered
A43: =A42+1 -> 30 | B43: 46372 | C43: 5200991553 | D43: Open | E43: =P43-AB43 -> 0 | F43: =L43-AC43 -> 0 | G43: Trench Grade | H43: 50 | J43: 4990500 | K43: =H43*J43 -> 249525000 | L43: =K43*50% -> 124762500 | M43: =(L43*20%)/H43 -> 499050 | N43: =(L43*20%)+I43 -> 24952500 | P43: =SUM(N43:O43) -> 24952500 | V43: =H43 -> 50 | Y43: =SUM(Q43:V43) -> 50 | Z43: =H43-Y43 -> 0 | AA43: =P43 -> 24952500 | AB43: =AA43 -> 24952500 | AC43: =L43 -> 124762500 | AD43: 46036 | AE43: 46036 | AG43: =AD43+60 -> 46096 | AI43: Delivered
A44: =A43+1 -> 31 | B44: 46021 | C44: 5200996833 | D44: Open | E44: =P44-AB44 -> 0 | F44: =L44-AC44 -> 0 | G44: new barge landing facility | H44: 1 | J44: 1188000000 | K44: 1188925400 | L44: =K44*50% -> 594462700 | M44: =(L44*20%)/H44 -> 118892540 | N44: =(L44*20%)+I44 -> 118892540 | P44: =SUM(N44:O44) -> 118892540 | Y44: 0 | Z44: 0 | AA44: =P44 -> 118892540 | AB44: =AA44 -> 118892540 | AC44: =L44 -> 594462700 | AI44: Open | AJ44: Blm Terkirim
B45: 46044 | C45: 5201004137 | D45: Open | G45: Marine Maintenance Jetty | H45: 1 | J45: 926640000 | K45: =H45*J45 -> 926640000 | L45: =K45*50% -> 463320000 | M45: =L45*20% -> 92664000 | N45: =(L45*20%)+I45 -> 92664000 | P45: =SUM(N45:O45) -> 92664000 | Y45: 0 | Z45: 0 | AB45: =N45+O45-AA45 -> 92664000 | AC45: =L45 -> 463320000 | AI45: Open | AJ45: Blm Terkirim
B46: 46045 | C46: 5201004344 | D46: Open | G46: Trench Grade | H46: 50 | J46: =249525000/H46 -> 4990500 | K46: =H46*J46 -> 249525000 | L46: =K46*50% -> 124762500 | M46: =(L46/H46)*20% -> 499050 | N46: =(L46*20%)+I46 -> 24952500 | P46: =SUM(N46:O46) -> 24952500 | Y46: 0 | Z46: 0 | AA46: 0 | AB46: =N46+O46-AA46 -> 24952500 | AC46: =L46 -> 124762500 | AI46: Open | AJ46: Blm Terkirim
B47: 46051 | C47: 5201005549 | D47: Open | G47: Top Frame 800 | H47: 2 | J47: 225000000 | K47: =H47*J47 -> 450000000 | L47: =K47*50% -> 225000000 | M47: =(L47/H47)*20% -> 22500000 | N47: =M47*H47 -> 45000000 | P47: =SUM(N47:O47) -> 45000000 | Y47: 0 | Z47: 0 | AA47: 0 | AB47: =N47+O47-AA47 -> 45000000 | AC47: =L47 -> 225000000 | AJ47: Blm Terkirim
B48: 46051 | C48: 5201005550 | D48: Open | G48: Top Frame 800 | H48: 2 | J48: 225000000 | K48: =H48*J48 -> 450000000 | L48: =K48*50% -> 225000000 | M48: =(L48/H48)*20% -> 22500000 | N48: =M48*H48 -> 45000000 | P48: =SUM(N48:O48) -> 45000000 | Y48: 0 | Z48: 0 | AA48: 0 | AB48: =N48+O48-AA48 -> 45000000 | AC48: =L48 -> 225000000 | AJ48: Blm Terkirim
B49: 46051 | C49: 5201005551 | D49: Open | G49: Muck Bumper | H49: 16 | J49: 37000000 | K49: =H49*J49 -> 592000000 | L49: =K49*50% -> 296000000 | M49: =(L49/H49)*20% -> 3700000 | N49: =L49*20% -> 59200000 | P49: =SUM(N49:O49) -> 59200000 | Y49: 0 | Z49: 0 | AA49: 0 | AB49: =N49+O49-AA49 -> 59200000 | AC49: =L49 -> 296000000 | AJ49: Blm Terkirim
B50: 46051 | C50: 5201005552 | D50: Open | G50: Muck Bumper | H50: 16 | J50: 37000000 | K50: =H50*J50 -> 592000000 | L50: =K50*50% -> 296000000 | M50: =(L50/H50)*20% -> 3700000 | N50: =L50*20% -> 59200000 | P50: =SUM(N50:O50) -> 59200000 | Y50: 0 | Z50: 0 | AA50: 0 | AB50: =N50+O50-AA50 -> 59200000 | AC50: =L50 -> 296000000 | AJ50: Blm Terkirim
B51: 46056 | C51: 52010xxxx1 | D51: Open | G51: Muck Bumper | H51: 16 | J51: 37000000 | K51: =H51*J51 -> 592000000 | L51: =K51*50% -> 296000000 | M51: =(L51/H51)*20% -> 3700000 | N51: =L51*20% -> 59200000 | P51: =SUM(N51:O51) -> 59200000 | Y51: 0 | Z51: 0 | AA51: 0 | AB51: =N51+O51-AA51 -> 59200000 | AC51: =L51 -> 296000000 | AJ51: Blm Terkirim
B52: 46056 | C52: 52010xxxx2 | D52: Open | G52: Muck Bumper | H52: 16 | J52: 37000000 | K52: =H52*J52 -> 592000000 | L52: =K52*50% -> 296000000 | M52: =(L52/H52)*20% -> 3700000 | N52: =L52*20% -> 59200000 | P52: =SUM(N52:O52) -> 59200000 | Y52: 0 | Z52: 0 | AA52: 0 | AB52: =N52+O52-AA52 -> 59200000 | AC52: =L52 -> 296000000 | AJ52: Blm Terkirim
B53: 46056 | C53: 52010xxxx3 | D53: Open | G53: Grizzly Cover | H53: 10 | J53: 72000000 | K53: =H53*J53 -> 720000000 | L53: =K53*50% -> 360000000 | M53: =(L53/H53)*20% -> 7200000 | N53: =L53*20% -> 72000000 | P53: =SUM(N53:O53) -> 72000000 | AC53: =L53 -> 360000000 | AJ53: Blm Terkirim
C57: TOTAL MARGIN | E57: =SUM(E12:E45) -> 1677598970 | F57: =SUM(F12:F45) -> 8286486100 | K57: =SUM(K12:K45) -> 27197512600 | L57: =SUM(L12:L45) -> 13598756300 | N57: =SUM(N12:N45) -> 2713031010 | O57: =SUM(O12:O45) -> 132522000 | P57: =SUM(P12:P45) -> 2845553010 | AA57: =SUM(AA12:AA45) -> 2752889010 | AB57: =SUM(AB12:AB44) -> 1075290040 | AC57: =SUM(AC12:AC50) -> 6479032700
H59: A | J59: B | K59: C | L59: D | M59: E | N59: F=A+B+C-D-E | AC59: 6354270200
H60: TGL | I60: Modal Setor Awal | J60: Modal PO Baru | K60: Margin | L60: Pencairan Modal | M60: Penarikan | N60: Dana Tersedia | AC60: =AC57-AC59 -> 124762500
B61: Total Tf Investasi | C61: =SUM(I77) -> 6401698600 | H61: 45839 | I61: =SUM(L12:L14) -> 900000000 | K61: =SUM(AA12:AA14) -> 180000000 | N61: =I61+K61 -> 1080000000
B62: Investasi yang ditahan | C62: =AC57 -> 6479032700 | H62: 45870 | I62: =SUM(L15:L18) -> 1125000000 | J62: =SUM(L19:L22) -> 1606174500 | K62: =SUM(AA15:AA18) -> 225000000 | N62: =N61+I62+K62+L62-J62-M62 -> 823825500
B63: Total Investasi transfer | C63: =C61-C62 -> -77334100 | H63: 45901 | I63: 1426698600 | J63: =SUM(L23:L27) -> 2250524100 | N63: =N62+I63+K63+L63-J63 -> 0
H64: 45931 | J64: =L29+L28 -> 342500000 | N64: =N63+I64+K64+L64-J64 -> -342500000
B65: Total Margin | C65: =SUM(P12:P44) -> 2752889010 | H65: 45962 | J65: =-SUM(L19:L28)+SUM(L30:L42) -> 2335313900 | K65: =SUM(AA19:AA28) -> 830880470 | M65: 1105000000 | N65: =N64+I65+K65+L65-J65-M65 -> -2951933430
B66: Margin Diterima | C66: =M65 -> 1105000000 | H66: 46007 | I66: 1300000000 | J66: =L43+L44+L45 -> 1182545200 | N66: =N65+I66+K66+L66-J66-M66 -> -2834478630
B67: Sisa | C67: =C65-C66 -> 1647889010 | D67: =C65-C68 -> 1677598970 | H67: 46014 | I67: 250000000 | N67: =N66+I67+K67+L67-J67-M67 -> -2584478630
B68: Margin Ditahan | C68: =SUM(AB29:AB44) -> 1075290040 | H68: 46015 | I68: 250000000 | N68: =N67+I68+K68+L68-J68-M68 -> -2334478630
B69: Margin Tersedia | C69: =C67-C68 -> 572598970 | H69: 46016 | I69: 250000000 | N69: =N68+I69+K69+L69-J69-M69 -> -2084478630
B70: Total dana Transfer | C70: =C63+C69 -> 495264870 | H70: 46017 | I70: 250000000 | N70: =N69+I70+K70+L70-J70-M70 -> -1834478630
H71: 46018 | I71: 250000000 | N71: =N70+I71+K71+L71-J71-M71 -> -1584478630
H72: 46019 | I72: 250000000 | N72: =N71+I72+K72+L72-J72-M72 -> -1334478630
H73: 46020 | I73: 150000000 | N73: =N72+I73+K73+L73-J73-M73 -> -1184478630
H74: 46034 | J74: =-SUM(L29:L30,L34:L35) -> -2404787500 | K74: =SUM(AA29:AA30) -> 209618500 | N74: =N73+I74+K74+L74-J74-M74 -> 1429927370
H75: 46045 | J75: =SUM(L46:L50) -> 1166762500 | N75: =N74+I75+K75+L75-J75-M75 -> 263164870
H76: 46056 | K76: =SUM(AA35) -> 232100000 | M76: 495264870 | N76: =N75+I76+K76+L76-J76-M76 -> 0
I77: =SUM(I61:I75) -> 6401698600 | J77: =SUM(J61:J75) -> 6479032700 | K77: =SUM(K61:K76) -> 1677598970 | L77: =SUM(L61:L66) -> 0 | M77: =SUM(M61:M76) -> 1600264870 | N77: =I77+K77+L77-J77-M77 -> 0
H79: Setor Modal Awal | I79: =I77-J77+K77-M77 -> 0 | L79: Asumsi
H80: Margin | I80: =SUM(P12:P27) -> 1235880470 | J80: =J77-C62 -> 0 | L80: Setor Modal | M80: =I77 -> 6401698600
H81: Modal PO baru | I81: =-J77 -> -6479032700 | J81: Baris 18-29 | L81: Margin | M81: =K77 -> 1677598970
H82: Penarikan | I82: =-M65 -> -1105000000 | L82: Penarikan Margin | M82: =-M65 -> -1105000000
H83: Dana Tersedia/Kurang | I83: =I79+I80+I81+I82 -> -6348152230 | L83: PO Baru | M83: =-J77 -> -6479032700
B84: Setoran Investasi | C84: =I77 -> 6401698600 | L84: Dana tersedia | M84: =M80+M81+M82+M83 -> 495264870 | O84: Total
B85: Modal Ditahan | C85: =SUM(L31,L35:L44) -> 4954450200 | H85: PO & margin akan cair | I85: =SUM(L29:L42,P29:P42) -> 7907676000 | J85: Baris 18-29 | O85: =M87+N87 -> 2429580000
B86: Investasi yang dikembalikan | C86: =C84-C85 -> 1447248400 | L86: Bulan | M86: Margin yang akan diterima | N86: Modal yang akan diterima | O86: =M88+N88 -> 2808315000
L87: 46023 | M87: =SUM(AA31,AA39:AA42) -> 404930000 | N87: =SUM(L31,L39:L42) -> 2024650000 | O87: =SUM(O85:O86) -> 5237895000
I88: 130000000 | L88: 46054 | M88: =SUM(AA33:AA35,AA43) -> 468052500 | N88: =SUM(L33:L35,L43) -> 2340262500
L89: Margin yang akan diterima | M89: =SUM(M87:M88) -> 872982500 | N89: =SUM(N87:N88) -> 4364912500 | O89: =M91+N91 -> 2529429240
O90: =O87+O89 -> 7767324240
L91: Belum Terkirim | M91: =SUM(AB36:AB38,AB44:AB45) -> 421571540 | N91: =SUM(L36:L38,L44:L45) -> 2107857700
L92: Total Margin Yg Akan diterim | M92: =M89+M91 -> 1294554040 | N92: =N89+N91 -> 6472770200
B93: Belum ada di hitungan pak M
B94: 46044 | C94: 5201004137 | D94: Open | G94: Marine Maintenance Jetty | P94: =SUM(N94:O94) -> 0 | Y94: 0 | Z94: 0 | AA94: 0 | AB94: =N95+O94-AA94 -> 92664000 | AC94: 594462700 | AI94: Open | AJ94: Blm Terkirim
B95: 46045 | C95: 5201004344 | D95: Open | G95: Trench Grade | H95: 1 | J95: 926640000 | K95: =H95*J95 -> 926640000 | L95: =K95*50% -> 463320000 | M95: =L95*20% -> 92664000 | N95: =(L95*20%)+I95 -> 92664000 | P95: =SUM(N95:O95) -> 92664000 | Y95: 0 | Z95: 0 | AA95: 0 | AB95: =N96+O95-AA95 -> 24952500 | AI95: Open | AJ95: Blm Terkirim
B96: 46051 | C96: 5201005549 | D96: Open | G96: Top Frame 800 | H96: 50 | J96: =249525000/H96 -> 4990500 | K96: =H96*J96 -> 249525000 | L96: =K96*50% -> 124762500 | M96: =(L96/H96)*20% -> 499050 | N96: =(L96*20%)+I96 -> 24952500 | P96: =SUM(N96:O96) -> 24952500 | Y96: 0 | Z96: 0 | AA96: 0 | AB96: =N97+O96-AA96 -> 45000000 | AJ96: Blm Terkirim
B97: 46051 | C97: 5201005550 | D97: Open | G97: Top Frame 800 | H97: 2 | J97: 225000000 | K97: =H97*J97 -> 450000000 | L97: =K97*50% -> 225000000 | M97: =(L97/H97)*20% -> 22500000 | N97: =M97*H97 -> 45000000 | P97: =SUM(N97:O97) -> 45000000 | Y97: 0 | Z97: 0 | AA97: 0 | AB97: =N98+O97-AA97 -> 45000000 | AJ97: Blm Terkirim
B98: 46051 | C98: 5201005551 | D98: Open | G98: Muck Bumper | H98: 2 | J98: 225000000 | K98: =H98*J98 -> 450000000 | L98: =K98*50% -> 225000000 | M98: =(L98/H98)*20% -> 22500000 | N98: =M98*H98 -> 45000000 | P98: =SUM(N98:O98) -> 45000000 | Y98: 0 | Z98: 0 | AA98: 0 | AB98: =N99+O98-AA98 -> 59200000 | AJ98: Blm Terkirim
B99: 46051 | C99: 5201005552 | D99: Open | G99: Muck Bumper | H99: 16 | J99: 37000000 | K99: =H99*J99 -> 592000000 | L99: =K99*50% -> 296000000 | M99: =(L99/H99)*20% -> 3700000 | N99: =L99*20% -> 59200000 | P99: =SUM(N99:O99) -> 59200000 | Y99: 0 | Z99: 0 | AA99: 0 | AB99: =N100+O99-AA99 -> 59200000 | AJ99: Blm Terkirim
H100: 16 | J100: 37000000 | K100: =H100*J100 -> 592000000 | L100: =K100*50% -> 296000000 | M100: =(L100/H100)*20% -> 3700000 | N100: =L100*20% -> 59200000

Sheet Summary V.4 (5)
C1: LIST INVESTASI
H7: =Detail!E2 -> 4 | J7: =Detail!F2 -> 5 | K7: =Detail!G2 -> 6 | L7: =Detail!H2 -> 7 | N7: =Detail!I2 -> 8
A10: NO | B10: Date | C10: No. PO | D10: Status | E10: Margin Diterima | F10: Modal Di terima | G10: Nama Barang | H10: =Detail!E3 -> Qty | I10: Harga Beli (only added if Margin is set) | J10: =Detail!F3 -> Harga | K10: Total PO | L10: Modal | M10: Margin Per Unit | N10: =Detail!I3 -> Margin | O10: Add Margin | P10: Total Margin | Q10: Invoice /DO | Y10: DO Total | Z10: DO Outstanding | AA10: Margin | AB10: Margin ditahan | AC10: MODAL DITAHAN | AD10: Del Time | AE10: Invoice date | AF10: adjusting TOP 30 Days | AG10: adjusting TOP 60 Days | AH10: Payment Date | AI10: Status | AJ10: Notes | AK10: Tari | AL10: Total Margin TARI | AM10: Selisih
Q11: Jul | R11: Aug | S11: Sep | T11: Oct | U11: Nov | V11: Dec | W11: Jan | X11: Add Margin (by Agreement) | AJ11: Notes
A12: 1 | B12: =VLOOKUP($C12,Detail!$B$4:$Q$21,2,0) -> 45839 | C12: 5200954145 | D12: Close | E12: =P12-AB12 -> 45000000 | F12: =L12-AC12 -> 225000000 | G12: Top Frame 800 | H12: =SUMIF(Detail!$B$4:$B$21,'Summary V.4 (5)'!$C12,Detail!$E$4:$E$21) -> 2 | J12: =VLOOKUP($C12,Detail!$B$4:$Q$21,5,0) -> 225000000 | K12: =H12*J12 -> 450000000 | L12: =SUMIF(Detail!$B$4:$B$21,'Summary V.4 (5)'!C12,Detail!$H$4:$H$21) -> 225000000 | M12: =(L12*20%)/H12 -> 22500000 | N12: =L12*20% -> 45000000 | P12: =SUM(N12:O12) -> 45000000 | Q12: =H12 -> 2 | Y12: =SUM(Q12:V12) -> 2 | Z12: =H12-Y12 -> 0 | AA12: =M12*Y12 -> 45000000 | AB12: =N12-AA12 -> 0 | AD12: 45861 | AE12: 45863 | AF12: 45894 | AI12: Close | AK12: =VLOOKUP(C12,investasi!$B$5:$G$18,6,0) -> 45000000 | AL12: =P12 -> 45000000 | AM12: =AK12-AL12 -> 0
A13: 2 | B13: =VLOOKUP($C13,Detail!$B$4:$Q$21,2,0) -> 45839 | C13: 5200954149 | D13: Close | E13: =P13-AB13 -> 67500000 | F13: =L13-AC13 -> 337500000 | G13: Top Frame 800 | H13: =SUMIF(Detail!$B$4:$B$21,'Summary V.4 (5)'!$C13,Detail!$E$4:$E$21) -> 3 | J13: =VLOOKUP($C13,Detail!$B$4:$Q$21,5,0) -> 225000000 | K13: =H13*J13 -> 675000000 | L13: =SUMIF(Detail!$B$4:$B$21,'Summary V.4 (5)'!C13,Detail!$H$4:$H$21) -> 337500000 | M13: =(L13*20%)/H13 -> 22500000 | N13: =L13*20% -> 67500000 | P13: =SUM(N13:O13) -> 67500000 | Q13: =H13 -> 3 | Y13: =SUM(Q13:V13) -> 3 | Z13: =H13-Y13 -> 0 | AA13: =M13*Y13 -> 67500000 | AB13: =N13-AA13 -> 0 | AD13: 45861 | AE13: 45863 | AF13: 45894 | AI13: Close | AK13: =VLOOKUP(C13,investasi!$B$5:$G$18,6,0) -> 67500000 | AL13: =P13 -> 67500000 | AM13: =AK13-AL13 -> 0
A14: 3 | B14: =VLOOKUP($C14,Detail!$B$4:$Q$21,2,0) -> 45839 | C14: 5200954160 | D14: Close | E14: =P14-AB14 -> 67500000 | F14: =L14-AC14 -> 337500000 | G14: Top Frame 800 | H14: =SUMIF(Detail!$B$4:$B$21,'Summary V.4 (5)'!$C14,Detail!$E$4:$E$21) -> 3 | J14: =VLOOKUP($C14,Detail!$B$4:$Q$21,5,0) -> 225000000 | K14: =H14*J14 -> 675000000 | L14: =SUMIF(Detail!$B$4:$B$21,'Summary V.4 (5)'!C14,Detail!$H$4:$H$21) -> 337500000 | M14: =(L14*20%)/H14 -> 22500000 | N14: =L14*20% -> 67500000 | P14: =SUM(N14:O14) -> 67500000 | Q14: =H14 -> 3 | Y14: =SUM(Q14:V14) -> 3 | Z14: =H14-Y14 -> 0 | AA14: =M14*Y14 -> 67500000 | AB14: =N14-AA14 -> 0 | AD14: 45861 | AE14: 45863 | AF14: 45894 | AI14: Close | AK14: =VLOOKUP(C14,investasi!$B$5:$G$18,6,0) -> 67500000 | AL14: =P14 -> 67500000 | AM14: =AK14-AL14 -> 0
A15: 4 | B15: =VLOOKUP($C15,Detail!$B$4:$Q$21,2,0) -> 45870 | C15: 5200954165 | D15: Close | E15: =P15-AB15 -> 67500000 | F15: =L15-AC15 -> 337500000 | G15: Top Frame 800 | H15: =SUMIF(Detail!$B$4:$B$21,'Summary V.4 (5)'!$C15,Detail!$E$4:$E$21) -> 3 | J15: =VLOOKUP($C15,Detail!$B$4:$Q$21,5,0) -> 225000000 | K15: =H15*J15 -> 675000000 | L15: =SUMIF(Detail!$B$4:$B$21,'Summary V.4 (5)'!C15,Detail!$H$4:$H$21) -> 337500000 | M15: =(L15*20%)/H15 -> 22500000 | N15: =L15*20% -> 67500000 | P15: =SUM(N15:O15) -> 67500000 | R15: =H15 -> 3 | Y15: =SUM(Q15:V15) -> 3 | Z15: =H15-Y15 -> 0 | AA15: =M15*Y15 -> 67500000 | AB15: =N15-AA15 -> 0 | AD15: 45868 | AE15: 45873 | AF15: 45904 | AI15: Close | AK15: =VLOOKUP(C15,investasi!$B$5:$G$18,6,0) -> 67500000 | AL15: =P15 -> 67500000 | AM15: =AK15-AL15 -> 0
A16: 5 | B16: =VLOOKUP($C16,Detail!$B$4:$Q$21,2,0) -> 45870 | C16: 5200954167 | D16: Close | E16: =P16-AB16 -> 67500000 | F16: =L16-AC16 -> 337500000 | G16: Top Frame 800 | H16: =SUMIF(Detail!$B$4:$B$21,'Summary V.4 (5)'!$C16,Detail!$E$4:$E$21) -> 3 | J16: =VLOOKUP($C16,Detail!$B$4:$Q$21,5,0) -> 225000000 | K16: =H16*J16 -> 675000000 | L16: =SUMIF(Detail!$B$4:$B$21,'Summary V.4 (5)'!C16,Detail!$H$4:$H$21) -> 337500000 | M16: =(L16*20%)/H16 -> 22500000 | N16: =L16*20% -> 67500000 | P16: =SUM(N16:O16) -> 67500000 | R16: =H16 -> 3 | Y16: =SUM(Q16:V16) -> 3 | Z16: =H16-Y16 -> 0 | AA16: =M16*Y16 -> 67500000 | AB16: =N16-AA16 -> 0 | AD16: 45868 | AE16: 45873 | AF16: 45904 | AI16: Close | AK16: =VLOOKUP(C16,investasi!$B$5:$G$18,6,0) -> 67500000 | AL16: =P16 -> 67500000 | AM16: =AK16-AL16 -> 0
A17: 6 | B17: =VLOOKUP($C17,Detail!$B$4:$Q$21,2,0) -> 45870 | C17: 5200954168 | D17: Close | E17: =P17-AB17 -> 45000000 | F17: =L17-AC17 -> 225000000 | G17: Top Frame 800 | H17: =SUMIF(Detail!$B$4:$B$21,'Summary V.4 (5)'!$C17,Detail!$E$4:$E$21) -> 2 | J17: =VLOOKUP($C17,Detail!$B$4:$Q$21,5,0) -> 225000000 | K17: =H17*J17 -> 450000000 | L17: =SUMIF(Detail!$B$4:$B$21,'Summary V.4 (5)'!C17,Detail!$H$4:$H$21) -> 225000000 | M17: =(L17*20%)/H17 -> 22500000 | N17: =L17*20% -> 45000000 | P17: =SUM(N17:O17) -> 45000000 | R17: =H17 -> 2 | Y17: =SUM(Q17:V17) -> 2 | Z17: =H17-Y17 -> 0 | AA17: =M17*Y17 -> 45000000 | AB17: =N17-AA17 -> 0 | AD17: 45868 | AE17: 45873 | AF17: 45904 | AI17: Close | AK17: =VLOOKUP(C17,investasi!$B$5:$G$18,6,0) -> 45000000 | AL17: =P17 -> 45000000 | AM17: =AK17-AL17 -> 0
A18: 7 | B18: =VLOOKUP($C18,Detail!$B$4:$Q$21,2,0) -> 45870 | C18: 5200954169 | D18: Close | E18: =P18-AB18 -> 45000000 | F18: =L18-AC18 -> 225000000 | G18: Top Frame 800 | H18: =SUMIF(Detail!$B$4:$B$21,'Summary V.4 (5)'!$C18,Detail!$E$4:$E$21) -> 2 | J18: =VLOOKUP($C18,Detail!$B$4:$Q$21,5,0) -> 225000000 | K18: =H18*J18 -> 450000000 | L18: =SUMIF(Detail!$B$4:$B$21,'Summary V.4 (5)'!C18,Detail!$H$4:$H$21) -> 225000000 | M18: =(L18*20%)/H18 -> 22500000 | N18: =L18*20% -> 45000000 | P18: =SUM(N18:O18) -> 45000000 | R18: =H18 -> 2 | Y18: =SUM(Q18:V18) -> 2 | Z18: =H18-Y18 -> 0 | AA18: =M18*Y18 -> 45000000 | AB18: =N18-AA18 -> 0 | AD18: 45868 | AE18: 45873 | AF18: 45904 | AI18: Close | AK18: =VLOOKUP(C18,investasi!$B$5:$G$18,6,0) -> 45000000 | AL18: =P18 -> 45000000 | AM18: =AK18-AL18 -> 0
A19: 8 | B19: =VLOOKUP($C19,Detail!$B$4:$Q$25,2,0) -> 45877 | C19: 5200777098 | D19: Close | E19: =P19-AB19 -> 114919900 | F19: =L19-AC19 -> 574599500 | G19: DVAR 3771-B0-20D-PPC Statcom Steel Support | H19: =SUMIF(Detail!$B$4:$B$25,'Summary V.4 (5)'!$C19,Detail!$E$4:$E$25) -> 1 | J19: =VLOOKUP($C19,Detail!$B$4:$Q$25,5,0) -> 1149199000 | K19: =H19*J19 -> 1149199000 | L19: =SUMIF(Detail!$B$4:$B$25,'Summary V.4 (5)'!C19,Detail!$H$4:$H$25) -> 574599500 | M19: =(L19*20%)/H19 -> 114919900 | N19: =L19*20% -> 114919900 | P19: =SUM(N19:O19) -> 114919900 | R19: 0 | S19: 1 | Y19: =SUM(Q19:V19) -> 1 | Z19: =H19-Y19 -> 0 | AA19: =M19*Y19 -> 114919900 | AB19: =N19-AA19 -> 0 | AD19: 45930 | AE19: =AD19+7 -> 45937 | AF19: =AE19+30 -> 45967 | AG19: =AE19+60 -> 45997 | AI19: Close | AK19: =VLOOKUP(C19,investasi!$B$5:$G$18,6,0) -> 57248700 | AL19: =P19 -> 114919900 | AM19: =AK19-AL19 -> -57671200 | AN19: Selisih di unit Qty, di catatan pak mushafa 2 unit(1 sudah terbayar , 1 unit belum terbayar ), dicatatan TARI 1 Unit
A20: 9 | B20: =VLOOKUP($C20,Detail!$B$4:$Q$25,2,0) -> 45877 | C20: 5200776987 | D20: Close | E20: =P20-AB20 -> 45000000 | F20: =L20-AC20 -> 225000000 | G20: Top Frame 800 | H20: =SUMIF(Detail!$B$4:$B$25,'Summary V.4 (5)'!$C20,Detail!$E$4:$E$25) -> 2 | J20: =VLOOKUP($C20,Detail!$B$4:$Q$25,5,0) -> 225000000 | K20: =H20*J20 -> 450000000 | L20: =SUMIF(Detail!$B$4:$B$25,'Summary V.4 (5)'!C20,Detail!$H$4:$H$25) -> 225000000 | M20: =(L20*20%)/H20 -> 22500000 | N20: =L20*20% -> 45000000 | P20: =SUM(N20:O20) -> 45000000 | R20: 0 | S20: 2 | Y20: =SUM(Q20:V20) -> 2 | Z20: =H20-Y20 -> 0 | AA20: =M20*Y20 -> 45000000 | AB20: =N20-AA20 -> 0 | AD20: 45923 | AE20: =AD20+7 -> 45930 | AF20: =AE20+30 -> 45960 | AG20: =AE20+60 -> 45990 | AI20: Close | AK20: =VLOOKUP(C20,investasi!$B$5:$G$18,6,0) -> 45000000 | AL20: =P20 -> 45000000 | AM20: =AK20-AL20 -> 0
A21: 10 | B21: =VLOOKUP($C21,Detail!$B$4:$Q$110,2,0) -> 45880 | C21: 5200777132 | D21: Close | E21: =P21-AB21 -> 52594750 | F21: =L21-AC21 -> 404575000 | G21: Leser Barrier MK 01-F3004973 | H21: 20 | J21: =VLOOKUP($C21,Detail!$B$4:$Q$25,5,0) -> 40457500 | K21: =H21*J21 -> 809150000 | L21: =K21*50% -> 404575000 | M21: =(L21*13%)/H21 -> 2629737.5 | N21: =L21*13% -> 52594750 | P21: =SUM(N21:O21) -> 52594750 | R21: 0 | T21: 20 | Y21: =SUM(Q21:V21) -> 20 | Z21: =H21-Y21 -> 0 | AA21: =M21*Y21 -> 52594750 | AB21: =N21-AA21 -> 0 | AD21: 45922 | AE21: =AD21+7 -> 45929 | AF21: =AE21+30 -> 45959 | AG21: =AE21+60 -> 45989 | AI21: Close | AK21: =VLOOKUP(C21,investasi!$B$5:$G$18,6,0) -> 52594750 | AL21: =P21 -> 52594750 | AM21: =AK21-AL21 -> 0
A22: 11 | B22: =Detail!$C$45 -> 45891 | C22: =Detail!$B$45 -> 5200972695 | D22: Close | E22: =P22-AB22 -> 102000000 | F22: =L22-AC22 -> 402000000 | G22: Tangki | H22: 8 | I22: 75000000 | J22: 100500000 | K22: =H22*J22 -> 804000000 | L22: =K22*50% -> 402000000 | M22: 12750000 | N22: =H22*M22 -> 102000000 | P22: =SUM(N22:O22) -> 102000000 | R22: 0 | S22: 8 | X22: Margin was arranged 25mil/ea | Y22: =SUM(Q22:V22) -> 8 | Z22: =H22-Y22 -> 0 | AA22: =M22*Y22 -> 102000000 | AB22: =N22-AA22 -> 0 | AD22: 45925 | AE22: =AD22+7 -> 45932 | AF22: =AE22+30 -> 45962 | AG22: =AE22+60 -> 45992 | AI22: Close | AK22: =VLOOKUP(C22,investasi!$B$5:$G$18,6,0) -> 80400000 | AL22: =P22 -> 102000000 | AM22: =AK22-AL22 -> -21600000 | AN22: Selisih margin | AP22: 21600000
A23: 12 | B23: 45897 | C23: =Detail!B53 -> 5200777558 | D23: Close | E23: =P23-AB23 -> 68500000 | F23: =L23-AC23 -> 342500000 | G23: Top Frame 2630 | H23: 1 | J23: =Detail!F53 -> 685000000 | K23: =H23*J23 -> 685000000 | L23: =K23*50% -> 342500000 | M23: =(L23*20%)/H23 -> 68500000 | N23: =L23*20% -> 68500000 | P23: =SUM(N23:O23) -> 68500000 | S23: 1 | Y23: =SUM(Q23:V23) -> 1 | Z23: =H23-Y23 -> 0 | AA23: =M23*Y23 -> 68500000 | AB23: =N23-AA23 -> 0 | AD23: 45923 | AE23: =AD23+7 -> 45930 | AF23: =AE23+30 -> 45960 | AG23: =AE23+60 -> 45990 | AI23: Close | AK23: =VLOOKUP(C23,investasi!$B$5:$G$18,6,0) -> 68500000 | AL23: =P23 -> 68500000 | AM23: =AK23-AL23 -> 0
A24: 13 | B24: 45901 | C24: =Detail!B54 -> 5200777559 | D24: Close | E24: =P24-AB24 -> 45000000 | F24: =L24-AC24 -> 225000000 | G24: Top Frame 800 | H24: 2 | J24: =Detail!F54 -> 225000000 | K24: =H24*J24 -> 450000000 | L24: =K24*50% -> 225000000 | M24: =(L24*20%)/H24 -> 22500000 | N24: =L24*20% -> 45000000 | P24: =SUM(N24:O24) -> 45000000 | S24: 2 | Y24: =SUM(Q24:V24) -> 2 | Z24: =H24-Y24 -> 0 | AA24: =M24*Y24 -> 45000000 | AB24: =N24-AA24 -> 0 | AD24: 45925 | AE24: =AD24+7 -> 45932 | AF24: =AE24+30 -> 45962 | AG24: =AE24+60 -> 45992 | AI24: Close | AK24: =VLOOKUP(C24,investasi!$B$5:$G$18,6,0) -> 45000000 | AL24: =P24 -> 45000000 | AM24: =AK24-AL24 -> 0
A25: 14 | B25: 45909 | C25: =Detail!$B$56 -> 5200777758 | D25: Close | E25: =P25-AB25 -> 223104820 | F25: =L25-AC25 -> 1115524100 | G25: Pipe Spool | H25: 1 | J25: =Detail!F56 -> 2231048200 | K25: =H25*J25 -> 2231048200 | L25: =K25*50% -> 1115524100 | M25: =(L25*20%)/H25 -> 223104820 | N25: =L25*20% -> 223104820 | P25: =SUM(N25:O25) -> 223104820 | S25: 1 | Y25: =SUM(Q25:V25) -> 1 | Z25: =H25-Y25 -> 0 | AA25: =M25*Y25 -> 223104820 | AB25: =N25-AA25 -> 0 | AD25: 45930 | AE25: =AD25+7 -> 45937 | AF25: =AE25+30 -> 45967 | AG25: =AE25+60 -> 45997 | AI25: Close | AK25: =VLOOKUP(C25,investasi!$B$5:$G$18,6,0) -> 223104820 | AL25: =P25 -> 223104820 | AM25: =AK25-AL25 -> 0
A26: 15 | B26: 45909 | C26: =Detail!$B$58 -> 5200778319 | D26: Close | E26: =P26-AB26 -> 45000000 | F26: =L26-AC26 -> 225000000 | G26: =Detail!$D$58 -> Top Frame 800 | H26: 2 | J26: =Detail!$F$58 -> 225000000 | K26: =H26*J26 -> 450000000 | L26: =K26*50% -> 225000000 | M26: =(L26*20%)/H26 -> 22500000 | N26: =L26*20% -> 45000000 | P26: =SUM(N26:O26) -> 45000000 | S26: 2 | Y26: =SUM(Q26:V26) -> 2 | Z26: =H26-Y26 -> 0 | AA26: =M26*Y26 -> 45000000 | AB26: =N26-AA26 -> 0 | AD26: 45940 | AE26: =AD26+7 -> 45947 | AF26: =AE26+30 -> 45977 | AG26: =AE26+60 -> 46007 | AI26: Close | AK26: =VLOOKUP(C26,investasi!$B$23:$G$26,6,0) -> 45000000 | AL26: =P26 -> 45000000 | AM26: =AK26-AL26 -> 0
A27: 16 | B27: 45915 | C27: 5200778328 | D27: Close | E27: =P27-AB27 -> 134761000 | F27: =L27-AC27 -> 342500000 | G27: Top Frame 2630 | H27: 1 | J27: =Detail!F59 -> 685000000 | K27: =H27*J27 -> 685000000 | L27: =K27*50% -> 342500000 | M27: =(L27*20%)/H27 -> 68500000 | N27: =(L27*20%)+I27 -> 68500000 | O27: 66261000 | P27: =SUM(N27:O27) -> 134761000 | S27: 1 | Y27: =SUM(Q27:V27) -> 1 | Z27: =H27-Y27 -> 0 | AA27: =M27*Y27+O27 -> 134761000 | AB27: =N27+O27-AA27 -> 0 | AD27: 45940 | AE27: =AD27+7 -> 45947 | AF27: =AE27+30 -> 45977 | AG27: =AE27+60 -> 46007 | AI27: Close | AK27: =VLOOKUP(C27,investasi!$B$23:$G$26,6,0)+investasi!I24 -> 134761000 | AL27: =P27 -> 134761000 | AM27: =AK27-AL27 -> 0
D28: Close | E28: =P28-AB28 -> 0 | F28: =L28-AC28 -> 0 | Y28: =SUM(Q28:V28) -> 0 | AI28: Close
A29: 18 | B29: 45965 | C29: =Detail!B60 -> 5200779815 | D29: Close | E29: =P29-AB29 -> 134761000 | F29: =L29-AC29 -> 342500000 | G29: Top Frame 2630 | H29: 1 | J29: =Detail!F60 -> 685000000 | K29: =H29*J29 -> 685000000 | L29: =K29*50% -> 342500000 | M29: =(L29*20%)/H29 -> 68500000 | N29: =(L29*20%)+I29 -> 68500000 | O29: 66261000 | P29: =SUM(N29:O29) -> 134761000 | U29: 1 | Y29: =SUM(Q29:V29) -> 1 | Z29: =H29-Y29 -> 0 | AA29: =M29*Y29+O29 -> 134761000 | AB29: =N29+O29-AA29 -> 0 | AD29: 45989 | AE29: 46008 | AF29: 46034 | AG29: =AE29+30 -> 46038 | AH29: 46034 | AI29: Close | AJ29: Payment 12 Jan 2026 | AK29: =VLOOKUP(C29,investasi!$B$23:$G$26,6,0)+investasi!I26 -> 134761000 | AL29: =P29 -> 134761000 | AM29: =AK29-AL29 -> 0
A30: =A29+1 -> 19 | B30: 45977 | C30: 5200988854 | D30: Close | E30: =P30-AB30 -> 74857500 | F30: =L30-AC30 -> 374287500 | G30: Trench Grade | H30: 150 | J30: 4990500 | K30: =H30*J30 -> 748575000 | L30: =K30*50% -> 374287500 | M30: =(L30*20%)/H30 -> 499050 | N30: =(L30*20%)+I30 -> 74857500 | P30: =SUM(N30:O30) -> 74857500 | U30: 150 | Y30: =SUM(Q30:V30) -> 150 | Z30: =H30-Y30 -> 0 | AA30: =M30*Y30+O30 -> 74857500 | AB30: =N30+O30-AA30 -> 0 | AD30: 45989 | AE30: 46008 | AF30: 46034 | AG30: =AE30+30 -> 46038 | AH30: 46034 | AI30: Close | AJ30: Payment 12 Jan 2026 | AN30: Tanki
A31: =A30+1 -> 20 | B31: 45977 | C31: 5200989664 | D31: Close | E31: =P31-AB31 -> 0 | F31: =L31-AC31 -> 0 | G31: Grating Ditch | H31: 50 | J31: 21100000 | K31: =H31*J31 -> 1055000000 | L31: =K31*50% -> 527500000 | M31: =(L31*20%)/H31 -> 2110000 | N31: =(L31*20%) -> 105500000 | P31: =SUM(N31:O31) -> 105500000 | V31: 50 | Y31: =SUM(Q31:V31) -> 50 | Z31: =H31-Y31 -> 0 | AA31: =M31*Y31+O31 -> 105500000 | AB31: =AA31 -> 105500000 | AC31: =L31 -> 527500000 | AD31: 46031 | AE31: 46031 | AF31: =AD31+30 -> 46061 | AI31: Delivered
D32: Open | E32: =P32-AB32 -> 0 | F32: =L32-AC32 -> 0 | G32: Grating Ditch | H32: 50 | J32: 21100000 | K32: =H32*J32 -> 1055000000 | L32: =K32*50% -> 527500000 | M32: =(L32*20%)/H32 -> 2110000 | N32: =(L32*20%)+I32 -> 105500000 | P32: =SUM(N32:O32) -> 105500000 | W32: 50 | Y32: =SUM(Q32:V32) -> 0 | Z32: =H32-Y32 -> 50 | AA32: =M32*Y32+O32 -> 0 | AB32: =N32+O32-AA32 -> 105500000 | AC32: =L32 -> 527500000 | AD32: 46031 | AE32: 46031 | AF32: =AD32+30 -> 46061 | AI32: Delivered
A33: =A31+1 -> 21 | B33: 45977 | C33: 5200989665 | D33: Delivered | E33: =P33-AB33 -> 0 | F33: =L33-AC33 -> 0 | G33: Grating Ditch | H33: 50 | J33: 21100000 | K33: =H33*J33 -> 1055000000 | L33: =K33*50% -> 527500000 | M33: =(L33*20%)/H33 -> 2110000 | N33: =(L33*20%)+I33 -> 105500000 | P33: =SUM(N33:O33) -> 105500000 | W33: 50 | Y33: =SUM(Q33:W33) -> 50 | Z33: =H33-Y33 -> 0 | AA33: =M33*Y33+O33 -> 105500000 | AB33: =AA33 -> 105500000 | AC33: =L33 -> 527500000 | AD33: 46030 | AE33: 46030 | AF33: =AD33+30 -> 46060 | AI33: Delivered
A34: =A32+1 -> 1 | B34: 45977 | C34: 5200989665 | D34: Delivered | E34: =P34-AB34 -> 0 | F34: =L34-AC34 -> 527500000 | G34: Grating Ditch | H34: 50 | J34: 21100000 | K34: =H34*J34 -> 1055000000 | L34: =K34*50% -> 527500000 | M34: =(L34*20%)/H34 -> 2110000 | N34: =(L34*20%)+I34 -> 105500000 | P34: =SUM(N34:O34) -> 105500000 | Y34: =SUM(Q34:W34) -> 0 | Z34: =H34-Y34 -> 50 | AA34: =M34*Y34+O34 -> 0 | AB34: =N34+O34-AA34 -> 105500000 | AD34: 46030 | AE34: 46030 | AF34: =AD34+30 -> 46060 | AI34: Delivered
A35: =A33+1 -> 22 | B35: 45977 | C35: 5200989666 | D35: Close | E35: =P35-AB35 -> 232100000 | F35: =L35-AC35 -> 1160500000 | G35: Grating Ditch | H35: 110 | J35: 21100000 | K35: =H35*J35 -> 2321000000 | L35: =K35*50% -> 1160500000 | M35: =(L35*20%)/H35 -> 2110000 | N35: =(L35*20%)+I35 -> 232100000 | P35: =SUM(N35:O35) -> 232100000 | W35: 110 | Y35: =SUM(Q35:W35) -> 110 | Z35: 0 | AA35: =M35*Y35+O35 -> 232100000 | AD35: 46027 | AE35: 45676 | AF35: =AE35+30 -> 45706 | AI35: Delivered | AJ35: Partial Deliv 55 ea
A36: =A35+1 -> 23 | B36: 45981 | C36: 5200992759 | D36: Open | E36: =P36-AB36 -> 0 | F36: =L36-AC36 -> 0 | G36: Tanki | H36: 6 | J36: 100500000 | K36: =H36*J36 -> 603000000 | L36: =K36*50% -> 301500000 | M36: 10050000 | N36: =M36*H36 -> 60300000 | P36: =SUM(N36:O36) -> 60300000 | W36: 6 | Y36: =SUM(Q36:W36) -> 6 | Z36: =H36-Y36 -> 0 | AA36: =M36*Y36+O36 -> 60300000 | AB36: =AA36 -> 60300000 | AC36: =L36 -> 301500000 | AD36: 46048 | AE36: 46048 | AF36: =AE36+30 -> 46078 | AI36: Delivered | AJ36: ada kenaikan harga material
A37: =A36+1 -> 24 | B37: 45985 | C37: 5200991260 | D37: Open | E37: =P37-AB37 -> 0 | F37: =L37-AC37 -> 0 | G37: Trench Grade | H37: 150 | J37: 4990500 | K37: =H37*J37 -> 748575000 | L37: =K37*50% -> 374287500 | M37: =(L37*20%)/H37 -> 499050 | N37: =(L37*20%)+I37 -> 74857500 | P37: =SUM(N37:O37) -> 74857500 | W37: =H37 -> 150 | Y37: =SUM(Q37:W37) -> 150 | Z37: =H37-Y37 -> 0 | AA37: =M37*Y37+O37 -> 74857500 | AB37: =AA37 -> 74857500 | AC37: =L37 -> 374287500 | AD37: 46041 | AE37: 46041 | AG37: =AD37+60 -> 46101 | AI37: Delivered | AJ37: Terkirim
A38: =A37+1 -> 25 | B38: 45985 | C38: 5200991264 | D38: Open | E38: =P38-AB38 -> 0 | F38: =L38-AC38 -> 0 | G38: Trench Grade | H38: 150 | J38: 4990500 | K38: =H38*J38 -> 748575000 | L38: =K38*50% -> 374287500 | M38: =(L38*20%)/H38 -> 499050 | N38: =(L38*20%)+I38 -> 74857500 | P38: =SUM(N38:O38) -> 74857500 | W38: =H38 -> 150 | Y38: =SUM(Q38:W38) -> 150 | Z38: =H38-Y38 -> 0 | AA38: =M38*Y38+O38 -> 74857500 | AB38: =AA38 -> 74857500 | AC38: =L38 -> 374287500 | AD38: 46041 | AE38: 46041 | AG38: =AD38+60 -> 46101 | AI38: Delivered | AJ38: Terkirim
A39: =A38+1 -> 26 | B39: 45986 | C39: 5200991456 | D39: Open | E39: =P39-AB39 -> 0 | F39: =L39-AC39 -> 0 | G39: Trench Grade | H39: 150 | J39: 4990500 | K39: =H39*J39 -> 748575000 | L39: =K39*50% -> 374287500 | M39: =(L39*20%)/H39 -> 499050 | N39: =(L39*20%)+I39 -> 74857500 | P39: =SUM(N39:O39) -> 74857500 | V39: =H39 -> 150 | Y39: =SUM(Q39:V39) -> 150 | Z39: =H39-Y39 -> 0 | AA39: =M39*Y39+O39 -> 74857500 | AB39: =AA39 -> 74857500 | AC39: =L39 -> 374287500 | AD39: 46036 | AE39: 46036 | AG39: =AD39+60 -> 46096 | AI39: Delivered
A40: =A39+1 -> 27 | B40: 45986 | C40: 5200991458 | D40: Open | E40: =P40-AB40 -> 0 | F40: =L40-AC40 -> 0 | G40: Trench Grade | H40: 150 | J40: 4990500 | K40: =H40*J40 -> 748575000 | L40: =K40*50% -> 374287500 | M40: =(L40*20%)/H40 -> 499050 | N40: =(L40*20%)+I40 -> 74857500 | P40: =SUM(N40:O40) -> 74857500 | V40: =H40 -> 150 | Y40: =SUM(Q40:V40) -> 150 | Z40: =H40-Y40 -> 0 | AA40: =M40*Y40+O40 -> 74857500 | AB40: =AA40 -> 74857500 | AC40: =L40 -> 374287500 | AD40: 46036 | AE40: 46036 | AG40: =AD40+60 -> 46096 | AI40: Delivered
A41: =A40+1 -> 28 | B41: 45986 | C41: 5200991502 | D41: Open | E41: =P41-AB41 -> 0 | F41: =L41-AC41 -> 0 | G41: Trench Grade | H41: 150 | J41: 4990500 | K41: =H41*J41 -> 748575000 | L41: =K41*50% -> 374287500 | M41: =(L41*20%)/H41 -> 499050 | N41: =(L41*20%)+I41 -> 74857500 | P41: =SUM(N41:O41) -> 74857500 | V41: =H41 -> 150 | Y41: =SUM(Q41:V41) -> 150 | Z41: =H41-Y41 -> 0 | AA41: =M41*Y41+O41 -> 74857500 | AB41: =AA41 -> 74857500 | AC41: =L41 -> 374287500 | AD41: 46030 | AE41: 46030 | AG41: =AD41+60 -> 46090 | AI41: Delivered
A42: =A41+1 -> 29 | B42: 45986 | C42: 5200991503 | D42: Open | E42: =P42-AB42 -> 0 | F42: =L42-AC42 -> 0 | G42: Trench Grade | H42: 150 | J42: 4990500 | K42: =H42*J42 -> 748575000 | L42: =K42*50% -> 374287500 | M42: =(L42*20%)/H42 -> 499050 | N42: =(L42*20%)+I42 -> 74857500 | P42: =SUM(N42:O42) -> 74857500 | V42: =H42 -> 150 | Y42: =SUM(Q42:V42) -> 150 | Z42: =H42-Y42 -> 0 | AA42: =M42*Y42+O42 -> 74857500 | AB42: =AA42 -> 74857500 | AC42: =L42 -> 374287500 | AD42: 46030 | AE42: 46030 | AG42: =AD42+60 -> 46090 | AI42: Delivered
A43: =A42+1 -> 30 | B43: 46372 | C43: 5200991553 | D43: Open | E43: =P43-AB43 -> 0 | F43: =L43-AC43 -> 0 | G43: Trench Grade | H43: 50 | J43: 4990500 | K43: =H43*J43 -> 249525000 | L43: =K43*50% -> 124762500 | M43: =(L43*20%)/H43 -> 499050 | N43: =(L43*20%)+I43 -> 24952500 | P43: =SUM(N43:O43) -> 24952500 | V43: =H43 -> 50 | Y43: =SUM(Q43:V43) -> 50 | Z43: =H43-Y43 -> 0 | AA43: =M43*Y43+O43 -> 24952500 | AB43: =AA43 -> 24952500 | AC43: =L43 -> 124762500 | AD43: 46036 | AE43: 46036 | AG43: =AD43+60 -> 46096 | AI43: Delivered
A44: =A43+1 -> 31 | B44: 46021 | C44: 5200996833 | D44: Open | E44: =P44-AB44 -> 0 | F44: =L44-AC44 -> 0 | G44: new barge landing facility | H44: 1 | J44: 1188000000 | K44: 1188925400 | L44: =K44*50% -> 594462700 | M44: =(L44*20%)/H44 -> 118892540 | N44: =(L44*20%)+I44 -> 118892540 | P44: =SUM(N44:O44) -> 118892540 | Y44: 0 | Z44: 0 | AA44: 0 | AB44: =N44+O44-AA44 -> 118892540 | AC44: =L44 -> 594462700 | AI44: Open | AJ44: Blm Terkirim
C47: TOTAL MARGIN | E47: =SUM(E12:E45) -> 1677598970 | F47: =SUM(F12:F45) -> 8286486100 | K47: =SUM(K12:K45) -> 26270872600 | L47: =SUM(L12:L45) -> 13135436300 | N47: =SUM(N12:N45) -> 2620367010 | O47: =SUM(O12:O45) -> 132522000 | P47: =SUM(P12:P45) -> 2752889010 | AA47: =SUM(AA12:AA45) -> 2422996470 | AB47: =SUM(AB12:AB45) -> 1075290040 | AC47: =SUM(AC12:AC45) -> 4848950200
H49: A | J49: B | K49: C | L49: D | M49: E | N49: F=A+B+C-D-E
H50: TGL | I50: Modal Setor Awal | J50: Margin | K50: Pencairan Modal | L50: Modal PO Baru | M50: Penarikan | N50: Dana Tersedia
B51: Total Tf Investasi | C51: =SUM(I66) -> 6401698600 | H51: 45839 | I51: =SUM(L12:L14) -> 900000000 | J51: =SUM(AA12:AA14) -> 180000000 | N51: =I51+J51 -> 1080000000
B52: Investasi yang ditahan | C52: =AC47 -> 4848950200 | D52: ='Summary V.4 (6)'!C62-'Summary V.4 (5)'!C52 -> 1630082500 | H52: 45870 | I52: =SUM(L15:L18) -> 1125000000 | J52: =SUM(AA15:AA18) -> 225000000 | L52: =SUM(L19:L22) -> 1606174500 | N52: =N51+I52+J52+K52-L52-M52 -> 823825500
B53: Total Investasi transfer | C53: =C51-C52 -> 1552748400 | H53: 45901 | I53: 1426698600 | L53: =SUM(L23:L27) -> 2250524100 | N53: =N52+I53+J53+K53-L53 -> 0
H54: 45931 | L54: =L29+L28 -> 342500000 | N54: =N53+I54+J54+K54-L54 -> -342500000
B55: Total Margin | C55: =SUM(P12:P44) -> 2752889010 | H55: 45962 | J55: =SUM(P19:P28) -> 830880470 | L55: =-SUM(L19:L28)+SUM(L30:L42) -> 2335313900 | M55: 1105000000 | N55: =N54+I55+J55+K55-L55-M55 -> -2951933430
B56: Margin Diterima | C56: =M55 -> 1105000000 | H56: 46007 | I56: 1300000000 | L56: =L43+L44+L45 -> 719225200 | N56: =N55+I56+J56+K56-L56-M56 -> -2371158630
B57: Sisa | C57: =C55-C56 -> 1647889010 | H57: 46014 | I57: 250000000 | N57: =N56+I57+J57+K57-L57-M57 -> -2121158630
B58: Margin Ditahan | C58: =SUM(AB29:AB44) -> 1075290040 | H58: 46015 | I58: 250000000 | N58: =N57+I58+J58+K58-L58-M58 -> -1871158630
B59: Margin Tersedia | C59: =C57-C58 -> 572598970 | H59: 46016 | I59: 250000000 | N59: =N58+I59+J59+K59-L59-M59 -> -1621158630
B60: Total dana Transfer | C60: =C53+C59 -> 2125347370 | D60: =C60-'Summary V.4 (6)'!C70 -> 1630082500 | H60: 46017 | I60: 250000000 | N60: =N59+I60+J60+K60-L60-M60 -> -1371158630
H61: 46018 | I61: 250000000 | N61: =N60+I61+J61+K61-L61-M61 -> -1121158630
H62: 46019 | I62: 250000000 | N62: =N61+I62+J62+K62-L62-M62 -> -871158630
H63: 46020 | I63: 150000000 | N63: =N62+I63+J63+K63-L63-M63 -> -721158630
H64: 46034 | J64: =SUM(P29:P31) -> 315118500 | L64: =-SUM(L29:L31) -> -1244287500 | N64: =N63+I64+J64+K64-L64-M64 -> 838247370
H65: 46045 | L65: =SUM(L85:L89) -> 1166762500 | N65: =N64+I65+J65+K65-L65-M65 -> -328515130
I66: =SUM(I51:I65) -> 6401698600 | J66: =SUM(J51:J65) -> 1550998970 | K66: =SUM(K51:K56) -> 0 | L66: =SUM(L51:L65) -> 7176212700 | M66: =SUM(M51:M64) -> 1105000000 | N66: =I66+J66+K66-L66-M66 -> -328515130
H68: Setor Modal Awal | I68: =I66 -> 6401698600 | L68: Asumsi
H69: Margin | I69: =SUM(P12:P27) -> 1235880470 | L69: Setor Modal | M69: =I66 -> 6401698600
H70: Modal PO baru | I70: =-L66 -> -7176212700 | J70: Baris 18-29 | L70: Margin | M70: =J66 -> 1550998970
H71: Penarikan | I71: =-M55 -> -1105000000 | L71: Penarikan Margin | M71: =-M55 -> -1105000000
H72: Dana Tersedia/Kurang | I72: =I68+I69+I70+I71 -> -643633630 | L72: PO Baru | M72: =-L66 -> -7176212700
L73: Dana tersedia | M73: =M69+M70+M71+M72 -> -328515130
B74: Setoran Investasi | C74: =I66 -> 6401698600 | H74: PO & margin akan cair | I74: =SUM(L29:L42,P29:P42) -> 7907676000 | J74: Baris 18-29 | O74: Total
B75: Modal Ditahan | C75: =SUM(L31,L35:L44) -> 4954450200 | L75: Bulan | M75: Margin yang akan diterima | N75: Modal yang akan diterima | O75: =M76+N76 -> 2429580000
B76: Investasi yang dikembalikan | C76: =C74-C75 -> 1447248400 | L76: 46023 | M76: =SUM(AA31,AA39:AA42) -> 404930000 | N76: =SUM(L31,L39:L42) -> 2024650000 | O76: =M77+N77 -> 2702815000
I77: 130000000 | L77: 46054 | M77: =SUM(AA33:AA35,AA43) -> 362552500 | N77: =SUM(L33:L35,L43) -> 2340262500 | O77: =SUM(O75:O76) -> 5132395000
L78: Margin yang akan diterima | M78: =SUM(M76:M77) -> 767482500 | N78: =SUM(N76:N77) -> 4364912500
O79: =M80+N80 -> 1973445240
L80: Belum Terkirim | M80: =SUM(AB36:AB38,AB44:AB45) -> 328907540 | N80: =SUM(L36:L38,L44:L45) -> 1644537700 | O80: =O77+O79 -> 7105840240
L81: Total Margin Yg Akan diterim | M81: =M78+M80 -> 1096390040 | N81: =N78+N80 -> 6009450200
B83: Belum ada di hitungan pak M
B84: 46044 | C84: 5201004137 | D84: Open | G84: Marine Maintenance Jetty | H84: 1 | J84: 926640000 | K84: =H84*J84 -> 926640000 | L84: =K84*50% -> 463320000 | M84: =L84*20% -> 92664000 | N84: =(L84*20%)+I84 -> 92664000 | P84: =SUM(N84:O84) -> 92664000 | Y84: 0 | Z84: 0 | AA84: 0 | AB84: =N84+O84-AA84 -> 92664000 | AC84: 594462700 | AI84: Open | AJ84: Blm Terkirim
B85: 46045 | C85: 5201004344 | D85: Open | G85: Trench Grade | H85: 50 | J85: =249525000/H85 -> 4990500 | K85: =H85*J85 -> 249525000 | L85: =K85*50% -> 124762500 | M85: =(L85/H85)*20% -> 499050 | N85: =(L85*20%)+I85 -> 24952500 | P85: =SUM(N85:O85) -> 24952500 | Y85: 0 | Z85: 0 | AA85: 0 | AB85: =N85+O85-AA85 -> 24952500 | AI85: Open | AJ85: Blm Terkirim
B86: 46051 | C86: 5201005549 | D86: Open | G86: Top Frame 800 | H86: 2 | J86: 225000000 | K86: =H86*J86 -> 450000000 | L86: =K86*50% -> 225000000 | M86: =(L86/H86)*20% -> 22500000 | N86: =M86*H86 -> 45000000 | P86: =SUM(N86:O86) -> 45000000 | Y86: 0 | Z86: 0 | AA86: 0 | AB86: =N86+O86-AA86 -> 45000000 | AJ86: Blm Terkirim
B87: 46051 | C87: 5201005550 | D87: Open | G87: Top Frame 800 | H87: 2 | J87: 225000000 | K87: =H87*J87 -> 450000000 | L87: =K87*50% -> 225000000 | M87: =(L87/H87)*20% -> 22500000 | N87: =M87*H87 -> 45000000 | P87: =SUM(N87:O87) -> 45000000 | Y87: 0 | Z87: 0 | AA87: 0 | AB87: =N87+O87-AA87 -> 45000000 | AJ87: Blm Terkirim
B88: 46051 | C88: 5201005551 | D88: Open | G88: Muck Bumper | H88: 16 | J88: 37000000 | K88: =H88*J88 -> 592000000 | L88: =K88*50% -> 296000000 | M88: =(L88/H88)*20% -> 3700000 | N88: =L88*20% -> 59200000 | P88: =SUM(N88:O88) -> 59200000 | Y88: 0 | Z88: 0 | AA88: 0 | AB88: =N88+O88-AA88 -> 59200000 | AJ88: Blm Terkirim
B89: 46051 | C89: 5201005552 | D89: Open | G89: Muck Bumper | H89: 16 | J89: 37000000 | K89: =H89*J89 -> 592000000 | L89: =K89*50% -> 296000000 | M89: =(L89/H89)*20% -> 3700000 | N89: =L89*20% -> 59200000 | P89: =SUM(N89:O89) -> 59200000 | Y89: 0 | Z89: 0 | AA89: 0 | AB89: =N89+O89-AA89 -> 59200000 | AJ89: Blm Terkirim

Sheet Summary V.4 (4)
C1: LIST INVESTASI
G7: =Detail!E2 -> 4 | I7: =Detail!F2 -> 5 | J7: =Detail!G2 -> 6 | K7: =Detail!H2 -> 7 | M7: =Detail!I2 -> 8
A10: NO | B10: Date | C10: No. PO | D10: Status | E10: Total Payment | F10: Nama Barang | G10: =Detail!E3 -> Qty | H10: Harga Beli (only added if Margin is set) | I10: =Detail!F3 -> Harga | J10: Total PO | K10: Modal | L10: Margin Per Unit | M10: =Detail!I3 -> Margin | N10: Add Margin | O10: Total Margin | P10: Invoice /DO | X10: DO Total | Y10: DO Outstanding | Z10: Margin | AA10: AR MARGIN | AB10: Del Time | AC10: Invoice date | AD10: adjusting TOP 30 Days | AE10: adjusting TOP 60 Days | AF10: Payment Date | AG10: Status | AH10: Notes | AI10: Notes | AJ10: Tari | AK10: Total Margin TARI | AL10: Selisih
P11: Jul | Q11: Aug | R11: Sep | S11: Oct | T11: Nov | U11: Dec | V11: Jan | W11: Add Margin (by Agreement) | AH11: Notes | AI11: Notes
A12: 1 | B12: =VLOOKUP($C12,Detail!$B$4:$Q$21,2,0) -> 45839 | C12: 5200954145 | D12: Close | E12: =O12+K12 -> 270000000 | F12: Top Frame 800 | G12: =SUMIF(Detail!$B$4:$B$21,'Summary V.4 (4)'!$C12,Detail!$E$4:$E$21) -> 2 | I12: =VLOOKUP($C12,Detail!$B$4:$Q$21,5,0) -> 225000000 | J12: =G12*I12 -> 450000000 | K12: =SUMIF(Detail!$B$4:$B$21,'Summary V.4 (4)'!C12,Detail!$H$4:$H$21) -> 225000000 | L12: =(K12*20%)/G12 -> 22500000 | M12: =K12*20% -> 45000000 | O12: =SUM(M12:N12) -> 45000000 | P12: =G12 -> 2 | X12: =SUM(P12:U12) -> 2 | Y12: =G12-X12 -> 0 | Z12: =L12*X12 -> 45000000 | AA12: =M12-Z12 -> 0 | AB12: 45861 | AC12: 45863 | AD12: 45894 | AG12: Close | AJ12: =VLOOKUP(C12,investasi!$B$5:$G$18,6,0) -> 45000000 | AK12: =O12 -> 45000000 | AL12: =AJ12-AK12 -> 0
A13: 2 | B13: =VLOOKUP($C13,Detail!$B$4:$Q$21,2,0) -> 45839 | C13: 5200954149 | D13: Close | E13: =O13+K13 -> 405000000 | F13: Top Frame 800 | G13: =SUMIF(Detail!$B$4:$B$21,'Summary V.4 (4)'!$C13,Detail!$E$4:$E$21) -> 3 | I13: =VLOOKUP($C13,Detail!$B$4:$Q$21,5,0) -> 225000000 | J13: =G13*I13 -> 675000000 | K13: =SUMIF(Detail!$B$4:$B$21,'Summary V.4 (4)'!C13,Detail!$H$4:$H$21) -> 337500000 | L13: =(K13*20%)/G13 -> 22500000 | M13: =K13*20% -> 67500000 | O13: =SUM(M13:N13) -> 67500000 | P13: =G13 -> 3 | X13: =SUM(P13:U13) -> 3 | Y13: =G13-X13 -> 0 | Z13: =L13*X13 -> 67500000 | AA13: =M13-Z13 -> 0 | AB13: 45861 | AC13: 45863 | AD13: 45894 | AG13: Close | AJ13: =VLOOKUP(C13,investasi!$B$5:$G$18,6,0) -> 67500000 | AK13: =O13 -> 67500000 | AL13: =AJ13-AK13 -> 0
A14: 3 | B14: =VLOOKUP($C14,Detail!$B$4:$Q$21,2,0) -> 45839 | C14: 5200954160 | D14: Close | E14: =O14+K14 -> 405000000 | F14: Top Frame 800 | G14: =SUMIF(Detail!$B$4:$B$21,'Summary V.4 (4)'!$C14,Detail!$E$4:$E$21) -> 3 | I14: =VLOOKUP($C14,Detail!$B$4:$Q$21,5,0) -> 225000000 | J14: =G14*I14 -> 675000000 | K14: =SUMIF(Detail!$B$4:$B$21,'Summary V.4 (4)'!C14,Detail!$H$4:$H$21) -> 337500000 | L14: =(K14*20%)/G14 -> 22500000 | M14: =K14*20% -> 67500000 | O14: =SUM(M14:N14) -> 67500000 | P14: =G14 -> 3 | X14: =SUM(P14:U14) -> 3 | Y14: =G14-X14 -> 0 | Z14: =L14*X14 -> 67500000 | AA14: =M14-Z14 -> 0 | AB14: 45861 | AC14: 45863 | AD14: 45894 | AG14: Close | AJ14: =VLOOKUP(C14,investasi!$B$5:$G$18,6,0) -> 67500000 | AK14: =O14 -> 67500000 | AL14: =AJ14-AK14 -> 0
A15: 4 | B15: =VLOOKUP($C15,Detail!$B$4:$Q$21,2,0) -> 45870 | C15: 5200954165 | D15: Close | E15: =O15+K15 -> 405000000 | F15: Top Frame 800 | G15: =SUMIF(Detail!$B$4:$B$21,'Summary V.4 (4)'!$C15,Detail!$E$4:$E$21) -> 3 | I15: =VLOOKUP($C15,Detail!$B$4:$Q$21,5,0) -> 225000000 | J15: =G15*I15 -> 675000000 | K15: =SUMIF(Detail!$B$4:$B$21,'Summary V.4 (4)'!C15,Detail!$H$4:$H$21) -> 337500000 | L15: =(K15*20%)/G15 -> 22500000 | M15: =K15*20% -> 67500000 | O15: =SUM(M15:N15) -> 67500000 | Q15: =G15 -> 3 | X15: =SUM(P15:U15) -> 3 | Y15: =G15-X15 -> 0 | Z15: =L15*X15 -> 67500000 | AA15: =M15-Z15 -> 0 | AB15: 45868 | AC15: 45873 | AD15: 45904 | AG15: Close | AJ15: =VLOOKUP(C15,investasi!$B$5:$G$18,6,0) -> 67500000 | AK15: =O15 -> 67500000 | AL15: =AJ15-AK15 -> 0
A16: 5 | B16: =VLOOKUP($C16,Detail!$B$4:$Q$21,2,0) -> 45870 | C16: 5200954167 | D16: Close | E16: =O16+K16 -> 405000000 | F16: Top Frame 800 | G16: =SUMIF(Detail!$B$4:$B$21,'Summary V.4 (4)'!$C16,Detail!$E$4:$E$21) -> 3 | I16: =VLOOKUP($C16,Detail!$B$4:$Q$21,5,0) -> 225000000 | J16: =G16*I16 -> 675000000 | K16: =SUMIF(Detail!$B$4:$B$21,'Summary V.4 (4)'!C16,Detail!$H$4:$H$21) -> 337500000 | L16: =(K16*20%)/G16 -> 22500000 | M16: =K16*20% -> 67500000 | O16: =SUM(M16:N16) -> 67500000 | Q16: =G16 -> 3 | X16: =SUM(P16:U16) -> 3 | Y16: =G16-X16 -> 0 | Z16: =L16*X16 -> 67500000 | AA16: =M16-Z16 -> 0 | AB16: 45868 | AC16: 45873 | AD16: 45904 | AG16: Close | AJ16: =VLOOKUP(C16,investasi!$B$5:$G$18,6,0) -> 67500000 | AK16: =O16 -> 67500000 | AL16: =AJ16-AK16 -> 0
A17: 6 | B17: =VLOOKUP($C17,Detail!$B$4:$Q$21,2,0) -> 45870 | C17: 5200954168 | D17: Close | E17: =O17+K17 -> 270000000 | F17: Top Frame 800 | G17: =SUMIF(Detail!$B$4:$B$21,'Summary V.4 (4)'!$C17,Detail!$E$4:$E$21) -> 2 | I17: =VLOOKUP($C17,Detail!$B$4:$Q$21,5,0) -> 225000000 | J17: =G17*I17 -> 450000000 | K17: =SUMIF(Detail!$B$4:$B$21,'Summary V.4 (4)'!C17,Detail!$H$4:$H$21) -> 225000000 | L17: =(K17*20%)/G17 -> 22500000 | M17: =K17*20% -> 45000000 | O17: =SUM(M17:N17) -> 45000000 | Q17: =G17 -> 2 | X17: =SUM(P17:U17) -> 2 | Y17: =G17-X17 -> 0 | Z17: =L17*X17 -> 45000000 | AA17: =M17-Z17 -> 0 | AB17: 45868 | AC17: 45873 | AD17: 45904 | AG17: Close | AJ17: =VLOOKUP(C17,investasi!$B$5:$G$18,6,0) -> 45000000 | AK17: =O17 -> 45000000 | AL17: =AJ17-AK17 -> 0
A18: 7 | B18: =VLOOKUP($C18,Detail!$B$4:$Q$21,2,0) -> 45870 | C18: 5200954169 | D18: Close | E18: =O18+K18 -> 270000000 | F18: Top Frame 800 | G18: =SUMIF(Detail!$B$4:$B$21,'Summary V.4 (4)'!$C18,Detail!$E$4:$E$21) -> 2 | I18: =VLOOKUP($C18,Detail!$B$4:$Q$21,5,0) -> 225000000 | J18: =G18*I18 -> 450000000 | K18: =SUMIF(Detail!$B$4:$B$21,'Summary V.4 (4)'!C18,Detail!$H$4:$H$21) -> 225000000 | L18: =(K18*20%)/G18 -> 22500000 | M18: =K18*20% -> 45000000 | O18: =SUM(M18:N18) -> 45000000 | Q18: =G18 -> 2 | X18: =SUM(P18:U18) -> 2 | Y18: =G18-X18 -> 0 | Z18: =L18*X18 -> 45000000 | AA18: =M18-Z18 -> 0 | AB18: 45868 | AC18: 45873 | AD18: 45904 | AG18: Close | AJ18: =VLOOKUP(C18,investasi!$B$5:$G$18,6,0) -> 45000000 | AK18: =O18 -> 45000000 | AL18: =AJ18-AK18 -> 0
A19: 8 | B19: =VLOOKUP($C19,Detail!$B$4:$Q$25,2,0) -> 45877 | C19: 5200777098 | D19: Close | E19: =O19+K19 -> 689519400 | F19: DVAR 3771-B0-20D-PPC Statcom Steel Support | G19: =SUMIF(Detail!$B$4:$B$25,'Summary V.4 (4)'!$C19,Detail!$E$4:$E$25) -> 1 | I19: =VLOOKUP($C19,Detail!$B$4:$Q$25,5,0) -> 1149199000 | J19: =G19*I19 -> 1149199000 | K19: =SUMIF(Detail!$B$4:$B$25,'Summary V.4 (4)'!C19,Detail!$H$4:$H$25) -> 574599500 | L19: =(K19*20%)/G19 -> 114919900 | M19: =K19*20% -> 114919900 | O19: =SUM(M19:N19) -> 114919900 | Q19: 0 | R19: 1 | X19: =SUM(P19:U19) -> 1 | Y19: =G19-X19 -> 0 | Z19: =L19*X19 -> 114919900 | AA19: =M19-Z19 -> 0 | AB19: 45930 | AC19: =AB19+7 -> 45937 | AD19: =AC19+30 -> 45967 | AE19: =AC19+60 -> 45997 | AG19: Close | AJ19: =VLOOKUP(C19,investasi!$B$5:$G$18,6,0) -> 57248700 | AK19: =O19 -> 114919900 | AL19: =AJ19-AK19 -> -57671200 | AM19: Selisih di unit Qty, di catatan pak mushafa 2 unit(1 sudah terbayar , 1 unit belum terbayar ), dicatatan TARI 1 Unit
A20: 9 | B20: =VLOOKUP($C20,Detail!$B$4:$Q$25,2,0) -> 45877 | C20: 5200776987 | D20: Close | E20: =O20+K20 -> 270000000 | F20: Top Frame 800 | G20: =SUMIF(Detail!$B$4:$B$25,'Summary V.4 (4)'!$C20,Detail!$E$4:$E$25) -> 2 | I20: =VLOOKUP($C20,Detail!$B$4:$Q$25,5,0) -> 225000000 | J20: =G20*I20 -> 450000000 | K20: =SUMIF(Detail!$B$4:$B$25,'Summary V.4 (4)'!C20,Detail!$H$4:$H$25) -> 225000000 | L20: =(K20*20%)/G20 -> 22500000 | M20: =K20*20% -> 45000000 | O20: =SUM(M20:N20) -> 45000000 | Q20: 0 | R20: 2 | X20: =SUM(P20:U20) -> 2 | Y20: =G20-X20 -> 0 | Z20: =L20*X20 -> 45000000 | AA20: =M20-Z20 -> 0 | AB20: 45923 | AC20: =AB20+7 -> 45930 | AD20: =AC20+30 -> 45960 | AE20: =AC20+60 -> 45990 | AG20: Close | AJ20: =VLOOKUP(C20,investasi!$B$5:$G$18,6,0) -> 45000000 | AK20: =O20 -> 45000000 | AL20: =AJ20-AK20 -> 0
A21: 10 | B21: =VLOOKUP($C21,Detail!$B$4:$Q$110,2,0) -> 45880 | C21: 5200777132 | D21: Close | E21: =O21+K21 -> 457169750 | F21: Leser Barrier MK 01-F3004973 | G21: 20 | I21: =VLOOKUP($C21,Detail!$B$4:$Q$25,5,0) -> 40457500 | J21: =G21*I21 -> 809150000 | K21: =J21*50% -> 404575000 | L21: =(K21*13%)/G21 -> 2629737.5 | M21: =K21*13% -> 52594750 | O21: =SUM(M21:N21) -> 52594750 | Q21: 0 | S21: 20 | X21: =SUM(P21:U21) -> 20 | Y21: =G21-X21 -> 0 | Z21: =L21*X21 -> 52594750 | AA21: =M21-Z21 -> 0 | AB21: 45922 | AC21: =AB21+7 -> 45929 | AD21: =AC21+30 -> 45959 | AE21: =AC21+60 -> 45989 | AG21: Close | AJ21: =VLOOKUP(C21,investasi!$B$5:$G$18,6,0) -> 52594750 | AK21: =O21 -> 52594750 | AL21: =AJ21-AK21 -> 0
A22: 11 | B22: =Detail!$C$45 -> 45891 | C22: =Detail!$B$45 -> 5200972695 | D22: Close | E22: =O22+K22 -> 504000000 | F22: Tangki | G22: 8 | H22: 75000000 | I22: 100500000 | J22: =G22*I22 -> 804000000 | K22: =J22*50% -> 402000000 | L22: 12750000 | M22: =G22*L22 -> 102000000 | O22: =SUM(M22:N22) -> 102000000 | Q22: 0 | R22: 8 | W22: Margin was arranged 25mil/ea | X22: =SUM(P22:U22) -> 8 | Y22: =G22-X22 -> 0 | Z22: =L22*X22 -> 102000000 | AA22: =M22-Z22 -> 0 | AB22: 45925 | AC22: =AB22+7 -> 45932 | AD22: =AC22+30 -> 45962 | AE22: =AC22+60 -> 45992 | AG22: Close | AJ22: =VLOOKUP(C22,investasi!$B$5:$G$18,6,0) -> 80400000 | AK22: =O22 -> 102000000 | AL22: =AJ22-AK22 -> -21600000 | AM22: Selisih margin
A23: 12 | B23: 45897 | C23: =Detail!B53 -> 5200777558 | D23: Close | E23: =O23+K23 -> 411000000 | F23: Top Frame 2630 | G23: 1 | I23: =Detail!F53 -> 685000000 | J23: =G23*I23 -> 685000000 | K23: =J23*50% -> 342500000 | L23: =(K23*20%)/G23 -> 68500000 | M23: =K23*20% -> 68500000 | O23: =SUM(M23:N23) -> 68500000 | R23: 1 | X23: =SUM(P23:U23) -> 1 | Y23: =G23-X23 -> 0 | Z23: =L23*X23 -> 68500000 | AA23: =M23-Z23 -> 0 | AB23: 45923 | AC23: =AB23+7 -> 45930 | AD23: =AC23+30 -> 45960 | AE23: =AC23+60 -> 45990 | AG23: Close | AJ23: =VLOOKUP(C23,investasi!$B$5:$G$18,6,0) -> 68500000 | AK23: =O23 -> 68500000 | AL23: =AJ23-AK23 -> 0
A24: 13 | B24: 45901 | C24: =Detail!B54 -> 5200777559 | D24: Close | E24: =O24+K24 -> 270000000 | F24: Top Frame 800 | G24: 2 | I24: =Detail!F54 -> 225000000 | J24: =G24*I24 -> 450000000 | K24: =J24*50% -> 225000000 | L24: =(K24*20%)/G24 -> 22500000 | M24: =K24*20% -> 45000000 | O24: =SUM(M24:N24) -> 45000000 | R24: 2 | X24: =SUM(P24:U24) -> 2 | Y24: =G24-X24 -> 0 | Z24: =L24*X24 -> 45000000 | AA24: =M24-Z24 -> 0 | AB24: 45925 | AC24: =AB24+7 -> 45932 | AD24: =AC24+30 -> 45962 | AE24: =AC24+60 -> 45992 | AG24: Close | AJ24: =VLOOKUP(C24,investasi!$B$5:$G$18,6,0) -> 45000000 | AK24: =O24 -> 45000000 | AL24: =AJ24-AK24 -> 0
A25: 14 | B25: 45909 | C25: =Detail!$B$56 -> 5200777758 | D25: Close | E25: =O25+K25 -> 1338628920 | F25: Pipe Spool | G25: 1 | I25: =Detail!F56 -> 2231048200 | J25: =G25*I25 -> 2231048200 | K25: =J25*50% -> 1115524100 | L25: =(K25*20%)/G25 -> 223104820 | M25: =K25*20% -> 223104820 | O25: =SUM(M25:N25) -> 223104820 | R25: 1 | X25: =SUM(P25:U25) -> 1 | Y25: =G25-X25 -> 0 | Z25: =L25*X25 -> 223104820 | AA25: =M25-Z25 -> 0 | AB25: 45930 | AC25: =AB25+7 -> 45937 | AD25: =AC25+30 -> 45967 | AE25: =AC25+60 -> 45997 | AG25: Close | AJ25: =VLOOKUP(C25,investasi!$B$5:$G$18,6,0) -> 223104820 | AK25: =O25 -> 223104820 | AL25: =AJ25-AK25 -> 0
A26: 15 | B26: 45909 | C26: =Detail!$B$58 -> 5200778319 | D26: Close | E26: =O26+K26 -> 270000000 | F26: =Detail!$D$58 -> Top Frame 800 | G26: 2 | I26: =Detail!$F$58 -> 225000000 | J26: =G26*I26 -> 450000000 | K26: =J26*50% -> 225000000 | L26: =(K26*20%)/G26 -> 22500000 | M26: =K26*20% -> 45000000 | O26: =SUM(M26:N26) -> 45000000 | R26: 2 | X26: =SUM(P26:U26) -> 2 | Y26: =G26-X26 -> 0 | Z26: =L26*X26 -> 45000000 | AA26: =M26-Z26 -> 0 | AB26: 45940 | AC26: =AB26+7 -> 45947 | AD26: =AC26+30 -> 45977 | AE26: =AC26+60 -> 46007 | AG26: Close | AJ26: =VLOOKUP(C26,investasi!$B$23:$G$26,6,0) -> 45000000 | AK26: =O26 -> 45000000 | AL26: =AJ26-AK26 -> 0
A27: 16 | B27: 45915 | C27: 5200778328 | D27: Close | E27: =O27+K27 -> 477261000 | F27: Top Frame 2630 | G27: 1 | I27: =Detail!F59 -> 685000000 | J27: =G27*I27 -> 685000000 | K27: =J27*50% -> 342500000 | L27: =(K27*20%)/G27 -> 68500000 | M27: =(K27*20%)+H27 -> 68500000 | N27: 66261000 | O27: =SUM(M27:N27) -> 134761000 | R27: 1 | X27: =SUM(P27:U27) -> 1 | Y27: =G27-X27 -> 0 | Z27: =L27*X27+N27 -> 134761000 | AA27: =M27+N27-Z27 -> 0 | AB27: 45940 | AC27: =AB27+7 -> 45947 | AD27: =AC27+30 -> 45977 | AE27: =AC27+60 -> 46007 | AG27: Close | AJ27: =VLOOKUP(C27,investasi!$B$23:$G$26,6,0)+investasi!I24 -> 134761000 | AK27: =O27 -> 134761000 | AL27: =AJ27-AK27 -> 0
D28: Close | E28: =O28+K28 -> 0 | X28: =SUM(P28:U28) -> 0 | AG28: Close
A29: 18 | B29: 45965 | C29: =Detail!B60 -> 5200779815 | D29: Close | E29: =O29+K29 -> 477261000 | F29: Top Frame 2630 | G29: 1 | I29: =Detail!F60 -> 685000000 | J29: =G29*I29 -> 685000000 | K29: =J29*50% -> 342500000 | L29: =(K29*20%)/G29 -> 68500000 | M29: =(K29*20%)+H29 -> 68500000 | N29: 66261000 | O29: =SUM(M29:N29) -> 134761000 | T29: 1 | X29: =SUM(P29:U29) -> 1 | Y29: =G29-X29 -> 0 | Z29: =L29*X29+N29 -> 134761000 | AA29: =M29+N29-Z29 -> 0 | AB29: 45989 | AC29: 46008 | AD29: 46034 | AE29: =AC29+30 -> 46038 | AF29: 46034 | AG29: Close | AH29: Payment 12 Jan 2026 | AJ29: =VLOOKUP(C29,investasi!$B$23:$G$26,6,0)+investasi!I26 -> 134761000 | AK29: =O29 -> 134761000 | AL29: =AJ29-AK29 -> 0
A30: =A29+1 -> 19 | B30: 45977 | C30: 5200988854 | D30: Close | E30: =O30+K30 -> 449145000 | F30: Trench Grade | G30: 150 | I30: 4990500 | J30: =G30*I30 -> 748575000 | K30: =J30*50% -> 374287500 | L30: =(K30*20%)/G30 -> 499050 | M30: =(K30*20%)+H30 -> 74857500 | O30: =SUM(M30:N30) -> 74857500 | T30: 150 | X30: =SUM(P30:U30) -> 150 | Y30: =G30-X30 -> 0 | Z30: =L30*X30+N30 -> 74857500 | AA30: =M30+N30-Z30 -> 0 | AB30: 45989 | AC30: 46008 | AD30: 46034 | AE30: =AC30+30 -> 46038 | AF30: 46034 | AG30: Close | AH30: Payment 12 Jan 2026
A31: =A30+1 -> 20 | B31: 45977 | C31: 5200989664 | D31: Close | E31: =O31+K31 -> 1266000000 | F31: Grating Ditch | G31: 100 | I31: 21100000 | J31: =G31*I31 -> 2110000000 | K31: =J31*50% -> 1055000000 | L31: =(K31*20%)/G31 -> 2110000 | M31: =(K31*20%)+H31 -> 211000000 | O31: =SUM(M31:N31) -> 211000000 | U31: 100 | X31: =SUM(P31:U31) -> 100 | Y31: =G31-X31 -> 0 | Z31: =L31*X31+N31 -> 211000000 | AA31: =M31+N31-Z31 -> 0 | AB31: 46031 | AC31: 46031 | AD31: =AB31+30 -> 46061 | AG31: Delivered
A32: =A31+1 -> 21 | B32: 45977 | C32: 5200989665 | D32: Delivered | F32: Grating Ditch | G32: 100 | I32: 21100000 | J32: =G32*I32 -> 2110000000 | K32: =J32*50% -> 1055000000 | L32: =(K32*20%)/G32 -> 2110000 | M32: =(K32*20%)+H32 -> 211000000 | O32: =SUM(M32:N32) -> 211000000 | U32: 100 | X32: =SUM(P32:V32) -> 100 | Y32: =G32-X32 -> 0 | Z32: =L32*X32+N32 -> 211000000 | AA32: =M32+N32-Z32 -> 0 | AB32: 46030 | AC32: 46030 | AD32: =AB32+30 -> 46060 | AG32: Delivered
A33: =A32+1 -> 22 | B33: 45977 | C33: 5200989666 | D33: Delivered | F33: Grating Ditch | G33: 110 | I33: 21100000 | J33: =G33*I33 -> 2321000000 | K33: =J33*50% -> 1160500000 | L33: =(K33*20%)/G33 -> 2110000 | M33: =(K33*20%)+H33 -> 232100000 | O33: =SUM(M33:N33) -> 232100000 | V33: 55 | X33: =SUM(P33:V33) -> 55 | Y33: 0 | Z33: =L33*X33+N33 -> 116050000 | AA33: 0 | AB33: 46027 | AC33: 45676 | AD33: =AC33+30 -> 45706 | AG33: Delivered | AH33: Partial Deliv 55 ea
D34: Delivered | V34: 55 | X34: =SUM(P34:V34) -> 55 | Y34: 0 | Z34: =X34*L33+N33 -> 116050000 | AA34: 0 | AB34: 46036 | AC34: 45676 | AD34: =AC34+30 -> 45706 | AG34: Delivered | AH34: Partial Deliv 55 ea
A35: =A33+1 -> 23 | B35: 45981 | C35: 5200992759 | D35: Delivered | F35: Tanki | G35: 6 | I35: 100500000 | J35: =G35*I35 -> 603000000 | K35: =J35*50% -> 301500000 | L35: 12750000 | M35: =L35*G35 -> 76500000 | O35: =SUM(M35:N35) -> 76500000 | V35: 6 | X35: =SUM(P35:V35) -> 6 | Y35: =G35-X35 -> 0 | Z35: =L35*X35+N35 -> 76500000 | AA35: =M35+N35-Z35 -> 0 | AB35: 46048 | AC35: 46048 | AD35: =AC35+30 -> 46078 | AG35: Delivered | AH35: Terkirim
A36: =A35+1 -> 24 | B36: 45985 | C36: 5200991260 | D36: Delivered | F36: Trench Grade | G36: 150 | I36: 4990500 | J36: =G36*I36 -> 748575000 | K36: =J36*50% -> 374287500 | L36: =(K36*20%)/G36 -> 499050 | M36: =(K36*20%)+H36 -> 74857500 | O36: =SUM(M36:N36) -> 74857500 | V36: =G36 -> 150 | X36: =SUM(P36:U36) -> 0 | Y36: =G36-X36 -> 150 | Z36: =L36*X36+N36 -> 0 | AA36: =M36+N36-Z36 -> 74857500 | AB36: 46041 | AC36: 46041 | AE36: =AB36+60 -> 46101 | AG36: Delivered | AH36: Terkirim
A37: =A36+1 -> 25 | B37: 45985 | C37: 5200991264 | D37: Delivered | F37: Trench Grade | G37: 150 | I37: 4990500 | J37: =G37*I37 -> 748575000 | K37: =J37*50% -> 374287500 | L37: =(K37*20%)/G37 -> 499050 | M37: =(K37*20%)+H37 -> 74857500 | O37: =SUM(M37:N37) -> 74857500 | V37: =G37 -> 150 | X37: =SUM(P37:U37) -> 0 | Y37: =G37-X37 -> 150 | Z37: =L37*X37+N37 -> 0 | AA37: =M37+N37-Z37 -> 74857500 | AB37: 46041 | AC37: 46041 | AE37: =AB37+60 -> 46101 | AG37: Delivered | AH37: Terkirim
A38: =A37+1 -> 26 | B38: 45986 | C38: 5200991456 | D38: Delivered | F38: Trench Grade | G38: 150 | I38: 4990500 | J38: =G38*I38 -> 748575000 | K38: =J38*50% -> 374287500 | L38: =(K38*20%)/G38 -> 499050 | M38: =(K38*20%)+H38 -> 74857500 | O38: =SUM(M38:N38) -> 74857500 | U38: =G38 -> 150 | X38: =SUM(P38:U38) -> 150 | Y38: =G38-X38 -> 0 | Z38: =L38*X38+N38 -> 74857500 | AA38: =M38+N38-Z38 -> 0 | AB38: 46036 | AC38: 46036 | AE38: =AB38+60 -> 46096 | AG38: Delivered
A39: =A38+1 -> 27 | B39: 45986 | C39: 5200991458 | D39: Delivered | F39: Trench Grade | G39: 150 | I39: 4990500 | J39: =G39*I39 -> 748575000 | K39: =J39*50% -> 374287500 | L39: =(K39*20%)/G39 -> 499050 | M39: =(K39*20%)+H39 -> 74857500 | O39: =SUM(M39:N39) -> 74857500 | U39: =G39 -> 150 | X39: =SUM(P39:U39) -> 150 | Y39: =G39-X39 -> 0 | Z39: =L39*X39+N39 -> 74857500 | AA39: =M39+N39-Z39 -> 0 | AB39: 46036 | AC39: 46036 | AE39: =AB39+60 -> 46096 | AG39: Delivered
A40: =A39+1 -> 28 | B40: 45986 | C40: 5200991502 | D40: Delivered | F40: Trench Grade | G40: 150 | I40: 4990500 | J40: =G40*I40 -> 748575000 | K40: =J40*50% -> 374287500 | L40: =(K40*20%)/G40 -> 499050 | M40: =(K40*20%)+H40 -> 74857500 | O40: =SUM(M40:N40) -> 74857500 | U40: =G40 -> 150 | X40: =SUM(P40:U40) -> 150 | Y40: =G40-X40 -> 0 | Z40: =L40*X40+N40 -> 74857500 | AA40: =M40+N40-Z40 -> 0 | AB40: 46030 | AC40: 46030 | AE40: =AB40+60 -> 46090 | AG40: Delivered
A41: =A40+1 -> 29 | B41: 45986 | C41: 5200991503 | D41: Delivered | F41: Trench Grade | G41: 150 | I41: 4990500 | J41: =G41*I41 -> 748575000 | K41: =J41*50% -> 374287500 | L41: =(K41*20%)/G41 -> 499050 | M41: =(K41*20%)+H41 -> 74857500 | O41: =SUM(M41:N41) -> 74857500 | U41: =G41 -> 150 | X41: =SUM(P41:U41) -> 150 | Y41: =G41-X41 -> 0 | Z41: =L41*X41+N41 -> 74857500 | AA41: =M41+N41-Z41 -> 0 | AB41: 46030 | AC41: 46030 | AE41: =AB41+60 -> 46090 | AG41: Delivered
A42: =A41+1 -> 30 | B42: 46372 | C42: 5200991553 | D42: Delivered | F42: Trench Grade | G42: 50 | I42: 4990500 | J42: =G42*I42 -> 249525000 | K42: =J42*50% -> 124762500 | L42: =(K42*20%)/G42 -> 499050 | M42: =(K42*20%)+H42 -> 24952500 | O42: =SUM(M42:N42) -> 24952500 | U42: =G42 -> 50 | X42: =SUM(P42:U42) -> 50 | Y42: =G42-X42 -> 0 | Z42: =L42*X42+N42 -> 24952500 | AA42: =M42+N42-Z42 -> 0 | AB42: 46036 | AC42: 46036 | AE42: =AB42+60 -> 46096 | AG42: Delivered
A43: =A42+1 -> 31 | B43: 46021 | C43: 5200996833 | D43: Open | F43: new barge landing facility | G43: 1 | I43: 1188000000 | J43: =G43*I43 -> 1188000000 | K43: =J43*50% -> 594000000 | L43: =(K43*20%)/G43 -> 118800000 | M43: =(K43*20%)+H43 -> 118800000 | O43: =SUM(M43:N43) -> 118800000 | X43: 0 | Y43: 0 | Z43: 0 | AA43: =M43+N43-Z43 -> 118800000 | AG43: Open | AH43: Blm Terkirim
B44: 46045 | C44: 5201004344 | D44: Open | F44: Trench Grade | G44: 50 | I44: =249525000/G44 -> 4990500 | J44: =G44*I44 -> 249525000 | K44: =J44*50% -> 124762500 | L44: =(K44/G44)*20% -> 499050 | M44: =(K44*20%)+H44 -> 24952500 | O44: =SUM(M44:N44) -> 24952500 | X44: 0 | Y44: 0 | Z44: 0 | AA44: =M44+N44-Z44 -> 24952500 | AG44: Open | AH44: Blm Terkirim
B45: 46051 | C45: 5201005549 | D45: Open | F45: Top Frame 800 | G45: 2 | I45: 225000000 | J45: =G45*I45 -> 450000000 | K45: =J45*50% -> 225000000 | L45: =(K45/G45)*20% -> 22500000 | M45: =L45*G45 -> 45000000 | O45: =SUM(M45:N45) -> 45000000 | X45: 0 | Y45: 0 | Z45: 0 | AA45: =M45+N45-Z45 -> 45000000 | AH45: Blm Terkirim
B46: 46051 | C46: 5201005550 | D46: Open | F46: Top Frame 800 | G46: 2 | I46: 225000000 | J46: =G46*I46 -> 450000000 | K46: =J46*50% -> 225000000 | L46: =(K46/G46)*20% -> 22500000 | M46: =L46*G46 -> 45000000 | O46: =SUM(M46:N46) -> 45000000 | X46: 0 | Y46: 0 | Z46: 0 | AA46: =M46+N46-Z46 -> 45000000 | AH46: Blm Terkirim
B47: 46051 | C47: 5201005551 | D47: Open | F47: Muck Bumper | G47: 16 | I47: 37000000 | J47: =G47*I47 -> 592000000 | K47: =J47*50% -> 296000000 | L47: =(K47/G47)*20% -> 3700000 | M47: =K47*20% -> 59200000 | O47: =SUM(M47:N47) -> 59200000 | X47: 0 | Y47: 0 | Z47: 0 | AA47: =M47+N47-Z47 -> 59200000 | AH47: Blm Terkirim
B48: 46051 | C48: 5201005552 | D48: Open | F48: Muck Bumper | G48: 16 | I48: 37000000 | J48: =G48*I48 -> 592000000 | K48: =J48*50% -> 296000000 | L48: =(K48/G48)*20% -> 3700000 | M48: =K48*20% -> 59200000 | O48: =SUM(M48:N48) -> 59200000 | X48: 0 | Y48: 0 | Z48: 0 | AA48: =M48+N48-Z48 -> 59200000 | AH48: Blm Terkirim
C51: TOTAL MARGIN | J51: =SUM(J12:J49) -> 28603472200 | K51: =SUM(K12:K49) -> 14301736100 | M51: =SUM(M12:M49) -> 2869826970 | N51: =SUM(N12:N49) -> 132522000 | O51: =SUM(O12:O49) -> 3002348970 | Z51: =SUM(Z12:Z49) -> 2500481470 | AA51: =SUM(AA12:AA49) -> 501867500
G53: A | I53: B | J53: C | K53: D | L53: E | M53: F=A+B+C-D-E
G54: TGL | H54: Modal Setor Awal | I54: Margin | J54: Pencairan Modal | K54: Modal PO Baru | L54: Penarikan | M54: Dana Tersedia
G55: 45839 | H55: =SUM(K12:K14) -> 900000000 | I55: =SUM(Z12:Z14) -> 180000000 | M55: =H55+I55 -> 1080000000
G56: 45870 | H56: =SUM(K15:K18) -> 1125000000 | I56: =SUM(Z15:Z18) -> 225000000 | K56: =SUM(K19:K22) -> 1606174500 | M56: =M55+H56+I56+J56-K56-L56 -> 823825500
G57: 45901 | H57: 1426698600 | K57: =SUM(K23:K27) -> 2250524100 | M57: =M56+H57+I57+J57-K57 -> 0
G58: 45931 | K58: =K29+K28 -> 342500000 | M58: =M57+H58+I58+J58-K58 -> -342500000
G59: 45962 | I59: =SUM(O19:O28) -> 830880470 | K59: =-SUM(K19:K28)+SUM(K30:K41) -> 2335313900 | L59: 1105000000 | M59: =M58+H59+I59+J59-K59-L59 -> -2951933430
G60: 46007 | H60: 1300000000 | K60: =K42+K43+K49 -> 718762500 | M60: =M59+H60+I60+J60-K60-L60 -> -2370695930
G61: 46014 | H61: 250000000 | M61: =M60+H61+I61+J61-K61-L61 -> -2120695930
G62: 46015 | H62: 250000000 | M62: =M61+H62+I62+J62-K62-L62 -> -1870695930
B63: Total Tf Investasi | C63: =SUM(H70) -> 6401698600 | G63: 46016 | H63: 250000000 | M63: =M62+H63+I63+J63-K63-L63 -> -1620695930
B64: Margin diterima (Close) | C64: =SUM(O12:O31) -> 1656498970 | G64: 46017 | H64: 250000000 | M64: =M63+H64+I64+J64-K64-L64 -> -1370695930
B65: Total Modal PO | C65: =-K51 -> -14301736100 | G65: 46018 | H65: 250000000 | M65: =M64+H65+I65+J65-K65-L65 -> -1120695930
B66: Modal Kembali PO (close) | C66: =SUM(K12:K31) -> 7653486100 | G66: 46019 | H66: 250000000 | M66: =M65+H66+I66+J66-K66-L66 -> -870695930
B67: Total dana | C67: =SUM(C63:C66) -> 1409947570 | G67: 46020 | H67: 150000000 | M67: =M66+H67+I67+J67-K67-L67 -> -720695930
B68: penarikan | C68: =L59 -> 1105000000 | G68: 46034 | I68: =SUM(O29:O31) -> 420618500 | K68: =-SUM(K29:K31) -> -1771787500 | M68: =M67+H68+I68+J68-K68-L68 -> 1471710070
B69: dana tersedia | C69: =C67-C68 -> 304947570 | G69: 46045 | K69: =SUM(K44:K48) -> 1166762500 | M69: =M68+H69+I69+J69-K69-L69 -> 304947570
H70: =SUM(H55:H69) -> 6401698600 | I70: =SUM(I55:I69) -> 1656498970 | J70: =SUM(J55:J60) -> 0 | K70: =SUM(K55:K69) -> 6648250000 | L70: =SUM(L55:L68) -> 1105000000 | M70: =H70+I70+J70-K70-L70 -> 304947570
G72: Setor Modal Awal | H72: =H70 -> 6401698600 | K72: Asumsi
G73: Margin | H73: =SUM(O12:O27) -> 1235880470 | K73: Setor Modal | L73: =H70 -> 6401698600
G74: Modal PO baru | H74: =-K70 -> -6648250000 | I74: Baris 18-29 | K74: Margin | L74: =I70 -> 1656498970
G75: Penarikan | H75: =-L59 -> -1105000000 | K75: Penarikan Margin | L75: =-L59 -> -1105000000
G76: Dana Tersedia/Kurang | H76: =H72+H73+H74+H75 -> -115670930 | K76: PO Baru | L76: =-K70 -> -6648250000
K77: Dana tersedia | L77: =L73+L74+L75+L76 -> 304947570
G78: PO & margin akan cair | H78: =SUM(K29:K41,O29:O41) -> 7923876000 | I78: Baris 18-29 | N78: Total
K79: Bulan | L79: Margin yang akan diterima | M79: Modal yang akan diterima | N79: =L80+M80 -> 3062580000
K80: 46023 | L80: =SUM(Z31,Z38:Z41) -> 510430000 | M80: =SUM(K31,K38:K41) -> 2552150000 | N80: =L81+M81 -> 2692265000
H81: 130000000 | K81: 46054 | L81: =SUM(Z32:Z33,Z42) -> 352002500 | M81: =SUM(K32:K33,K42) -> 2340262500 | N81: =SUM(N79:N80) -> 5754845000
K82: Margin yang akan diterima | L82: =SUM(L80:L81) -> 862432500 | M82: =SUM(M80:M81) -> 4892412500
N83: =L84+M84 -> 3312705000
K84: Belum Terkirim | L84: =SUM(AA35:AA37,AA43:AA49) -> 501867500 | M84: =SUM(K35:K37,K43:K49) -> 2810837500 | N84: =N81+N83 -> 9067550000
K85: Total Margin Yg Akan diterim | L85: =L82+L84 -> 1364300000 | M85: =M82+M84 -> 7703250000

Sheet Summary V.4 (PO833)
C1: LIST INVESTASI
G7: =Detail!E2 -> 4 | I7: =Detail!F2 -> 5 | J7: =Detail!G2 -> 6 | K7: =Detail!H2 -> 7 | M7: =Detail!I2 -> 8
A10: NO | B10: Date | C10: No. PO | D10: Status | E10: Total Payment | F10: Nama Barang | G10: =Detail!E3 -> Qty | H10: Harga Beli (only added if Margin is set) | I10: =Detail!F3 -> Harga | J10: Total PO | K10: Modal | L10: Margin Per Unit | M10: =Detail!I3 -> Margin | N10: Add Margin | O10: Total Margin | P10: Invoice /DO | X10: DO Total | Y10: DO Outstanding | Z10: Margin | AA10: AR MARGIN | AB10: Del Time | AC10: Invoice date | AD10: adjusting TOP 30 Days | AE10: adjusting TOP 60 Days | AF10: Payment Date | AG10: Status | AH10: Notes | AI10: Notes | AJ10: Tari | AK10: Total Margin TARI | AL10: Selisih
P11: Jul | Q11: Aug | R11: Sep | S11: Oct | T11: Nov | U11: Dec | V11: Jan | W11: Add Margin (by Agreement) | AH11: Notes | AI11: Notes
A12: 1 | B12: =VLOOKUP($C12,Detail!$B$4:$Q$21,2,0) -> 45839 | C12: 5200954145 | D12: Close | E12: =O12+K12 -> 270000000 | F12: Top Frame 800 | G12: =SUMIF(Detail!$B$4:$B$21,'Summary V.4 (PO833)'!$C12,Detail!$E$4:$E$21) -> 2 | I12: =VLOOKUP($C12,Detail!$B$4:$Q$21,5,0) -> 225000000 | J12: =G12*I12 -> 450000000 | K12: =SUMIF(Detail!$B$4:$B$21,'Summary V.4 (PO833)'!C12,Detail!$H$4:$H$21) -> 225000000 | L12: =(K12*20%)/G12 -> 22500000 | M12: =K12*20% -> 45000000 | O12: =SUM(M12:N12) -> 45000000 | P12: =G12 -> 2 | X12: =SUM(P12:U12) -> 2 | Y12: =G12-X12 -> 0 | Z12: =L12*X12 -> 45000000 | AA12: =M12-Z12 -> 0 | AB12: 45861 | AC12: 45863 | AD12: 45894 | AG12: Close | AJ12: =VLOOKUP(C12,investasi!$B$5:$G$18,6,0) -> 45000000 | AK12: =O12 -> 45000000 | AL12: =AJ12-AK12 -> 0
A13: 2 | B13: =VLOOKUP($C13,Detail!$B$4:$Q$21,2,0) -> 45839 | C13: 5200954149 | D13: Close | E13: =O13+K13 -> 405000000 | F13: Top Frame 800 | G13: =SUMIF(Detail!$B$4:$B$21,'Summary V.4 (PO833)'!$C13,Detail!$E$4:$E$21) -> 3 | I13: =VLOOKUP($C13,Detail!$B$4:$Q$21,5,0) -> 225000000 | J13: =G13*I13 -> 675000000 | K13: =SUMIF(Detail!$B$4:$B$21,'Summary V.4 (PO833)'!C13,Detail!$H$4:$H$21) -> 337500000 | L13: =(K13*20%)/G13 -> 22500000 | M13: =K13*20% -> 67500000 | O13: =SUM(M13:N13) -> 67500000 | P13: =G13 -> 3 | X13: =SUM(P13:U13) -> 3 | Y13: =G13-X13 -> 0 | Z13: =L13*X13 -> 67500000 | AA13: =M13-Z13 -> 0 | AB13: 45861 | AC13: 45863 | AD13: 45894 | AG13: Close | AJ13: =VLOOKUP(C13,investasi!$B$5:$G$18,6,0) -> 67500000 | AK13: =O13 -> 67500000 | AL13: =AJ13-AK13 -> 0
A14: 3 | B14: =VLOOKUP($C14,Detail!$B$4:$Q$21,2,0) -> 45839 | C14: 5200954160 | D14: Close | E14: =O14+K14 -> 405000000 | F14: Top Frame 800 | G14: =SUMIF(Detail!$B$4:$B$21,'Summary V.4 (PO833)'!$C14,Detail!$E$4:$E$21) -> 3 | I14: =VLOOKUP($C14,Detail!$B$4:$Q$21,5,0) -> 225000000 | J14: =G14*I14 -> 675000000 | K14: =SUMIF(Detail!$B$4:$B$21,'Summary V.4 (PO833)'!C14,Detail!$H$4:$H$21) -> 337500000 | L14: =(K14*20%)/G14 -> 22500000 | M14: =K14*20% -> 67500000 | O14: =SUM(M14:N14) -> 67500000 | P14: =G14 -> 3 | X14: =SUM(P14:U14) -> 3 | Y14: =G14-X14 -> 0 | Z14: =L14*X14 -> 67500000 | AA14: =M14-Z14 -> 0 | AB14: 45861 | AC14: 45863 | AD14: 45894 | AG14: Close | AJ14: =VLOOKUP(C14,investasi!$B$5:$G$18,6,0) -> 67500000 | AK14: =O14 -> 67500000 | AL14: =AJ14-AK14 -> 0
A15: 4 | B15: =VLOOKUP($C15,Detail!$B$4:$Q$21,2,0) -> 45870 | C15: 5200954165 | D15: Close | E15: =O15+K15 -> 405000000 | F15: Top Frame 800 | G15: =SUMIF(Detail!$B$4:$B$21,'Summary V.4 (PO833)'!$C15,Detail!$E$4:$E$21) -> 3 | I15: =VLOOKUP($C15,Detail!$B$4:$Q$21,5,0) -> 225000000 | J15: =G15*I15 -> 675000000 | K15: =SUMIF(Detail!$B$4:$B$21,'Summary V.4 (PO833)'!C15,Detail!$H$4:$H$21) -> 337500000 | L15: =(K15*20%)/G15 -> 22500000 | M15: =K15*20% -> 67500000 | O15: =SUM(M15:N15) -> 67500000 | Q15: =G15 -> 3 | X15: =SUM(P15:U15) -> 3 | Y15: =G15-X15 -> 0 | Z15: =L15*X15 -> 67500000 | AA15: =M15-Z15 -> 0 | AB15: 45868 | AC15: 45873 | AD15: 45904 | AG15: Close | AJ15: =VLOOKUP(C15,investasi!$B$5:$G$18,6,0) -> 67500000 | AK15: =O15 -> 67500000 | AL15: =AJ15-AK15 -> 0
A16: 5 | B16: =VLOOKUP($C16,Detail!$B$4:$Q$21,2,0) -> 45870 | C16: 5200954167 | D16: Close | E16: =O16+K16 -> 405000000 | F16: Top Frame 800 | G16: =SUMIF(Detail!$B$4:$B$21,'Summary V.4 (PO833)'!$C16,Detail!$E$4:$E$21) -> 3 | I16: =VLOOKUP($C16,Detail!$B$4:$Q$21,5,0) -> 225000000 | J16: =G16*I16 -> 675000000 | K16: =SUMIF(Detail!$B$4:$B$21,'Summary V.4 (PO833)'!C16,Detail!$H$4:$H$21) -> 337500000 | L16: =(K16*20%)/G16 -> 22500000 | M16: =K16*20% -> 67500000 | O16: =SUM(M16:N16) -> 67500000 | Q16: =G16 -> 3 | X16: =SUM(P16:U16) -> 3 | Y16: =G16-X16 -> 0 | Z16: =L16*X16 -> 67500000 | AA16: =M16-Z16 -> 0 | AB16: 45868 | AC16: 45873 | AD16: 45904 | AG16: Close | AJ16: =VLOOKUP(C16,investasi!$B$5:$G$18,6,0) -> 67500000 | AK16: =O16 -> 67500000 | AL16: =AJ16-AK16 -> 0
A17: 6 | B17: =VLOOKUP($C17,Detail!$B$4:$Q$21,2,0) -> 45870 | C17: 5200954168 | D17: Close | E17: =O17+K17 -> 270000000 | F17: Top Frame 800 | G17: =SUMIF(Detail!$B$4:$B$21,'Summary V.4 (PO833)'!$C17,Detail!$E$4:$E$21) -> 2 | I17: =VLOOKUP($C17,Detail!$B$4:$Q$21,5,0) -> 225000000 | J17: =G17*I17 -> 450000000 | K17: =SUMIF(Detail!$B$4:$B$21,'Summary V.4 (PO833)'!C17,Detail!$H$4:$H$21) -> 225000000 | L17: =(K17*20%)/G17 -> 22500000 | M17: =K17*20% -> 45000000 | O17: =SUM(M17:N17) -> 45000000 | Q17: =G17 -> 2 | X17: =SUM(P17:U17) -> 2 | Y17: =G17-X17 -> 0 | Z17: =L17*X17 -> 45000000 | AA17: =M17-Z17 -> 0 | AB17: 45868 | AC17: 45873 | AD17: 45904 | AG17: Close | AJ17: =VLOOKUP(C17,investasi!$B$5:$G$18,6,0) -> 45000000 | AK17: =O17 -> 45000000 | AL17: =AJ17-AK17 -> 0
A18: 7 | B18: =VLOOKUP($C18,Detail!$B$4:$Q$21,2,0) -> 45870 | C18: 5200954169 | D18: Close | E18: =O18+K18 -> 270000000 | F18: Top Frame 800 | G18: =SUMIF(Detail!$B$4:$B$21,'Summary V.4 (PO833)'!$C18,Detail!$E$4:$E$21) -> 2 | I18: =VLOOKUP($C18,Detail!$B$4:$Q$21,5,0) -> 225000000 | J18: =G18*I18 -> 450000000 | K18: =SUMIF(Detail!$B$4:$B$21,'Summary V.4 (PO833)'!C18,Detail!$H$4:$H$21) -> 225000000 | L18: =(K18*20%)/G18 -> 22500000 | M18: =K18*20% -> 45000000 | O18: =SUM(M18:N18) -> 45000000 | Q18: =G18 -> 2 | X18: =SUM(P18:U18) -> 2 | Y18: =G18-X18 -> 0 | Z18: =L18*X18 -> 45000000 | AA18: =M18-Z18 -> 0 | AB18: 45868 | AC18: 45873 | AD18: 45904 | AG18: Close | AJ18: =VLOOKUP(C18,investasi!$B$5:$G$18,6,0) -> 45000000 | AK18: =O18 -> 45000000 | AL18: =AJ18-AK18 -> 0
A19: 8 | B19: =VLOOKUP($C19,Detail!$B$4:$Q$25,2,0) -> 45877 | C19: 5200777098 | D19: Close | E19: =O19+K19 -> 689519400 | F19: DVAR 3771-B0-20D-PPC Statcom Steel Support | G19: =SUMIF(Detail!$B$4:$B$25,'Summary V.4 (PO833)'!$C19,Detail!$E$4:$E$25) -> 1 | I19: =VLOOKUP($C19,Detail!$B$4:$Q$25,5,0) -> 1149199000 | J19: =G19*I19 -> 1149199000 | K19: =SUMIF(Detail!$B$4:$B$25,'Summary V.4 (PO833)'!C19,Detail!$H$4:$H$25) -> 574599500 | L19: =(K19*20%)/G19 -> 114919900 | M19: =K19*20% -> 114919900 | O19: =SUM(M19:N19) -> 114919900 | Q19: 0 | R19: 1 | X19: =SUM(P19:U19) -> 1 | Y19: =G19-X19 -> 0 | Z19: =L19*X19 -> 114919900 | AA19: =M19-Z19 -> 0 | AB19: 45930 | AC19: =AB19+7 -> 45937 | AD19: =AC19+30 -> 45967 | AE19: =AC19+60 -> 45997 | AG19: Close | AJ19: =VLOOKUP(C19,investasi!$B$5:$G$18,6,0) -> 57248700 | AK19: =O19 -> 114919900 | AL19: =AJ19-AK19 -> -57671200 | AM19: Selisih di unit Qty, di catatan pak mushafa 2 unit(1 sudah terbayar , 1 unit belum terbayar ), dicatatan TARI 1 Unit
A20: 9 | B20: =VLOOKUP($C20,Detail!$B$4:$Q$25,2,0) -> 45877 | C20: 5200776987 | D20: Close | E20: =O20+K20 -> 270000000 | F20: Top Frame 800 | G20: =SUMIF(Detail!$B$4:$B$25,'Summary V.4 (PO833)'!$C20,Detail!$E$4:$E$25) -> 2 | I20: =VLOOKUP($C20,Detail!$B$4:$Q$25,5,0) -> 225000000 | J20: =G20*I20 -> 450000000 | K20: =SUMIF(Detail!$B$4:$B$25,'Summary V.4 (PO833)'!C20,Detail!$H$4:$H$25) -> 225000000 | L20: =(K20*20%)/G20 -> 22500000 | M20: =K20*20% -> 45000000 | O20: =SUM(M20:N20) -> 45000000 | Q20: 0 | R20: 2 | X20: =SUM(P20:U20) -> 2 | Y20: =G20-X20 -> 0 | Z20: =L20*X20 -> 45000000 | AA20: =M20-Z20 -> 0 | AB20: 45923 | AC20: =AB20+7 -> 45930 | AD20: =AC20+30 -> 45960 | AE20: =AC20+60 -> 45990 | AG20: Close | AJ20: =VLOOKUP(C20,investasi!$B$5:$G$18,6,0) -> 45000000 | AK20: =O20 -> 45000000 | AL20: =AJ20-AK20 -> 0
A21: 10 | B21: =VLOOKUP($C21,Detail!$B$4:$Q$110,2,0) -> 45880 | C21: 5200777132 | D21: Close | E21: =O21+K21 -> 457169750 | F21: Leser Barrier MK 01-F3004973 | G21: 20 | I21: =VLOOKUP($C21,Detail!$B$4:$Q$25,5,0) -> 40457500 | J21: =G21*I21 -> 809150000 | K21: =J21*50% -> 404575000 | L21: =(K21*13%)/G21 -> 2629737.5 | M21: =K21*13% -> 52594750 | O21: =SUM(M21:N21) -> 52594750 | Q21: 0 | S21: 20 | X21: =SUM(P21:U21) -> 20 | Y21: =G21-X21 -> 0 | Z21: =L21*X21 -> 52594750 | AA21: =M21-Z21 -> 0 | AB21: 45922 | AC21: =AB21+7 -> 45929 | AD21: =AC21+30 -> 45959 | AE21: =AC21+60 -> 45989 | AG21: Close | AJ21: =VLOOKUP(C21,investasi!$B$5:$G$18,6,0) -> 52594750 | AK21: =O21 -> 52594750 | AL21: =AJ21-AK21 -> 0
A22: 11 | B22: =Detail!$C$45 -> 45891 | C22: =Detail!$B$45 -> 5200972695 | D22: Close | E22: =O22+K22 -> 504000000 | F22: Tangki | G22: 8 | H22: 75000000 | I22: 100500000 | J22: =G22*I22 -> 804000000 | K22: =J22*50% -> 402000000 | L22: 12750000 | M22: =G22*L22 -> 102000000 | O22: =SUM(M22:N22) -> 102000000 | Q22: 0 | R22: 8 | W22: Margin was arranged 25mil/ea | X22: =SUM(P22:U22) -> 8 | Y22: =G22-X22 -> 0 | Z22: =L22*X22 -> 102000000 | AA22: =M22-Z22 -> 0 | AB22: 45925 | AC22: =AB22+7 -> 45932 | AD22: =AC22+30 -> 45962 | AE22: =AC22+60 -> 45992 | AG22: Close | AJ22: =VLOOKUP(C22,investasi!$B$5:$G$18,6,0) -> 80400000 | AK22: =O22 -> 102000000 | AL22: =AJ22-AK22 -> -21600000 | AM22: Selisih margin
A23: 12 | B23: 45897 | C23: =Detail!B53 -> 5200777558 | D23: Close | E23: =O23+K23 -> 411000000 | F23: Top Frame 2630 | G23: 1 | I23: =Detail!F53 -> 685000000 | J23: =G23*I23 -> 685000000 | K23: =J23*50% -> 342500000 | L23: =(K23*20%)/G23 -> 68500000 | M23: =K23*20% -> 68500000 | O23: =SUM(M23:N23) -> 68500000 | R23: 1 | X23: =SUM(P23:U23) -> 1 | Y23: =G23-X23 -> 0 | Z23: =L23*X23 -> 68500000 | AA23: =M23-Z23 -> 0 | AB23: 45923 | AC23: =AB23+7 -> 45930 | AD23: =AC23+30 -> 45960 | AE23: =AC23+60 -> 45990 | AG23: Close | AJ23: =VLOOKUP(C23,investasi!$B$5:$G$18,6,0) -> 68500000 | AK23: =O23 -> 68500000 | AL23: =AJ23-AK23 -> 0
A24: 13 | B24: 45901 | C24: =Detail!B54 -> 5200777559 | D24: Close | E24: =O24+K24 -> 270000000 | F24: Top Frame 800 | G24: 2 | I24: =Detail!F54 -> 225000000 | J24: =G24*I24 -> 450000000 | K24: =J24*50% -> 225000000 | L24: =(K24*20%)/G24 -> 22500000 | M24: =K24*20% -> 45000000 | O24: =SUM(M24:N24) -> 45000000 | R24: 2 | X24: =SUM(P24:U24) -> 2 | Y24: =G24-X24 -> 0 | Z24: =L24*X24 -> 45000000 | AA24: =M24-Z24 -> 0 | AB24: 45925 | AC24: =AB24+7 -> 45932 | AD24: =AC24+30 -> 45962 | AE24: =AC24+60 -> 45992 | AG24: Close | AJ24: =VLOOKUP(C24,investasi!$B$5:$G$18,6,0) -> 45000000 | AK24: =O24 -> 45000000 | AL24: =AJ24-AK24 -> 0
A25: 14 | B25: 45909 | C25: =Detail!$B$56 -> 5200777758 | D25: Close | E25: =O25+K25 -> 1338628920 | F25: Pipe Spool | G25: 1 | I25: =Detail!F56 -> 2231048200 | J25: =G25*I25 -> 2231048200 | K25: =J25*50% -> 1115524100 | L25: =(K25*20%)/G25 -> 223104820 | M25: =K25*20% -> 223104820 | O25: =SUM(M25:N25) -> 223104820 | R25: 1 | X25: =SUM(P25:U25) -> 1 | Y25: =G25-X25 -> 0 | Z25: =L25*X25 -> 223104820 | AA25: =M25-Z25 -> 0 | AB25: 45930 | AC25: =AB25+7 -> 45937 | AD25: =AC25+30 -> 45967 | AE25: =AC25+60 -> 45997 | AG25: Close | AJ25: =VLOOKUP(C25,investasi!$B$5:$G$18,6,0) -> 223104820 | AK25: =O25 -> 223104820 | AL25: =AJ25-AK25 -> 0
A26: 15 | B26: 45909 | C26: =Detail!$B$58 -> 5200778319 | D26: Close | E26: =O26+K26 -> 270000000 | F26: =Detail!$D$58 -> Top Frame 800 | G26: 2 | I26: =Detail!$F$58 -> 225000000 | J26: =G26*I26 -> 450000000 | K26: =J26*50% -> 225000000 | L26: =(K26*20%)/G26 -> 22500000 | M26: =K26*20% -> 45000000 | O26: =SUM(M26:N26) -> 45000000 | R26: 2 | X26: =SUM(P26:U26) -> 2 | Y26: =G26-X26 -> 0 | Z26: =L26*X26 -> 45000000 | AA26: =M26-Z26 -> 0 | AB26: 45940 | AC26: =AB26+7 -> 45947 | AD26: =AC26+30 -> 45977 | AE26: =AC26+60 -> 46007 | AG26: Close | AJ26: =VLOOKUP(C26,investasi!$B$23:$G$26,6,0) -> 45000000 | AK26: =O26 -> 45000000 | AL26: =AJ26-AK26 -> 0
A27: 16 | B27: 45915 | C27: 5200778328 | D27: Close | E27: =O27+K27 -> 477261000 | F27: Top Frame 2630 | G27: 1 | I27: =Detail!F59 -> 685000000 | J27: =G27*I27 -> 685000000 | K27: =J27*50% -> 342500000 | L27: =(K27*20%)/G27 -> 68500000 | M27: =(K27*20%)+H27 -> 68500000 | N27: 66261000 | O27: =SUM(M27:N27) -> 134761000 | R27: 1 | X27: =SUM(P27:U27) -> 1 | Y27: =G27-X27 -> 0 | Z27: =L27*X27+N27 -> 134761000 | AA27: =M27+N27-Z27 -> 0 | AB27: 45940 | AC27: =AB27+7 -> 45947 | AD27: =AC27+30 -> 45977 | AE27: =AC27+60 -> 46007 | AG27: Close | AJ27: =VLOOKUP(C27,investasi!$B$23:$G$26,6,0)+investasi!I24 -> 134761000 | AK27: =O27 -> 134761000 | AL27: =AJ27-AK27 -> 0
D28: Close | E28: =O28+K28 -> 0 | X28: =SUM(P28:U28) -> 0 | AG28: Close
A29: 18 | B29: 45965 | C29: =Detail!B60 -> 5200779815 | D29: Close | E29: =O29+K29 -> 477261000 | F29: Top Frame 2630 | G29: 1 | I29: =Detail!F60 -> 685000000 | J29: =G29*I29 -> 685000000 | K29: =J29*50% -> 342500000 | L29: =(K29*20%)/G29 -> 68500000 | M29: =(K29*20%)+H29 -> 68500000 | N29: 66261000 | O29: =SUM(M29:N29) -> 134761000 | T29: 1 | X29: =SUM(P29:U29) -> 1 | Y29: =G29-X29 -> 0 | Z29: =L29*X29+N29 -> 134761000 | AA29: =M29+N29-Z29 -> 0 | AB29: 45989 | AC29: 46008 | AD29: 46034 | AE29: =AC29+30 -> 46038 | AF29: 46034 | AG29: Close | AH29: Payment 12 Jan 2026 | AJ29: =VLOOKUP(C29,investasi!$B$23:$G$26,6,0)+investasi!I26 -> 134761000 | AK29: =O29 -> 134761000 | AL29: =AJ29-AK29 -> 0
A30: =A29+1 -> 19 | B30: 45977 | C30: 5200988854 | D30: Close | E30: =O30+K30 -> 449145000 | F30: Trench Grade | G30: 150 | I30: 4990500 | J30: =G30*I30 -> 748575000 | K30: =J30*50% -> 374287500 | L30: =(K30*20%)/G30 -> 499050 | M30: =(K30*20%)+H30 -> 74857500 | O30: =SUM(M30:N30) -> 74857500 | T30: 150 | X30: =SUM(P30:U30) -> 150 | Y30: =G30-X30 -> 0 | Z30: =L30*X30+N30 -> 74857500 | AA30: =M30+N30-Z30 -> 0 | AB30: 45989 | AC30: 46008 | AD30: 46034 | AE30: =AC30+30 -> 46038 | AF30: 46034 | AG30: Close | AH30: Payment 12 Jan 2026
A31: =A30+1 -> 20 | B31: 45977 | C31: 5200989664 | D31: Close | E31: =O31+K31 -> 1266000000 | F31: Grating Ditch | G31: 100 | I31: 21100000 | J31: =G31*I31 -> 2110000000 | K31: =J31*50% -> 1055000000 | L31: =(K31*20%)/G31 -> 2110000 | M31: =(K31*20%)+H31 -> 211000000 | O31: =SUM(M31:N31) -> 211000000 | U31: 100 | X31: =SUM(P31:U31) -> 100 | Y31: =G31-X31 -> 0 | Z31: =L31*X31+N31 -> 211000000 | AA31: =M31+N31-Z31 -> 0 | AB31: 46031 | AC31: 46031 | AD31: =AB31+30 -> 46061 | AG31: Delivered
A32: =A31+1 -> 21 | B32: 45977 | C32: 5200989665 | D32: Delivered | F32: Grating Ditch | G32: 100 | I32: 21100000 | J32: =G32*I32 -> 2110000000 | K32: =J32*50% -> 1055000000 | L32: =(K32*20%)/G32 -> 2110000 | M32: =(K32*20%)+H32 -> 211000000 | O32: =SUM(M32:N32) -> 211000000 | U32: 100 | X32: =SUM(P32:V32) -> 100 | Y32: =G32-X32 -> 0 | Z32: =L32*X32+N32 -> 211000000 | AA32: =M32+N32-Z32 -> 0 | AB32: 46030 | AC32: 46030 | AD32: =AB32+30 -> 46060 | AG32: Delivered
A33: =A32+1 -> 22 | B33: 45977 | C33: 5200989666 | D33: Delivered | F33: Grating Ditch | G33: 110 | I33: 21100000 | J33: =G33*I33 -> 2321000000 | K33: =J33*50% -> 1160500000 | L33: =(K33*20%)/G33 -> 2110000 | M33: =(K33*20%)+H33 -> 232100000 | O33: =SUM(M33:N33) -> 232100000 | V33: 55 | X33: =SUM(P33:V33) -> 55 | Y33: 0 | Z33: =L33*X33+N33 -> 116050000 | AA33: 0 | AB33: 46027 | AC33: 45676 | AD33: =AC33+30 -> 45706 | AG33: Delivered | AH33: Partial Deliv 55 ea
D34: Delivered | V34: 55 | X34: =SUM(P34:V34) -> 55 | Y34: 0 | Z34: =X34*L33+N33 -> 116050000 | AA34: 0 | AB34: 46036 | AC34: 45676 | AD34: =AC34+30 -> 45706 | AG34: Delivered | AH34: Partial Deliv 55 ea
A35: =A33+1 -> 23 | B35: 45981 | C35: 5200992759 | D35: Delivered | F35: Tanki | G35: 6 | I35: 100500000 | J35: =G35*I35 -> 603000000 | K35: =J35*50% -> 301500000 | L35: 12750000 | M35: =L35*G35 -> 76500000 | O35: =SUM(M35:N35) -> 76500000 | V35: 6 | X35: =SUM(P35:V35) -> 6 | Y35: =G35-X35 -> 0 | Z35: =L35*X35+N35 -> 76500000 | AA35: =M35+N35-Z35 -> 0 | AB35: 46048 | AC35: 46048 | AD35: =AC35+30 -> 46078 | AG35: Delivered | AH35: Terkirim
A36: =A35+1 -> 24 | B36: 45985 | C36: 5200991260 | D36: Delivered | F36: Trench Grade | G36: 150 | I36: 4990500 | J36: =G36*I36 -> 748575000 | K36: =J36*50% -> 374287500 | L36: =(K36*20%)/G36 -> 499050 | M36: =(K36*20%)+H36 -> 74857500 | O36: =SUM(M36:N36) -> 74857500 | V36: =G36 -> 150 | X36: =SUM(P36:U36) -> 0 | Y36: =G36-X36 -> 150 | Z36: =L36*X36+N36 -> 0 | AA36: =M36+N36-Z36 -> 74857500 | AB36: 46041 | AC36: 46041 | AE36: =AB36+60 -> 46101 | AG36: Delivered | AH36: Terkirim
A37: =A36+1 -> 25 | B37: 45985 | C37: 5200991264 | D37: Delivered | F37: Trench Grade | G37: 150 | I37: 4990500 | J37: =G37*I37 -> 748575000 | K37: =J37*50% -> 374287500 | L37: =(K37*20%)/G37 -> 499050 | M37: =(K37*20%)+H37 -> 74857500 | O37: =SUM(M37:N37) -> 74857500 | V37: =G37 -> 150 | X37: =SUM(P37:U37) -> 0 | Y37: =G37-X37 -> 150 | Z37: =L37*X37+N37 -> 0 | AA37: =M37+N37-Z37 -> 74857500 | AB37: 46041 | AC37: 46041 | AE37: =AB37+60 -> 46101 | AG37: Delivered | AH37: Terkirim
A38: =A37+1 -> 26 | B38: 45986 | C38: 5200991456 | D38: Delivered | F38: Trench Grade | G38: 150 | I38: 4990500 | J38: =G38*I38 -> 748575000 | K38: =J38*50% -> 374287500 | L38: =(K38*20%)/G38 -> 499050 | M38: =(K38*20%)+H38 -> 74857500 | O38: =SUM(M38:N38) -> 74857500 | U38: =G38 -> 150 | X38: =SUM(P38:U38) -> 150 | Y38: =G38-X38 -> 0 | Z38: =L38*X38+N38 -> 74857500 | AA38: =M38+N38-Z38 -> 0 | AB38: 46036 | AC38: 46036 | AE38: =AB38+60 -> 46096 | AG38: Delivered
A39: =A38+1 -> 27 | B39: 45986 | C39: 5200991458 | D39: Delivered | F39: Trench Grade | G39: 150 | I39: 4990500 | J39: =G39*I39 -> 748575000 | K39: =J39*50% -> 374287500 | L39: =(K39*20%)/G39 -> 499050 | M39: =(K39*20%)+H39 -> 74857500 | O39: =SUM(M39:N39) -> 74857500 | U39: =G39 -> 150 | X39: =SUM(P39:U39) -> 150 | Y39: =G39-X39 -> 0 | Z39: =L39*X39+N39 -> 74857500 | AA39: =M39+N39-Z39 -> 0 | AB39: 46036 | AC39: 46036 | AE39: =AB39+60 -> 46096 | AG39: Delivered
A40: =A39+1 -> 28 | B40: 45986 | C40: 5200991502 | D40: Delivered | F40: Trench Grade | G40: 150 | I40: 4990500 | J40: =G40*I40 -> 748575000 | K40: =J40*50% -> 374287500 | L40: =(K40*20%)/G40 -> 499050 | M40: =(K40*20%)+H40 -> 74857500 | O40: =SUM(M40:N40) -> 74857500 | U40: =G40 -> 150 | X40: =SUM(P40:U40) -> 150 | Y40: =G40-X40 -> 0 | Z40: =L40*X40+N40 -> 74857500 | AA40: =M40+N40-Z40 -> 0 | AB40: 46030 | AC40: 46030 | AE40: =AB40+60 -> 46090 | AG40: Delivered
A41: =A40+1 -> 29 | B41: 45986 | C41: 5200991503 | D41: Delivered | F41: Trench Grade | G41: 150 | I41: 4990500 | J41: =G41*I41 -> 748575000 | K41: =J41*50% -> 374287500 | L41: =(K41*20%)/G41 -> 499050 | M41: =(K41*20%)+H41 -> 74857500 | O41: =SUM(M41:N41) -> 74857500 | U41: =G41 -> 150 | X41: =SUM(P41:U41) -> 150 | Y41: =G41-X41 -> 0 | Z41: =L41*X41+N41 -> 74857500 | AA41: =M41+N41-Z41 -> 0 | AB41: 46030 | AC41: 46030 | AE41: =AB41+60 -> 46090 | AG41: Delivered
A42: =A41+1 -> 30 | B42: 46372 | C42: 5200991553 | D42: Delivered | F42: Trench Grade | G42: 50 | I42: 4990500 | J42: =G42*I42 -> 249525000 | K42: =J42*50% -> 124762500 | L42: =(K42*20%)/G42 -> 499050 | M42: =(K42*20%)+H42 -> 24952500 | O42: =SUM(M42:N42) -> 24952500 | U42: =G42 -> 50 | X42: =SUM(P42:U42) -> 50 | Y42: =G42-X42 -> 0 | Z42: =L42*X42+N42 -> 24952500 | AA42: =M42+N42-Z42 -> 0 | AB42: 46036 | AC42: 46036 | AE42: =AB42+60 -> 46096 | AG42: Delivered
A43: =A42+1 -> 31 | B43: 46021 | C43: 5200996833 | D43: Open | F43: new barge landing facility | G43: 1 | I43: 1188000000 | J43: =G43*I43 -> 1188000000 | K43: =J43*50% -> 594000000 | L43: =(K43*20%)/G43 -> 118800000 | M43: =(K43*20%)+H43 -> 118800000 | O43: =SUM(M43:N43) -> 118800000 | X43: 0 | Y43: 0 | Z43: 0 | AA43: =M43+N43-Z43 -> 118800000 | AG43: Open | AH43: Blm Terkirim
B44: 46044 | C44: 5201004137 | D44: Open | F44: Marine Maintenance Jetty | G44: 1 | I44: 926640000 | K44: =J44*50% -> 0 | L44: =K44*20% -> 0 | M44: =(K44*20%)+H44 -> 0 | O44: =SUM(M44:N44) -> 0 | X44: 0 | Y44: 0 | Z44: 0 | AA44: =M44+N44-Z44 -> 0 | AG44: Open | AH44: Blm Terkirim
B45: 46045 | C45: 5201004344 | D45: Open | F45: Trench Grade | G45: 50 | I45: =249525000/G45 -> 4990500 | K45: =J45*50% -> 0 | L45: =(K45/G45)*20% -> 0 | M45: =(K45*20%)+H45 -> 0 | O45: =SUM(M45:N45) -> 0 | X45: 0 | Y45: 0 | Z45: 0 | AA45: =M45+N45-Z45 -> 0 | AG45: Open | AH45: Blm Terkirim
B46: 46051 | C46: 5201005549 | D46: Open | F46: Top Frame 800 | G46: 2 | I46: 225000000 | K46: =J46*50% -> 0 | L46: =(K46/G46)*20% -> 0 | M46: =L46*G46 -> 0 | O46: =SUM(M46:N46) -> 0 | X46: 0 | Y46: 0 | Z46: 0 | AA46: =M46+N46-Z46 -> 0 | AH46: Blm Terkirim
B47: 46051 | C47: 5201005550 | D47: Open | F47: Top Frame 800 | G47: 2 | I47: 225000000 | K47: =J47*50% -> 0 | L47: =(K47/G47)*20% -> 0 | M47: =L47*G47 -> 0 | O47: =SUM(M47:N47) -> 0 | X47: 0 | Y47: 0 | Z47: 0 | AA47: =M47+N47-Z47 -> 0 | AH47: Blm Terkirim
B48: 46051 | C48: 5201005551 | D48: Open | F48: Muck Bumper | G48: 16 | I48: 37000000 | K48: =J48*50% -> 0 | L48: =(K48/G48)*20% -> 0 | M48: =K48*20% -> 0 | O48: =SUM(M48:N48) -> 0 | X48: 0 | Y48: 0 | Z48: 0 | AA48: =M48+N48-Z48 -> 0 | AH48: Blm Terkirim
B49: 46051 | C49: 5201005552 | D49: Open | F49: Muck Bumper | G49: 16 | I49: 37000000 | K49: =J49*50% -> 0 | L49: =(K49/G49)*20% -> 0 | M49: =K49*20% -> 0 | O49: =SUM(M49:N49) -> 0 | X49: 0 | Y49: 0 | Z49: 0 | AA49: =M49+N49-Z49 -> 0 | AH49: Blm Terkirim
C52: TOTAL MARGIN | J52: =SUM(J12:J50) -> 26269947200 | K52: =SUM(K12:K50) -> 13134973600 | M52: =SUM(M12:M50) -> 2636474470 | N52: =SUM(N12:N50) -> 132522000 | O52: =SUM(O12:O50) -> 2768996470 | Z52: =SUM(Z12:Z50) -> 2500481470 | AA52: =SUM(AA12:AA50) -> 268515000
G54: A | I54: B | J54: C | K54: D | L54: E | M54: F=A+B+C-D-E
G55: TGL | H55: Modal Setor Awal | I55: Margin | J55: Pencairan Modal | K55: Modal PO Baru | L55: Penarikan | M55: Dana Tersedia
G56: 45839 | H56: =SUM(K12:K14) -> 900000000 | I56: =SUM(Z12:Z14) -> 180000000 | M56: =H56+I56 -> 1080000000
G57: 45870 | H57: =SUM(K15:K18) -> 1125000000 | I57: =SUM(Z15:Z18) -> 225000000 | K57: =SUM(K19:K22) -> 1606174500 | M57: =M56+H57+I57+J57-K57-L57 -> 823825500
G58: 45901 | H58: 1426698600 | K58: =SUM(K23:K27) -> 2250524100 | M58: =M57+H58+I58+J58-K58 -> 0
G59: 45931 | K59: =K29+K28 -> 342500000 | M59: =M58+H59+I59+J59-K59 -> -342500000
G60: 45962 | I60: =SUM(O19:O28) -> 830880470 | K60: =-SUM(K19:K28)+SUM(K30:K41) -> 2335313900 | L60: 1105000000 | M60: =M59+H60+I60+J60-K60-L60 -> -2951933430
G61: 46007 | H61: 1300000000 | K61: =K42+K43+K50 -> 718762500 | M61: =M60+H61+I61+J61-K61-L61 -> -2370695930
G62: 46014 | H62: 250000000 | M62: =M61+H62+I62+J62-K62-L62 -> -2120695930
G63: 46015 | H63: 250000000 | M63: =M62+H63+I63+J63-K63-L63 -> -1870695930
B64: Total Tf Investasi | C64: =SUM(H71) -> 6401698600 | G64: 46016 | H64: 250000000 | M64: =M63+H64+I64+J64-K64-L64 -> -1620695930
B65: Margin diterima (Close) | C65: =SUM(O12:O31) -> 1656498970 | G65: 46017 | H65: 250000000 | M65: =M64+H65+I65+J65-K65-L65 -> -1370695930
B66: Total Modal PO | C66: =-K52 -> -13134973600 | G66: 46018 | H66: 250000000 | M66: =M65+H66+I66+J66-K66-L66 -> -1120695930
B67: Modal Kembali PO (close) | C67: =SUM(K12:K31) -> 7653486100 | G67: 46019 | H67: 250000000 | M67: =M66+H67+I67+J67-K67-L67 -> -870695930
B68: Total dana | C68: =SUM(C64:C67) -> 2576710070 | G68: 46020 | H68: 150000000 | M68: =M67+H68+I68+J68-K68-L68 -> -720695930
B69: penarikan | C69: =L60 -> 1105000000 | G69: 46034 | I69: =SUM(O29:O31) -> 420618500 | K69: =-SUM(K29:K31) -> -1771787500 | M69: =M68+H69+I69+J69-K69-L69 -> 1471710070
B70: dana tersedia | C70: =C68-C69 -> 1471710070 | G70: 46045 | K70: =SUM(K44:K45) -> 0 | M70: =M69+H70+I70+J70-K70-L70 -> 1471710070
H71: =SUM(H56:H70) -> 6401698600 | I71: =SUM(I56:I70) -> 1656498970 | J71: =SUM(J56:J61) -> 0 | K71: =SUM(K56:K70) -> 5481487500 | L71: =SUM(L56:L69) -> 1105000000 | M71: =H71+I71+J71-K71-L71 -> 1471710070
G73: Setor Modal Awal | H73: =H71 -> 6401698600 | K73: Asumsi
G74: Margin | H74: =SUM(O12:O27) -> 1235880470 | K74: Setor Modal | L74: =H71 -> 6401698600
G75: Modal PO baru | H75: =-K71 -> -5481487500 | I75: Baris 18-29 | K75: Margin | L75: =I71 -> 1656498970
G76: Penarikan | H76: =-L60 -> -1105000000 | K76: Penarikan Margin | L76: =-L60 -> -1105000000
G77: Dana Tersedia/Kurang | H77: =H73+H74+H75+H76 -> 1051091570 | K77: PO Baru | L77: =-K71 -> -5481487500
K78: Dana tersedia | L78: =L74+L75+L76+L77 -> 1471710070
G79: PO & margin akan cair | H79: =SUM(K29:K41,O29:O41) -> 7923876000 | I79: Baris 18-29 | N79: Total
K80: Bulan | L80: Margin yang akan diterima | M80: Modal yang akan diterima | N80: =L81+M81 -> 3062580000
K81: 46023 | L81: =SUM(Z31,Z38:Z41) -> 510430000 | M81: =SUM(K31,K38:K41) -> 2552150000 | N81: =L82+M82 -> 2692265000
H82: 130000000 | K82: 46054 | L82: =SUM(Z32:Z33,Z42) -> 352002500 | M82: =SUM(K32:K33,K42) -> 2340262500 | N82: =SUM(N80:N81) -> 5754845000
K83: Margin yang akan diterima | L83: =SUM(L81:L82) -> 862432500 | M83: =SUM(M81:M82) -> 4892412500
N84: =L85+M85 -> 1912590000
K85: Belum Terkirim | L85: =SUM(AA35:AA37,AA43:AA50) -> 268515000 | M85: =SUM(K35:K37,K43:K50) -> 1644075000 | N85: =N82+N84 -> 7667435000
K86: Total Margin Yg Akan diterim | L86: =L83+L85 -> 1130947500 | M86: =M83+M85 -> 6536487500

Sheet Sheet2
B6: Status FI Aging 50 Days
B7: Status FI Aging 29 Days
B12: Status FI Aging 35 Days
B13: Status FI Aging 35 Days
B14: Status FI Aging 44 Days
B15: Status FI Aging 44 Days
B16: Status FI Aging 29 Days

Sheet Summary V.4 (2) 2  (2)
B1: LIST INVESTASI
C3: Close
C4: Delivered
C5: Partial Delivery
C6: Open
C7: Margin Selisih | E7: =Detail!E2 -> 4 | G7: =Detail!F2 -> 5 | H7: =Detail!G2 -> 6 | I7: =Detail!H2 -> 7 | K7: =Detail!I2 -> 8
C8: Tidak aada di PO Tari
A10: NO | B10: No. PO | C10: Date | D10: Nama Barang | E10: =Detail!E3 -> Qty | F10: Harga Beli (only added if Margin is set) | G10: =Detail!F3 -> Harga | H10: Total PO | I10: Modal | J10: Margin Per Unit | K10: =Detail!I3 -> Margin | L10: Add Margin | M10: Total Margin | N10: Invoice /DO | V10: DO Total | W10: DO Outstanding | X10: Margin | Y10: AR MARGIN | Z10: Del Time | AA10: Invoice date | AB10: Initial Payment Date | AC10: adjusting TOP 30 Days | AD10: Payment Date | AE10: Status | AF10: Notes | AG10: Notes | AH10: Tari | AI10: Total Margin TARI | AJ10: Selisih
N11: Jul | O11: Aug | P11: Sep | Q11: Oct | R11: Nov | S11: Dec | T11: Jan | U11: Add Margin (by Agreement) | AF11: Notes | AG11: Notes
A12: 1 | B12: 5200954145 | C12: =VLOOKUP($B12,Detail!$B$4:$Q$21,2,0) -> 45839 | D12: Top Frame 800 | E12: =SUMIF(Detail!$B$4:$B$21,'Summary V.4 (2) 2 (2)'!$B12,Detail!$E$4:$E$21) -> 2 | G12: =VLOOKUP($B12,Detail!$B$4:$Q$21,5,0) -> 225000000 | H12: =E12*G12 -> 450000000 | I12: =SUMIF(Detail!$B$4:$B$21,'Summary V.4 (2) 2 (2)'!B12,Detail!$H$4:$H$21) -> 225000000 | J12: =(I12*20%)/E12 -> 22500000 | K12: =I12*20% -> 45000000 | M12: =SUM(K12:L12) -> 45000000 | N12: =E12 -> 2 | V12: =SUM(N12:S12) -> 2 | W12: =E12-V12 -> 0 | X12: =J12*V12 -> 45000000 | Y12: =K12-X12 -> 0 | Z12: 45861 | AA12: 45863 | AB12: 45894 | AE12: Close | AH12: =VLOOKUP(B12,investasi!$B$5:$G$18,6,0) -> 45000000 | AI12: =M12 -> 45000000 | AJ12: =AH12-AI12 -> 0
A13: 2 | B13: 5200954149 | C13: =VLOOKUP($B13,Detail!$B$4:$Q$21,2,0) -> 45839 | D13: Top Frame 800 | E13: =SUMIF(Detail!$B$4:$B$21,'Summary V.4 (2) 2 (2)'!$B13,Detail!$E$4:$E$21) -> 3 | G13: =VLOOKUP($B13,Detail!$B$4:$Q$21,5,0) -> 225000000 | H13: =E13*G13 -> 675000000 | I13: =SUMIF(Detail!$B$4:$B$21,'Summary V.4 (2) 2 (2)'!B13,Detail!$H$4:$H$21) -> 337500000 | J13: =(I13*20%)/E13 -> 22500000 | K13: =I13*20% -> 67500000 | M13: =SUM(K13:L13) -> 67500000 | N13: =E13 -> 3 | V13: =SUM(N13:S13) -> 3 | W13: =E13-V13 -> 0 | X13: =J13*V13 -> 67500000 | Y13: =K13-X13 -> 0 | Z13: 45861 | AA13: 45863 | AB13: 45894 | AE13: Close | AH13: =VLOOKUP(B13,investasi!$B$5:$G$18,6,0) -> 67500000 | AI13: =M13 -> 67500000 | AJ13: =AH13-AI13 -> 0
A14: 3 | B14: 5200954160 | C14: =VLOOKUP($B14,Detail!$B$4:$Q$21,2,0) -> 45839 | D14: Top Frame 800 | E14: =SUMIF(Detail!$B$4:$B$21,'Summary V.4 (2) 2 (2)'!$B14,Detail!$E$4:$E$21) -> 3 | G14: =VLOOKUP($B14,Detail!$B$4:$Q$21,5,0) -> 225000000 | H14: =E14*G14 -> 675000000 | I14: =SUMIF(Detail!$B$4:$B$21,'Summary V.4 (2) 2 (2)'!B14,Detail!$H$4:$H$21) -> 337500000 | J14: =(I14*20%)/E14 -> 22500000 | K14: =I14*20% -> 67500000 | M14: =SUM(K14:L14) -> 67500000 | N14: =E14 -> 3 | V14: =SUM(N14:S14) -> 3 | W14: =E14-V14 -> 0 | X14: =J14*V14 -> 67500000 | Y14: =K14-X14 -> 0 | Z14: 45861 | AA14: 45863 | AB14: 45894 | AE14: Close | AH14: =VLOOKUP(B14,investasi!$B$5:$G$18,6,0) -> 67500000 | AI14: =M14 -> 67500000 | AJ14: =AH14-AI14 -> 0
A15: 4 | B15: 5200954165 | C15: =VLOOKUP($B15,Detail!$B$4:$Q$21,2,0) -> 45870 | D15: Top Frame 800 | E15: =SUMIF(Detail!$B$4:$B$21,'Summary V.4 (2) 2 (2)'!$B15,Detail!$E$4:$E$21) -> 3 | G15: =VLOOKUP($B15,Detail!$B$4:$Q$21,5,0) -> 225000000 | H15: =E15*G15 -> 675000000 | I15: =SUMIF(Detail!$B$4:$B$21,'Summary V.4 (2) 2 (2)'!B15,Detail!$H$4:$H$21) -> 337500000 | J15: =(I15*20%)/E15 -> 22500000 | K15: =I15*20% -> 67500000 | M15: =SUM(K15:L15) -> 67500000 | O15: =E15 -> 3 | V15: =SUM(N15:S15) -> 3 | W15: =E15-V15 -> 0 | X15: =J15*V15 -> 67500000 | Y15: =K15-X15 -> 0 | Z15: 45868 | AA15: 45873 | AB15: 45904 | AE15: Close | AH15: =VLOOKUP(B15,investasi!$B$5:$G$18,6,0) -> 67500000 | AI15: =M15 -> 67500000 | AJ15: =AH15-AI15 -> 0
A16: 5 | B16: 5200954167 | C16: =VLOOKUP($B16,Detail!$B$4:$Q$21,2,0) -> 45870 | D16: Top Frame 800 | E16: =SUMIF(Detail!$B$4:$B$21,'Summary V.4 (2) 2 (2)'!$B16,Detail!$E$4:$E$21) -> 3 | G16: =VLOOKUP($B16,Detail!$B$4:$Q$21,5,0) -> 225000000 | H16: =E16*G16 -> 675000000 | I16: =SUMIF(Detail!$B$4:$B$21,'Summary V.4 (2) 2 (2)'!B16,Detail!$H$4:$H$21) -> 337500000 | J16: =(I16*20%)/E16 -> 22500000 | K16: =I16*20% -> 67500000 | M16: =SUM(K16:L16) -> 67500000 | O16: =E16 -> 3 | V16: =SUM(N16:S16) -> 3 | W16: =E16-V16 -> 0 | X16: =J16*V16 -> 67500000 | Y16: =K16-X16 -> 0 | Z16: 45868 | AA16: 45873 | AB16: 45904 | AE16: Close | AH16: =VLOOKUP(B16,investasi!$B$5:$G$18,6,0) -> 67500000 | AI16: =M16 -> 67500000 | AJ16: =AH16-AI16 -> 0
A17: 6 | B17: 5200954168 | C17: =VLOOKUP($B17,Detail!$B$4:$Q$21,2,0) -> 45870 | D17: Top Frame 800 | E17: =SUMIF(Detail!$B$4:$B$21,'Summary V.4 (2) 2 (2)'!$B17,Detail!$E$4:$E$21) -> 2 | G17: =VLOOKUP($B17,Detail!$B$4:$Q$21,5,0) -> 225000000 | H17: =E17*G17 -> 450000000 | I17: =SUMIF(Detail!$B$4:$B$21,'Summary V.4 (2) 2 (2)'!B17,Detail!$H$4:$H$21) -> 225000000 | J17: =(I17*20%)/E17 -> 22500000 | K17: =I17*20% -> 45000000 | M17: =SUM(K17:L17) -> 45000000 | O17: =E17 -> 2 | V17: =SUM(N17:S17) -> 2 | W17: =E17-V17 -> 0 | X17: =J17*V17 -> 45000000 | Y17: =K17-X17 -> 0 | Z17: 45868 | AA17: 45873 | AB17: 45904 | AE17: Close | AH17: =VLOOKUP(B17,investasi!$B$5:$G$18,6,0) -> 45000000 | AI17: =M17 -> 45000000 | AJ17: =AH17-AI17 -> 0
A18: 7 | B18: 5200954169 | C18: =VLOOKUP($B18,Detail!$B$4:$Q$21,2,0) -> 45870 | D18: Top Frame 800 | E18: =SUMIF(Detail!$B$4:$B$21,'Summary V.4 (2) 2 (2)'!$B18,Detail!$E$4:$E$21) -> 2 | G18: =VLOOKUP($B18,Detail!$B$4:$Q$21,5,0) -> 225000000 | H18: =E18*G18 -> 450000000 | I18: =SUMIF(Detail!$B$4:$B$21,'Summary V.4 (2) 2 (2)'!B18,Detail!$H$4:$H$21) -> 225000000 | J18: =(I18*20%)/E18 -> 22500000 | K18: =I18*20% -> 45000000 | M18: =SUM(K18:L18) -> 45000000 | O18: =E18 -> 2 | V18: =SUM(N18:S18) -> 2 | W18: =E18-V18 -> 0 | X18: =J18*V18 -> 45000000 | Y18: =K18-X18 -> 0 | Z18: 45868 | AA18: 45873 | AB18: 45904 | AE18: Close | AH18: =VLOOKUP(B18,investasi!$B$5:$G$18,6,0) -> 45000000 | AI18: =M18 -> 45000000 | AJ18: =AH18-AI18 -> 0
A19: 8 | B19: 5200777098 | C19: =VLOOKUP($B19,Detail!$B$4:$Q$25,2,0) -> 45877 | D19: DVAR 3771-B0-20D-PPC Statcom Steel Support | E19: =SUMIF(Detail!$B$4:$B$25,'Summary V.4 (2) 2 (2)'!$B19,Detail!$E$4:$E$25) -> 1 | G19: =VLOOKUP($B19,Detail!$B$4:$Q$25,5,0) -> 1149199000 | H19: =E19*G19 -> 1149199000 | I19: =SUMIF(Detail!$B$4:$B$25,'Summary V.4 (2) 2 (2)'!B19,Detail!$H$4:$H$25) -> 574599500 | J19: =(I19*20%)/E19 -> 114919900 | K19: =I19*20% -> 114919900 | M19: =SUM(K19:L19) -> 114919900 | O19: 0 | P19: 1 | V19: =SUM(N19:S19) -> 1 | W19: =E19-V19 -> 0 | X19: =J19*V19 -> 114919900 | Y19: =K19-X19 -> 0 | Z19: 45930 | AA19: =Z19+7 -> 45937 | AB19: =AA19+30 -> 45967 | AC19: =AA19+60 -> 45997 | AE19: Close | AH19: =VLOOKUP(B19,investasi!$B$5:$G$18,6,0) -> 57248700 | AI19: =M19 -> 114919900 | AJ19: =AH19-AI19 -> -57671200 | AK19: Selisih di unit Qty, di catatan pak mushafa 2 unit(1 sudah terbayar , 1 unit belum terbayar ), dicatatan TARI 1 Unit
A20: 9 | B20: 5200776987 | C20: =VLOOKUP($B20,Detail!$B$4:$Q$25,2,0) -> 45877 | D20: Top Frame 800 | E20: =SUMIF(Detail!$B$4:$B$25,'Summary V.4 (2) 2 (2)'!$B20,Detail!$E$4:$E$25) -> 2 | G20: =VLOOKUP($B20,Detail!$B$4:$Q$25,5,0) -> 225000000 | H20: =E20*G20 -> 450000000 | I20: =SUMIF(Detail!$B$4:$B$25,'Summary V.4 (2) 2 (2)'!B20,Detail!$H$4:$H$25) -> 225000000 | J20: =(I20*20%)/E20 -> 22500000 | K20: =I20*20% -> 45000000 | M20: =SUM(K20:L20) -> 45000000 | O20: 0 | P20: 2 | V20: =SUM(N20:S20) -> 2 | W20: =E20-V20 -> 0 | X20: =J20*V20 -> 45000000 | Y20: =K20-X20 -> 0 | Z20: 45923 | AA20: =Z20+7 -> 45930 | AB20: =AA20+30 -> 45960 | AC20: =AA20+60 -> 45990 | AE20: Close | AH20: =VLOOKUP(B20,investasi!$B$5:$G$18,6,0) -> 45000000 | AI20: =M20 -> 45000000 | AJ20: =AH20-AI20 -> 0
A21: 10 | B21: 5200777132 | C21: =VLOOKUP($B21,Detail!$B$4:$Q$110,2,0) -> 45880 | D21: Leser Barrier MK 01-F3004973 | E21: 20 | G21: =VLOOKUP($B21,Detail!$B$4:$Q$25,5,0) -> 40457500 | H21: =E21*G21 -> 809150000 | I21: =H21*50% -> 404575000 | J21: =(I21*13%)/E21 -> 2629737.5 | K21: =I21*13% -> 52594750 | M21: =SUM(K21:L21) -> 52594750 | O21: 0 | Q21: 20 | V21: =SUM(N21:S21) -> 20 | W21: =E21-V21 -> 0 | X21: =J21*V21 -> 52594750 | Y21: =K21-X21 -> 0 | Z21: 45922 | AA21: =Z21+7 -> 45929 | AB21: =AA21+30 -> 45959 | AC21: =AA21+60 -> 45989 | AE21: Close | AH21: =VLOOKUP(B21,investasi!$B$5:$G$18,6,0) -> 52594750 | AI21: =M21 -> 52594750 | AJ21: =AH21-AI21 -> 0
A22: 11 | B22: =Detail!$B$45 -> 5200972695 | C22: =Detail!$C$45 -> 45891 | D22: Tangki | E22: 8 | F22: 75000000 | G22: 100500000 | H22: =E22*G22 -> 804000000 | I22: =H22*50% -> 402000000 | J22: 12750000 | K22: =E22*J22 -> 102000000 | M22: =SUM(K22:L22) -> 102000000 | O22: 0 | P22: 8 | U22: Margin was arranged 25mil/ea | V22: =SUM(N22:S22) -> 8 | W22: =E22-V22 -> 0 | X22: =J22*V22 -> 102000000 | Y22: =K22-X22 -> 0 | Z22: 45925 | AA22: =Z22+7 -> 45932 | AB22: =AA22+30 -> 45962 | AC22: =AA22+60 -> 45992 | AE22: Close | AH22: =VLOOKUP(B22,investasi!$B$5:$G$18,6,0) -> 80400000 | AI22: =M22 -> 102000000 | AJ22: =AH22-AI22 -> -21600000 | AK22: Selisih margin
A23: 12 | B23: =Detail!B53 -> 5200777558 | C23: 45897 | D23: Top Frame 2630 | E23: 1 | G23: =Detail!F53 -> 685000000 | H23: =E23*G23 -> 685000000 | I23: =H23*50% -> 342500000 | J23: =(I23*20%)/E23 -> 68500000 | K23: =I23*20% -> 68500000 | M23: =SUM(K23:L23) -> 68500000 | P23: 1 | V23: =SUM(N23:S23) -> 1 | W23: =E23-V23 -> 0 | X23: =J23*V23 -> 68500000 | Y23: =K23-X23 -> 0 | Z23: 45923 | AA23: =Z23+7 -> 45930 | AB23: =AA23+30 -> 45960 | AC23: =AA23+60 -> 45990 | AE23: Close | AH23: =VLOOKUP(B23,investasi!$B$5:$G$18,6,0) -> 68500000 | AI23: =M23 -> 68500000 | AJ23: =AH23-AI23 -> 0
A24: 13 | B24: =Detail!B54 -> 5200777559 | C24: 45901 | D24: Top Frame 800 | E24: 2 | G24: =Detail!F54 -> 225000000 | H24: =E24*G24 -> 450000000 | I24: =H24*50% -> 225000000 | J24: =(I24*20%)/E24 -> 22500000 | K24: =I24*20% -> 45000000 | M24: =SUM(K24:L24) -> 45000000 | P24: 2 | V24: =SUM(N24:S24) -> 2 | W24: =E24-V24 -> 0 | X24: =J24*V24 -> 45000000 | Y24: =K24-X24 -> 0 | Z24: 45925 | AA24: =Z24+7 -> 45932 | AB24: =AA24+30 -> 45962 | AC24: =AA24+60 -> 45992 | AE24: Close | AH24: =VLOOKUP(B24,investasi!$B$5:$G$18,6,0) -> 45000000 | AI24: =M24 -> 45000000 | AJ24: =AH24-AI24 -> 0
A25: 14 | B25: =Detail!$B$56 -> 5200777758 | C25: 45909 | D25: Pipe Spool | E25: 1 | G25: =Detail!F56 -> 2231048200 | H25: =E25*G25 -> 2231048200 | I25: =H25*50% -> 1115524100 | J25: =(I25*20%)/E25 -> 223104820 | K25: =I25*20% -> 223104820 | M25: =SUM(K25:L25) -> 223104820 | P25: 1 | V25: =SUM(N25:S25) -> 1 | W25: =E25-V25 -> 0 | X25: =J25*V25 -> 223104820 | Y25: =K25-X25 -> 0 | Z25: 45930 | AA25: =Z25+7 -> 45937 | AB25: =AA25+30 -> 45967 | AC25: =AA25+60 -> 45997 | AE25: Close | AH25: =VLOOKUP(B25,investasi!$B$5:$G$18,6,0) -> 223104820 | AI25: =M25 -> 223104820 | AJ25: =AH25-AI25 -> 0
A26: 15 | B26: =Detail!$B$58 -> 5200778319 | C26: 45909 | D26: =Detail!$D$58 -> Top Frame 800 | E26: 2 | G26: =Detail!$F$58 -> 225000000 | H26: =E26*G26 -> 450000000 | I26: =H26*50% -> 225000000 | J26: =(I26*20%)/E26 -> 22500000 | K26: =I26*20% -> 45000000 | M26: =SUM(K26:L26) -> 45000000 | P26: 2 | V26: =SUM(N26:S26) -> 2 | W26: =E26-V26 -> 0 | X26: =J26*V26 -> 45000000 | Y26: =K26-X26 -> 0 | Z26: 45940 | AA26: =Z26+7 -> 45947 | AB26: =AA26+30 -> 45977 | AC26: =AA26+60 -> 46007 | AE26: Close | AH26: =VLOOKUP(B26,investasi!$B$23:$G$26,6,0) -> 45000000 | AI26: =M26 -> 45000000 | AJ26: =AH26-AI26 -> 0
A27: 16 | B27: 5200778328 | C27: 45915 | D27: Top Frame 2630 | E27: 1 | G27: =Detail!F59 -> 685000000 | H27: =E27*G27 -> 685000000 | I27: =H27*50% -> 342500000 | J27: =(I27*20%)/E27 -> 68500000 | K27: =(I27*20%)+F27 -> 68500000 | L27: 66261000 | M27: =SUM(K27:L27) -> 134761000 | P27: 1 | V27: =SUM(N27:S27) -> 1 | W27: =E27-V27 -> 0 | X27: =J27*V27+L27 -> 134761000 | Y27: =K27+L27-X27 -> 0 | Z27: 45940 | AA27: =Z27+7 -> 45947 | AB27: =AA27+30 -> 45977 | AC27: =AA27+60 -> 46007 | AE27: Close | AH27: =VLOOKUP(B27,investasi!$B$23:$G$26,6,0)+investasi!I24 -> 134761000 | AI27: =M27 -> 134761000 | AJ27: =AH27-AI27 -> 0
V28: =SUM(N28:S28) -> 0 | AE28: Close
A29: 18 | B29: =Detail!B60 -> 5200779815 | C29: 45965 | D29: Top Frame 2630 | E29: 1 | G29: =Detail!F60 -> 685000000 | H29: =E29*G29 -> 685000000 | I29: =H29*50% -> 342500000 | J29: =(I29*20%)/E29 -> 68500000 | K29: =(I29*20%)+F29 -> 68500000 | L29: 66261000 | M29: =SUM(K29:L29) -> 134761000 | R29: 1 | V29: =SUM(N29:S29) -> 1 | W29: =E29-V29 -> 0 | X29: =J29*V29+L29 -> 134761000 | Y29: =K29+L29-X29 -> 0 | Z29: 45989 | AA29: 46008 | AB29: 46034 | AC29: =AA29+30 -> 46038 | AD29: 46034 | AE29: Close | AF29: Payment 12 Jan 2026 | AH29: =VLOOKUP(B29,investasi!$B$23:$G$26,6,0)+investasi!I26 -> 134761000 | AI29: =M29 -> 134761000 | AJ29: =AH29-AI29 -> 0
A30: =A29+1 -> 19 | B30: 5200988854 | C30: 45977 | D30: Trench Grade | E30: 150 | G30: 4990500 | H30: =E30*G30 -> 748575000 | I30: =H30*50% -> 374287500 | J30: =(I30*20%)/E30 -> 499050 | K30: =(I30*20%)+F30 -> 74857500 | M30: =SUM(K30:L30) -> 74857500 | R30: 150 | V30: =SUM(N30:S30) -> 150 | W30: =E30-V30 -> 0 | X30: =J30*V30+L30 -> 74857500 | Y30: =K30+L30-X30 -> 0 | Z30: 45989 | AA30: 46008 | AB30: 46034 | AC30: =AA30+30 -> 46038 | AD30: 46034 | AE30: Close | AF30: Payment 12 Jan 2026
A31: =A30+1 -> 20 | B31: 5200989664 | C31: 45977 | D31: Grating Ditch | E31: 100 | G31: 21100000 | H31: =E31*G31 -> 2110000000 | I31: =H31*50% -> 1055000000 | J31: =(I31*20%)/E31 -> 2110000 | K31: =(I31*20%)+F31 -> 211000000 | M31: =SUM(K31:L31) -> 211000000 | S31: 100 | V31: =SUM(N31:S31) -> 100 | W31: =E31-V31 -> 0 | X31: =J31*V31+L31 -> 211000000 | Y31: =K31+L31-X31 -> 0 | Z31: 46031 | AB31: =Z31+30 -> 46061 | AE31: Delivered | AF31: Belum Di invoice 50, 50 unit penfgiriman | AG31: Status FI Aging 43 Days
A32: =A31+1 -> 21 | B32: 5200989665 | C32: 45977 | D32: Grating Ditch | E32: 100 | G32: 21100000 | H32: =E32*G32 -> 2110000000 | I32: =H32*50% -> 1055000000 | J32: =(I32*20%)/E32 -> 2110000 | K32: =(I32*20%)+F32 -> 211000000 | M32: =SUM(K32:L32) -> 211000000 | S32: 100 | V32: =SUM(N32:T32) -> 100 | W32: =E32-V32 -> 0 | X32: =J32*V32+L32 -> 211000000 | Y32: =K32+L32-X32 -> 0 | Z32: 46030 | AB32: =Z32+30 -> 46060 | AE32: Delivered | AF32: Belum Di invoice 50, 50 unit penfgiriman | AG32: Status FI Aging 22 Days
A33: =A32+1 -> 22 | B33: 5200989666 | C33: 45977 | D33: Grating Ditch | E33: 110 | G33: 21100000 | H33: =E33*G33 -> 2321000000 | I33: =H33*50% -> 1160500000 | J33: =(I33*20%)/E33 -> 2110000 | K33: =(I33*20%)+F33 -> 232100000 | M33: =SUM(K33:L33) -> 232100000 | T33: 110 | V33: =SUM(N33:T33) -> 110 | W33: =E33-V33 -> 0 | X33: =J33*V33+L33 -> 232100000 | Y33: =K33+L33-X33 -> 0 | Z33: 46027 | AA33: 45676 | AB33: =AA33+30 -> 45706 | AE33: Delivered | AF33: 110 ea Terkirim
A34: =A33+1 -> 23 | B34: 5200992759 | C34: 45981 | D34: Tanki | E34: 6 | G34: 100500000 | H34: =E34*G34 -> 603000000 | I34: =H34*50% -> 301500000 | J34: 12750000 | K34: =J34*E34 -> 76500000 | M34: =SUM(K34:L34) -> 76500000 | V34: =SUM(N34:S34) -> 0 | Y34: =K34+L34-X34 -> 76500000 | AE34: Open | AF34: Blm Terkirim
A35: =A34+1 -> 24 | B35: 5200991260 | C35: 45985 | D35: Trench Grade | E35: 150 | G35: 4990500 | H35: =E35*G35 -> 748575000 | I35: =H35*50% -> 374287500 | J35: =(I35*20%)/E35 -> 499050 | K35: =(I35*20%)+F35 -> 74857500 | M35: =SUM(K35:L35) -> 74857500 | T35: =E35 -> 150 | V35: =SUM(N35:S35) -> 0 | W35: =E35-V35 -> 150 | X35: =J35*V35+L35 -> 0 | Y35: =K35+L35-X35 -> 74857500 | Z35: 46041 | AE35: Delivered | AF35: Blm Terkirim
A36: =A35+1 -> 25 | B36: 5200991264 | C36: 45985 | D36: Trench Grade | E36: 150 | G36: 4990500 | H36: =E36*G36 -> 748575000 | I36: =H36*50% -> 374287500 | J36: =(I36*20%)/E36 -> 499050 | K36: =(I36*20%)+F36 -> 74857500 | M36: =SUM(K36:L36) -> 74857500 | T36: =E36 -> 150 | V36: =SUM(N36:S36) -> 0 | W36: =E36-V36 -> 150 | X36: =J36*V36+L36 -> 0 | Y36: =K36+L36-X36 -> 74857500 | Z36: 46041 | AE36: Delivered | AF36: Blm Terkirim
A37: =A36+1 -> 26 | B37: 5200991456 | C37: 45986 | D37: Trench Grade | E37: 150 | G37: 4990500 | H37: =E37*G37 -> 748575000 | I37: =H37*50% -> 374287500 | J37: =(I37*20%)/E37 -> 499050 | K37: =(I37*20%)+F37 -> 74857500 | M37: =SUM(K37:L37) -> 74857500 | S37: =E37 -> 150 | V37: =SUM(N37:S37) -> 150 | W37: =E37-V37 -> 0 | X37: =J37*V37+L37 -> 74857500 | Y37: =K37+L37-X37 -> 0 | Z37: 46036 | AC37: =Z37+60 -> 46096 | AE37: Delivered | AF37: Blm Invoice | AG37: Status FI Aging 28 Days
A38: =A37+1 -> 27 | B38: 5200991458 | C38: 45986 | D38: Trench Grade | E38: 150 | G38: 4990500 | H38: =E38*G38 -> 748575000 | I38: =H38*50% -> 374287500 | J38: =(I38*20%)/E38 -> 499050 | K38: =(I38*20%)+F38 -> 74857500 | M38: =SUM(K38:L38) -> 74857500 | S38: =E38 -> 150 | V38: =SUM(N38:S38) -> 150 | W38: =E38-V38 -> 0 | X38: =J38*V38+L38 -> 74857500 | Y38: =K38+L38-X38 -> 0 | Z38: 46036 | AC38: =Z38+60 -> 46096 | AE38: Delivered | AF38: Blm Invoice | AG38: Status FI Aging 28 Days
A39: =A38+1 -> 28 | B39: 5200991502 | C39: 45986 | D39: Trench Grade | E39: 150 | G39: 4990500 | H39: =E39*G39 -> 748575000 | I39: =H39*50% -> 374287500 | J39: =(I39*20%)/E39 -> 499050 | K39: =(I39*20%)+F39 -> 74857500 | M39: =SUM(K39:L39) -> 74857500 | S39: =E39 -> 150 | V39: =SUM(N39:S39) -> 150 | W39: =E39-V39 -> 0 | X39: =J39*V39+L39 -> 74857500 | Y39: =K39+L39-X39 -> 0 | Z39: 46030 | AC39: =Z39+60 -> 46090 | AE39: Delivered | AF39: Blm Invoice | AG39: Status FI Aging 37 Days
A40: =A39+1 -> 29 | B40: 5200991503 | C40: 45986 | D40: Trench Grade | E40: 150 | G40: 4990500 | H40: =E40*G40 -> 748575000 | I40: =H40*50% -> 374287500 | J40: =(I40*20%)/E40 -> 499050 | K40: =(I40*20%)+F40 -> 74857500 | M40: =SUM(K40:L40) -> 74857500 | S40: =E40 -> 150 | V40: =SUM(N40:S40) -> 150 | W40: =E40-V40 -> 0 | X40: =J40*V40+L40 -> 74857500 | Y40: =K40+L40-X40 -> 0 | Z40: 46030 | AC40: =Z40+60 -> 46090 | AE40: Delivered | AF40: Blm Invoice | AG40: Status FI Aging 37 Days
A41: =A40+1 -> 30 | B41: 5200991553 | C41: 46372 | D41: Trench Grade | E41: 50 | G41: 4990500 | H41: =E41*G41 -> 249525000 | I41: =H41*50% -> 124762500 | J41: =(I41*20%)/E41 -> 499050 | K41: =(I41*20%)+F41 -> 24952500 | M41: =SUM(K41:L41) -> 24952500 | S41: =E41 -> 50 | V41: =SUM(N41:S41) -> 50 | W41: =E41-V41 -> 0 | X41: =J41*V41+L41 -> 24952500 | Y41: =K41+L41-X41 -> 0 | Z41: 46036 | AC41: =Z41+60 -> 46096 | AE41: Delivered | AF41: Blm Invoice | AG41: Status FI Aging 22 Days
A42: =A41+1 -> 31 | B42: 5200996833 | C42: 46021 | D42: new barge landing facility | E42: 1 | H42: 1188000000 | I42: =H42*50% -> 594000000 | J42: =(I42*20%)/E42 -> 118800000 | K42: =(I42*20%)+F42 -> 118800000 | M42: =SUM(K42:L42) -> 118800000 | Y42: =K42+L42-X42 -> 118800000 | AE42: Open | AF42: Blm Terkirim
B45: TOTAL MARGIN | H45: =SUM(H12:H43) -> 26269947200 | I45: =SUM(I12:I43) -> 13134973600 | K45: =SUM(K12:K43) -> 2636474470 | L45: =SUM(L12:L43) -> 132522000 | M45: =SUM(M12:M43) -> 2768996470 | X45: =SUM(X12:X43) -> 2423981470 | Y45: =SUM(Y12:Y43) -> 345015000
E47: A | G47: B | H47: C | I47: D | J47: E | K47: F=A+B+C-D-E
E48: TGL | F48: Modal Setor Awal | G48: Margin | H48: Pencairan Modal | I48: Modal PO Baru | J48: Penarikan | K48: Dana Tersedia
E49: 45839 | F49: =SUM(I12:I14) -> 900000000 | G49: =SUM(X12:X14) -> 180000000 | K49: =F49+G49 -> 1080000000
E50: 45870 | F50: =SUM(I15:I18) -> 1125000000 | G50: =SUM(X15:X18) -> 225000000 | I50: =SUM(I19:I22) -> 1606174500 | K50: =K49+F50+G50+H50-I50-J50 -> 823825500
E51: 45901 | F51: 1426698600 | I51: =SUM(I23:I27) -> 2250524100 | K51: =K50+F51+G51+H51-I51 -> 0
E52: 45931 | I52: =I29+I28 -> 342500000 | K52: =K51+F52+G52+H52-I52 -> -342500000
E53: 45962 | G53: =SUM(M19:M28) -> 830880470 | I53: =-SUM(I19:I28)+SUM(I30:I40) -> 2335313900 | J53: 1105000000 | K53: =K52+F53+G53+H53-I53-J53 -> -2951933430
E54: 46007 | F54: 1300000000 | I54: =I41+I42+I43 -> 718762500 | K54: =K53+F54+G54+H54-I54-J54 -> -2370695930
E55: 46014 | F55: 250000000 | K55: =K54+F55+G55+H55-I55-J55 -> -2120695930
E56: 46015 | F56: 250000000 | K56: =K55+F56+G56+H56-I56-J56 -> -1870695930
B57: Total Investasi | C57: =SUM(F63) -> 6401698600 | E57: 46016 | F57: 250000000 | K57: =K56+F57+G57+H57-I57-J57 -> -1620695930
B58: Margin diterima (Close) | C58: =SUM(M12:M30) -> 1445498970 | E58: 46017 | F58: 250000000 | K58: =K57+F58+G58+H58-I58-J58 -> -1370695930
B59: Total Modal PO | C59: =-I45 -> -13134973600 | E59: 46018 | F59: 250000000 | K59: =K58+F59+G59+H59-I59-J59 -> -1120695930
B60: Modal Kembali PO (close) | C60: =SUM(I12:I30) -> 6598486100 | E60: 46019 | F60: 250000000 | K60: =K59+F60+G60+H60-I60-J60 -> -870695930
B61: Total dana | C61: =SUM(C57:C60) -> 1310710070 | E61: 46020 | F61: 150000000 | K61: =K60+F61+G61+H61-I61-J61 -> -720695930
B62: penarikan | C62: =J53 -> 1105000000 | E62: 46034 | G62: =SUM(M29:M30) -> 209618500 | I62: =-SUM(I29:I30) -> -716787500 | K62: =K61+F62+G62+H62-I62-J62 -> 205710070
B63: dana tersedia | C63: =C61-C62 -> 205710070 | F63: =SUM(F49:F62) -> 6401698600 | G63: =SUM(G49:G62) -> 1445498970 | H63: =SUM(H49:H54) -> 0 | I63: =SUM(I49:I62) -> 6536487500 | J63: =SUM(J49:J62) -> 1105000000 | K63: =F63+G63+H63-I63-J63 -> 205710070
E65: Setor Modal Awal | F65: =F63 -> 6401698600 | I65: Asumsi
E66: Margin | F66: =SUM(M12:M27) -> 1235880470 | I66: Setor Modal | J66: =F63 -> 6401698600
E67: Modal PO baru | F67: =-I63 -> -6536487500 | G67: Baris 18-29 | I67: Margin | J67: =G63 -> 1445498970
E68: Penarikan | F68: =-J53 -> -1105000000 | I68: Penarikan Margin | J68: =-J53 -> -1105000000
E69: Dana Tersedia/Kurang | F69: =F65+F66+F67+F68 -> -3908430 | I69: PO Baru | J69: =-I63 -> -6536487500
I70: Dana tersedia | J70: =J66+J67+J68+J69 -> 205710070
E71: PO & margin akan cair | F71: =SUM(I29:I40,M29:M40) -> 7923876000 | G71: Baris 18-29
I72: Bulan | J72: Margin yang akan diterima | K72: Modal yang akan diterima | L72: Total
I73: 46023 | J73: =SUM(X31,X37:X40) -> 510430000 | K73: =SUM(I31,I37:I40) -> 2552150000 | L73: =J73+K73 -> 3062580000
F74: 130000000 | I74: 46054 | J74: =SUM(X32:X33,X41) -> 468052500 | K74: =SUM(I32:I33,I41) -> 2340262500 | L74: =J74+K74 -> 2808315000
I75: Margin yang akan diterima | J75: =SUM(J73:J74) -> 978482500 | K75: =SUM(K73:K74) -> 4892412500 | L75: =SUM(L73:L74) -> 5870895000
I77: Belum Terkirim | J77: =SUM(Y34:Y36,Y42:Y43) -> 345015000 | K77: =SUM(I34:I36,I42:I43) -> 1644075000 | L77: =J77+K77 -> 1989090000
I78: Total Margin Yg Akan diterim | J78: =J75+J77 -> 1323497500 | K78: =K75+K77 -> 6536487500 | L78: =L75+L77 -> 7859985000

Sheet Summary V.4 (2) 2 
B1: LIST INVESTASI
C3: Close
C4: Delivered
C5: Partial Delivery
C6: Open
C7: Margin Selisih | E7: =Detail!E2 -> 4 | G7: =Detail!F2 -> 5 | H7: =Detail!G2 -> 6 | I7: =Detail!H2 -> 7 | K7: =Detail!I2 -> 8
C8: Tidak aada di PO Tari
A10: NO | B10: No. PO | C10: Date | D10: Nama Barang | E10: =Detail!E3 -> Qty | F10: Harga Beli (only added if Margin is set) | G10: =Detail!F3 -> Harga | H10: Total PO | I10: Modal | J10: Margin Per Unit | K10: =Detail!I3 -> Margin | L10: Add Margin | M10: Total Margin | N10: Invoice /DO | V10: DO Total | W10: DO Outstanding | X10: Margin | Y10: AR MARGIN | Z10: Del Time | AA10: Invoice date | AB10: Initial Payment Date | AC10: adjusting TOP 30 Days | AD10: Status | AE10: Notes | AG10: Tari | AH10: Total Margin TARI | AI10: Selisih
N11: Jul | O11: Aug | P11: Sep | Q11: Oct | R11: Nov | S11: Dec | T11: Jan | U11: Add Margin (by Agreement) | AE11: Notes
A12: 1 | B12: 5200954145 | C12: =VLOOKUP($B12,Detail!$B$4:$Q$21,2,0) -> 45839 | D12: Top Frame 800 | E12: =SUMIF(Detail!$B$4:$B$21,'Summary V.4 (2) 2 '!$B12,Detail!$E$4:$E$21) -> 2 | G12: =VLOOKUP($B12,Detail!$B$4:$Q$21,5,0) -> 225000000 | H12: =E12*G12 -> 450000000 | I12: =SUMIF(Detail!$B$4:$B$21,'Summary V.4 (2) 2 '!B12,Detail!$H$4:$H$21) -> 225000000 | J12: =(I12*20%)/E12 -> 22500000 | K12: =I12*20% -> 45000000 | M12: =SUM(K12:L12) -> 45000000 | N12: =E12 -> 2 | V12: =SUM(N12:S12) -> 2 | W12: =E12-V12 -> 0 | X12: =J12*V12 -> 45000000 | Y12: =K12-X12 -> 0 | Z12: 45861 | AA12: 45863 | AB12: 45894 | AD12: Close | AG12: =VLOOKUP(B12,investasi!$B$5:$G$18,6,0) -> 45000000 | AH12: =M12 -> 45000000 | AI12: =AG12-AH12 -> 0
A13: 2 | B13: 5200954149 | C13: =VLOOKUP($B13,Detail!$B$4:$Q$21,2,0) -> 45839 | D13: Top Frame 800 | E13: =SUMIF(Detail!$B$4:$B$21,'Summary V.4 (2) 2 '!$B13,Detail!$E$4:$E$21) -> 3 | G13: =VLOOKUP($B13,Detail!$B$4:$Q$21,5,0) -> 225000000 | H13: =E13*G13 -> 675000000 | I13: =SUMIF(Detail!$B$4:$B$21,'Summary V.4 (2) 2 '!B13,Detail!$H$4:$H$21) -> 337500000 | J13: =(I13*20%)/E13 -> 22500000 | K13: =I13*20% -> 67500000 | M13: =SUM(K13:L13) -> 67500000 | N13: =E13 -> 3 | V13: =SUM(N13:S13) -> 3 | W13: =E13-V13 -> 0 | X13: =J13*V13 -> 67500000 | Y13: =K13-X13 -> 0 | Z13: 45861 | AA13: 45863 | AB13: 45894 | AD13: Close | AG13: =VLOOKUP(B13,investasi!$B$5:$G$18,6,0) -> 67500000 | AH13: =M13 -> 67500000 | AI13: =AG13-AH13 -> 0
A14: 3 | B14: 5200954160 | C14: =VLOOKUP($B14,Detail!$B$4:$Q$21,2,0) -> 45839 | D14: Top Frame 800 | E14: =SUMIF(Detail!$B$4:$B$21,'Summary V.4 (2) 2 '!$B14,Detail!$E$4:$E$21) -> 3 | G14: =VLOOKUP($B14,Detail!$B$4:$Q$21,5,0) -> 225000000 | H14: =E14*G14 -> 675000000 | I14: =SUMIF(Detail!$B$4:$B$21,'Summary V.4 (2) 2 '!B14,Detail!$H$4:$H$21) -> 337500000 | J14: =(I14*20%)/E14 -> 22500000 | K14: =I14*20% -> 67500000 | M14: =SUM(K14:L14) -> 67500000 | N14: =E14 -> 3 | V14: =SUM(N14:S14) -> 3 | W14: =E14-V14 -> 0 | X14: =J14*V14 -> 67500000 | Y14: =K14-X14 -> 0 | Z14: 45861 | AA14: 45863 | AB14: 45894 | AD14: Close | AG14: =VLOOKUP(B14,investasi!$B$5:$G$18,6,0) -> 67500000 | AH14: =M14 -> 67500000 | AI14: =AG14-AH14 -> 0
A15: 4 | B15: 5200954165 | C15: =VLOOKUP($B15,Detail!$B$4:$Q$21,2,0) -> 45870 | D15: Top Frame 800 | E15: =SUMIF(Detail!$B$4:$B$21,'Summary V.4 (2) 2 '!$B15,Detail!$E$4:$E$21) -> 3 | G15: =VLOOKUP($B15,Detail!$B$4:$Q$21,5,0) -> 225000000 | H15: =E15*G15 -> 675000000 | I15: =SUMIF(Detail!$B$4:$B$21,'Summary V.4 (2) 2 '!B15,Detail!$H$4:$H$21) -> 337500000 | J15: =(I15*20%)/E15 -> 22500000 | K15: =I15*20% -> 67500000 | M15: =SUM(K15:L15) -> 67500000 | O15: =E15 -> 3 | V15: =SUM(N15:S15) -> 3 | W15: =E15-V15 -> 0 | X15: =J15*V15 -> 67500000 | Y15: =K15-X15 -> 0 | Z15: 45868 | AA15: 45873 | AB15: 45904 | AD15: Close | AG15: =VLOOKUP(B15,investasi!$B$5:$G$18,6,0) -> 67500000 | AH15: =M15 -> 67500000 | AI15: =AG15-AH15 -> 0
A16: 5 | B16: 5200954167 | C16: =VLOOKUP($B16,Detail!$B$4:$Q$21,2,0) -> 45870 | D16: Top Frame 800 | E16: =SUMIF(Detail!$B$4:$B$21,'Summary V.4 (2) 2 '!$B16,Detail!$E$4:$E$21) -> 3 | G16: =VLOOKUP($B16,Detail!$B$4:$Q$21,5,0) -> 225000000 | H16: =E16*G16 -> 675000000 | I16: =SUMIF(Detail!$B$4:$B$21,'Summary V.4 (2) 2 '!B16,Detail!$H$4:$H$21) -> 337500000 | J16: =(I16*20%)/E16 -> 22500000 | K16: =I16*20% -> 67500000 | M16: =SUM(K16:L16) -> 67500000 | O16: =E16 -> 3 | V16: =SUM(N16:S16) -> 3 | W16: =E16-V16 -> 0 | X16: =J16*V16 -> 67500000 | Y16: =K16-X16 -> 0 | Z16: 45868 | AA16: 45873 | AB16: 45904 | AD16: Close | AG16: =VLOOKUP(B16,investasi!$B$5:$G$18,6,0) -> 67500000 | AH16: =M16 -> 67500000 | AI16: =AG16-AH16 -> 0
A17: 6 | B17: 5200954168 | C17: =VLOOKUP($B17,Detail!$B$4:$Q$21,2,0) -> 45870 | D17: Top Frame 800 | E17: =SUMIF(Detail!$B$4:$B$21,'Summary V.4 (2) 2 '!$B17,Detail!$E$4:$E$21) -> 2 | G17: =VLOOKUP($B17,Detail!$B$4:$Q$21,5,0) -> 225000000 | H17: =E17*G17 -> 450000000 | I17: =SUMIF(Detail!$B$4:$B$21,'Summary V.4 (2) 2 '!B17,Detail!$H$4:$H$21) -> 225000000 | J17: =(I17*20%)/E17 -> 22500000 | K17: =I17*20% -> 45000000 | M17: =SUM(K17:L17) -> 45000000 | O17: =E17 -> 2 | V17: =SUM(N17:S17) -> 2 | W17: =E17-V17 -> 0 | X17: =J17*V17 -> 45000000 | Y17: =K17-X17 -> 0 | Z17: 45868 | AA17: 45873 | AB17: 45904 | AD17: Close | AG17: =VLOOKUP(B17,investasi!$B$5:$G$18,6,0) -> 45000000 | AH17: =M17 -> 45000000 | AI17: =AG17-AH17 -> 0
A18: 7 | B18: 5200954169 | C18: =VLOOKUP($B18,Detail!$B$4:$Q$21,2,0) -> 45870 | D18: Top Frame 800 | E18: =SUMIF(Detail!$B$4:$B$21,'Summary V.4 (2) 2 '!$B18,Detail!$E$4:$E$21) -> 2 | G18: =VLOOKUP($B18,Detail!$B$4:$Q$21,5,0) -> 225000000 | H18: =E18*G18 -> 450000000 | I18: =SUMIF(Detail!$B$4:$B$21,'Summary V.4 (2) 2 '!B18,Detail!$H$4:$H$21) -> 225000000 | J18: =(I18*20%)/E18 -> 22500000 | K18: =I18*20% -> 45000000 | M18: =SUM(K18:L18) -> 45000000 | O18: =E18 -> 2 | V18: =SUM(N18:S18) -> 2 | W18: =E18-V18 -> 0 | X18: =J18*V18 -> 45000000 | Y18: =K18-X18 -> 0 | Z18: 45868 | AA18: 45873 | AB18: 45904 | AD18: Close | AG18: =VLOOKUP(B18,investasi!$B$5:$G$18,6,0) -> 45000000 | AH18: =M18 -> 45000000 | AI18: =AG18-AH18 -> 0
A19: 8 | B19: 5200777098 | C19: =VLOOKUP($B19,Detail!$B$4:$Q$25,2,0) -> 45877 | D19: DVAR 3771-B0-20D-PPC Statcom Steel Support | E19: =SUMIF(Detail!$B$4:$B$25,'Summary V.4 (2) 2 '!$B19,Detail!$E$4:$E$25) -> 1 | G19: =VLOOKUP($B19,Detail!$B$4:$Q$25,5,0) -> 1149199000 | H19: =E19*G19 -> 1149199000 | I19: =SUMIF(Detail!$B$4:$B$25,'Summary V.4 (2) 2 '!B19,Detail!$H$4:$H$25) -> 574599500 | J19: =(I19*20%)/E19 -> 114919900 | K19: =I19*20% -> 114919900 | M19: =SUM(K19:L19) -> 114919900 | O19: 0 | P19: 1 | V19: =SUM(N19:S19) -> 1 | W19: =E19-V19 -> 0 | X19: =J19*V19 -> 114919900 | Y19: =K19-X19 -> 0 | Z19: 45930 | AA19: =Z19+7 -> 45937 | AB19: =AA19+30 -> 45967 | AC19: =AA19+60 -> 45997 | AD19: Close | AG19: =VLOOKUP(B19,investasi!$B$5:$G$18,6,0) -> 57248700 | AH19: =M19 -> 114919900 | AI19: =AG19-AH19 -> -57671200 | AJ19: Selisih di unit Qty, di catatan pak mushafa 2 unit(1 sudah terbayar , 1 unit belum terbayar ), dicatatan TARI 1 Unit
A20: 9 | B20: 5200776987 | C20: =VLOOKUP($B20,Detail!$B$4:$Q$25,2,0) -> 45877 | D20: Top Frame 800 | E20: =SUMIF(Detail!$B$4:$B$25,'Summary V.4 (2) 2 '!$B20,Detail!$E$4:$E$25) -> 2 | G20: =VLOOKUP($B20,Detail!$B$4:$Q$25,5,0) -> 225000000 | H20: =E20*G20 -> 450000000 | I20: =SUMIF(Detail!$B$4:$B$25,'Summary V.4 (2) 2 '!B20,Detail!$H$4:$H$25) -> 225000000 | J20: =(I20*20%)/E20 -> 22500000 | K20: =I20*20% -> 45000000 | M20: =SUM(K20:L20) -> 45000000 | O20: 0 | P20: 2 | V20: =SUM(N20:S20) -> 2 | W20: =E20-V20 -> 0 | X20: =J20*V20 -> 45000000 | Y20: =K20-X20 -> 0 | Z20: 45923 | AA20: =Z20+7 -> 45930 | AB20: =AA20+30 -> 45960 | AC20: =AA20+60 -> 45990 | AD20: Close | AG20: =VLOOKUP(B20,investasi!$B$5:$G$18,6,0) -> 45000000 | AH20: =M20 -> 45000000 | AI20: =AG20-AH20 -> 0
A21: 10 | B21: 5200777132 | C21: =VLOOKUP($B21,Detail!$B$4:$Q$110,2,0) -> 45880 | D21: Leser Barrier MK 01-F3004973 | E21: 20 | G21: =VLOOKUP($B21,Detail!$B$4:$Q$25,5,0) -> 40457500 | H21: =E21*G21 -> 809150000 | I21: =H21*50% -> 404575000 | J21: =(I21*13%)/E21 -> 2629737.5 | K21: =I21*13% -> 52594750 | M21: =SUM(K21:L21) -> 52594750 | O21: 0 | Q21: 20 | V21: =SUM(N21:S21) -> 20 | W21: =E21-V21 -> 0 | X21: =J21*V21 -> 52594750 | Y21: =K21-X21 -> 0 | Z21: 45922 | AA21: =Z21+7 -> 45929 | AB21: =AA21+30 -> 45959 | AC21: =AA21+60 -> 45989 | AD21: Close | AG21: =VLOOKUP(B21,investasi!$B$5:$G$18,6,0) -> 52594750 | AH21: =M21 -> 52594750 | AI21: =AG21-AH21 -> 0
A22: 11 | B22: =Detail!$B$45 -> 5200972695 | C22: =Detail!$C$45 -> 45891 | D22: Tangki | E22: 8 | F22: 75000000 | G22: 100500000 | H22: =E22*G22 -> 804000000 | I22: =H22*50% -> 402000000 | J22: 12750000 | K22: =E22*J22 -> 102000000 | M22: =SUM(K22:L22) -> 102000000 | O22: 0 | P22: 8 | U22: Margin was arranged 25mil/ea | V22: =SUM(N22:S22) -> 8 | W22: =E22-V22 -> 0 | X22: =J22*V22 -> 102000000 | Y22: =K22-X22 -> 0 | Z22: 45925 | AA22: =Z22+7 -> 45932 | AB22: =AA22+30 -> 45962 | AC22: =AA22+60 -> 45992 | AD22: Close | AG22: =VLOOKUP(B22,investasi!$B$5:$G$18,6,0) -> 80400000 | AH22: =M22 -> 102000000 | AI22: =AG22-AH22 -> -21600000 | AJ22: Selisih margin
A23: 12 | B23: =Detail!B53 -> 5200777558 | C23: 45897 | D23: Top Frame 2630 | E23: 1 | G23: =Detail!F53 -> 685000000 | H23: =E23*G23 -> 685000000 | I23: =H23*50% -> 342500000 | J23: =(I23*20%)/E23 -> 68500000 | K23: =I23*20% -> 68500000 | M23: =SUM(K23:L23) -> 68500000 | P23: 1 | V23: =SUM(N23:S23) -> 1 | W23: =E23-V23 -> 0 | X23: =J23*V23 -> 68500000 | Y23: =K23-X23 -> 0 | Z23: 45923 | AA23: =Z23+7 -> 45930 | AB23: =AA23+30 -> 45960 | AC23: =AA23+60 -> 45990 | AD23: Close | AG23: =VLOOKUP(B23,investasi!$B$5:$G$18,6,0) -> 68500000 | AH23: =M23 -> 68500000 | AI23: =AG23-AH23 -> 0
A24: 13 | B24: =Detail!B54 -> 5200777559 | C24: 45901 | D24: Top Frame 800 | E24: 2 | G24: =Detail!F54 -> 225000000 | H24: =E24*G24 -> 450000000 | I24: =H24*50% -> 225000000 | J24: =(I24*20%)/E24 -> 22500000 | K24: =I24*20% -> 45000000 | M24: =SUM(K24:L24) -> 45000000 | P24: 2 | V24: =SUM(N24:S24) -> 2 | W24: =E24-V24 -> 0 | X24: =J24*V24 -> 45000000 | Y24: =K24-X24 -> 0 | Z24: 45925 | AA24: =Z24+7 -> 45932 | AB24: =AA24+30 -> 45962 | AC24: =AA24+60 -> 45992 | AD24: Close | AG24: =VLOOKUP(B24,investasi!$B$5:$G$18,6,0) -> 45000000 | AH24: =M24 -> 45000000 | AI24: =AG24-AH24 -> 0
A25: 14 | B25: =Detail!$B$56 -> 5200777758 | C25: 45909 | D25: Pipe Spool | E25: 1 | G25: =Detail!F56 -> 2231048200 | H25: =E25*G25 -> 2231048200 | I25: =H25*50% -> 1115524100 | J25: =(I25*20%)/E25 -> 223104820 | K25: =I25*20% -> 223104820 | M25: =SUM(K25:L25) -> 223104820 | P25: 1 | V25: =SUM(N25:S25) -> 1 | W25: =E25-V25 -> 0 | X25: =J25*V25 -> 223104820 | Y25: =K25-X25 -> 0 | Z25: 45930 | AA25: =Z25+7 -> 45937 | AB25: =AA25+30 -> 45967 | AC25: =AA25+60 -> 45997 | AD25: Close | AG25: =VLOOKUP(B25,investasi!$B$5:$G$18,6,0) -> 223104820 | AH25: =M25 -> 223104820 | AI25: =AG25-AH25 -> 0
A26: 15 | B26: =Detail!$B$58 -> 5200778319 | C26: 45909 | D26: =Detail!$D$58 -> Top Frame 800 | E26: 2 | G26: =Detail!$F$58 -> 225000000 | H26: =E26*G26 -> 450000000 | I26: =H26*50% -> 225000000 | J26: =(I26*20%)/E26 -> 22500000 | K26: =I26*20% -> 45000000 | M26: =SUM(K26:L26) -> 45000000 | P26: 2 | V26: =SUM(N26:S26) -> 2 | W26: =E26-V26 -> 0 | X26: =J26*V26 -> 45000000 | Y26: =K26-X26 -> 0 | Z26: 45940 | AA26: =Z26+7 -> 45947 | AB26: =AA26+30 -> 45977 | AC26: =AA26+60 -> 46007 | AD26: Close | AG26: =VLOOKUP(B26,investasi!$B$23:$G$26,6,0) -> 45000000 | AH26: =M26 -> 45000000 | AI26: =AG26-AH26 -> 0
A27: 16 | B27: 5200778328 | C27: 45915 | D27: Top Frame 2630 | E27: 1 | G27: =Detail!F59 -> 685000000 | H27: =E27*G27 -> 685000000 | I27: =H27*50% -> 342500000 | J27: =(I27*20%)/E27 -> 68500000 | K27: =(I27*20%)+F27 -> 68500000 | L27: 66261000 | M27: =SUM(K27:L27) -> 134761000 | P27: 1 | V27: =SUM(N27:S27) -> 1 | W27: =E27-V27 -> 0 | X27: =J27*V27+L27 -> 134761000 | Y27: =K27+L27-X27 -> 0 | Z27: 45940 | AA27: =Z27+7 -> 45947 | AB27: =AA27+30 -> 45977 | AC27: =AA27+60 -> 46007 | AD27: Close | AG27: =VLOOKUP(B27,investasi!$B$23:$G$26,6,0)+investasi!I24 -> 134761000 | AH27: =M27 -> 134761000 | AI27: =AG27-AH27 -> 0
V28: =SUM(N28:S28) -> 0 | AD28: Close
A29: 18 | B29: =Detail!B60 -> 5200779815 | C29: 45965 | D29: Top Frame 2630 | E29: 1 | G29: =Detail!F60 -> 685000000 | H29: =E29*G29 -> 685000000 | I29: =H29*50% -> 342500000 | J29: =(I29*20%)/E29 -> 68500000 | K29: =(I29*20%)+F29 -> 68500000 | L29: 66261000 | M29: =SUM(K29:L29) -> 134761000 | R29: 1 | V29: =SUM(N29:S29) -> 1 | W29: =E29-V29 -> 0 | X29: =J29*V29+L29 -> 134761000 | Y29: =K29+L29-X29 -> 0 | Z29: 45989 | AA29: 46008 | AB29: =AA29+30 -> 46038 | AC29: =AA29+30 -> 46038 | AD29: Delivered | AG29: =VLOOKUP(B29,investasi!$B$23:$G$26,6,0)+investasi!I26 -> 134761000 | AH29: =M29 -> 134761000 | AI29: =AG29-AH29 -> 0
A30: =A29+1 -> 19 | B30: 5200988854 | C30: 45977 | D30: Trench Grade | E30: 150 | G30: 4990500 | H30: =E30*G30 -> 748575000 | I30: =H30*50% -> 374287500 | J30: =(I30*20%)/E30 -> 499050 | K30: =(I30*20%)+F30 -> 74857500 | M30: =SUM(K30:L30) -> 74857500 | R30: 150 | V30: =SUM(N30:S30) -> 150 | W30: =E30-V30 -> 0 | X30: =J30*V30+L30 -> 74857500 | Y30: =K30+L30-X30 -> 0 | Z30: 45989 | AA30: 46008 | AB30: =AA30+30 -> 46038 | AC30: =AA30+30 -> 46038 | AD30: Delivered
A31: =A30+1 -> 20 | B31: 5200989664 | C31: 45977 | D31: Grating Ditch | E31: 100 | G31: 21100000 | H31: =E31*G31 -> 2110000000 | I31: =H31*50% -> 1055000000 | J31: =(I31*20%)/E31 -> 2110000 | K31: =(I31*20%)+F31 -> 211000000 | M31: =SUM(K31:L31) -> 211000000 | S31: 100 | V31: =SUM(N31:S31) -> 100 | W31: =E31-V31 -> 0 | X31: =J31*V31+L31 -> 211000000 | Y31: =K31+L31-X31 -> 0 | Z31: 45999 | AA31: =Z31 -> 45999 | AB31: =AA31+30 -> 46029 | AC31: =AA31+30 -> 46029 | AD31: Delivered | AE31: Belum Di invoice 50, 50 unit penfgiriman
A32: =A31+1 -> 21 | B32: 5200989665 | C32: 45977 | D32: Grating Ditch | E32: 100 | G32: 21100000 | H32: =E32*G32 -> 2110000000 | I32: =H32*50% -> 1055000000 | J32: =(I32*20%)/E32 -> 2110000 | K32: =(I32*20%)+F32 -> 211000000 | M32: =SUM(K32:L32) -> 211000000 | S32: 100 | V32: =SUM(N32:T32) -> 100 | W32: =E32-V32 -> 0 | X32: =J32*V32+L32 -> 211000000 | Y32: =K32+L32-X32 -> 0 | Z32: 46020 | AA32: =Z32 -> 46020 | AB32: =AA32+30 -> 46050 | AC32: =AA32+30 -> 46050 | AD32: Delivered | AE32: Belum Di invoice 50, 50 unit penfgiriman
A33: =A32+1 -> 22 | B33: 5200989666 | C33: 45977 | D33: Grating Ditch | E33: 110 | G33: 21100000 | H33: =E33*G33 -> 2321000000 | I33: =H33*50% -> 1160500000 | J33: =(I33*20%)/E33 -> 2110000 | K33: =(I33*20%)+F33 -> 232100000 | M33: =SUM(K33:L33) -> 232100000 | T33: 55 | V33: =SUM(N33:T33) -> 55 | W33: =E33-V33 -> 55 | X33: =J33*V33+L33 -> 116050000 | Y33: =K33+L33-X33 -> 116050000 | Z33: 46027 | AA33: =Z33 -> 46027 | AB33: =AA33+30 -> 46057 | AC33: =AA33+30 -> 46057 | AD33: Partial Delivery | AE33: 55 ea Terkirim
A34: =A33+1 -> 23 | B34: 5200992759 | C34: 45981 | D34: Tanki | E34: 6 | G34: 100500000 | H34: =E34*G34 -> 603000000 | I34: =H34*50% -> 301500000 | J34: 12750000 | K34: =J34*E34 -> 76500000 | M34: =SUM(K34:L34) -> 76500000 | V34: =SUM(N34:S34) -> 0 | Y34: =K34+L34-X34 -> 76500000 | AD34: Open
A35: =A34+1 -> 24 | B35: 5200991260 | C35: 45985 | D35: Trench Grade | E35: 150 | G35: 4990500 | H35: =E35*G35 -> 748575000 | I35: =H35*50% -> 374287500 | J35: =(I35*20%)/E35 -> 499050 | K35: =(I35*20%)+F35 -> 74857500 | M35: =SUM(K35:L35) -> 74857500 | S35: =E35 -> 150 | V35: =SUM(N35:S35) -> 150 | W35: =E35-V35 -> 0 | X35: =J35*V35+L35 -> 74857500 | Y35: =K35+L35-X35 -> 0 | Z35: =C35+14 -> 45999 | AA35: =Z35 -> 45999 | AB35: =AA35+30 -> 46029 | AC35: =AA35+30 -> 46029 | AD35: Delivered
A36: =A35+1 -> 25 | B36: 5200991264 | C36: 45985 | D36: Trench Grade | E36: 150 | G36: 4990500 | H36: =E36*G36 -> 748575000 | I36: =H36*50% -> 374287500 | J36: =(I36*20%)/E36 -> 499050 | K36: =(I36*20%)+F36 -> 74857500 | M36: =SUM(K36:L36) -> 74857500 | S36: =E36 -> 150 | V36: =SUM(N36:S36) -> 150 | W36: =E36-V36 -> 0 | X36: =J36*V36+L36 -> 74857500 | Y36: =K36+L36-X36 -> 0 | Z36: =C36+21 -> 46006 | AA36: =Z36 -> 46006 | AB36: =AA36+30 -> 46036 | AC36: =AA36+30 -> 46036 | AD36: Delivered
A37: =A36+1 -> 26 | B37: 5200991456 | C37: 45986 | D37: Trench Grade | E37: 150 | G37: 4990500 | H37: =E37*G37 -> 748575000 | I37: =H37*50% -> 374287500 | J37: =(I37*20%)/E37 -> 499050 | K37: =(I37*20%)+F37 -> 74857500 | M37: =SUM(K37:L37) -> 74857500 | S37: =E37 -> 150 | V37: =SUM(N37:S37) -> 150 | W37: =E37-V37 -> 0 | X37: =J37*V37+L37 -> 74857500 | Y37: =K37+L37-X37 -> 0 | Z37: 46014 | AA37: =Z37 -> 46014 | AB37: =AA37+30 -> 46044 | AC37: =AA37+30 -> 46044 | AD37: Delivered | AE37: Blm Invoice
A38: =A37+1 -> 27 | B38: 5200991458 | C38: 45986 | D38: Trench Grade | E38: 150 | G38: 4990500 | H38: =E38*G38 -> 748575000 | I38: =H38*50% -> 374287500 | J38: =(I38*20%)/E38 -> 499050 | K38: =(I38*20%)+F38 -> 74857500 | M38: =SUM(K38:L38) -> 74857500 | S38: =E38 -> 150 | V38: =SUM(N38:S38) -> 150 | W38: =E38-V38 -> 0 | X38: =J38*V38+L38 -> 74857500 | Y38: =K38+L38-X38 -> 0 | Z38: 46014 | AA38: =Z38 -> 46014 | AB38: =AA38+30 -> 46044 | AC38: =AA38+30 -> 46044 | AD38: Delivered | AE38: Blm Invoice
A39: =A38+1 -> 28 | B39: 5200991502 | C39: 45986 | D39: Trench Grade | E39: 150 | G39: 4990500 | H39: =E39*G39 -> 748575000 | I39: =H39*50% -> 374287500 | J39: =(I39*20%)/E39 -> 499050 | K39: =(I39*20%)+F39 -> 74857500 | M39: =SUM(K39:L39) -> 74857500 | S39: =E39 -> 150 | V39: =SUM(N39:S39) -> 150 | W39: =E39-V39 -> 0 | X39: =J39*V39+L39 -> 74857500 | Y39: =K39+L39-X39 -> 0 | Z39: 46005 | AA39: =Z39 -> 46005 | AB39: =AA39+30 -> 46035 | AC39: =AA39+30 -> 46035 | AD39: Delivered | AE39: Blm Invoice
A40: =A39+1 -> 29 | B40: 5200991503 | C40: 45986 | D40: Trench Grade | E40: 150 | G40: 4990500 | H40: =E40*G40 -> 748575000 | I40: =H40*50% -> 374287500 | J40: =(I40*20%)/E40 -> 499050 | K40: =(I40*20%)+F40 -> 74857500 | M40: =SUM(K40:L40) -> 74857500 | S40: =E40 -> 150 | V40: =SUM(N40:S40) -> 150 | W40: =E40-V40 -> 0 | X40: =J40*V40+L40 -> 74857500 | Y40: =K40+L40-X40 -> 0 | Z40: 46005 | AA40: =Z40 -> 46005 | AB40: =AA40+30 -> 46035 | AC40: =AA40+30 -> 46035 | AD40: Delivered | AE40: Blm Invoice
A41: =A40+1 -> 30 | B41: 5200991553 | C41: 46372 | D41: Trench Grade | E41: 50 | G41: 4990500 | H41: =E41*G41 -> 249525000 | I41: =H41*50% -> 124762500 | J41: =(I41*20%)/E41 -> 499050 | K41: =(I41*20%)+F41 -> 24952500 | M41: =SUM(K41:L41) -> 24952500 | S41: =E41 -> 50 | V41: =SUM(N41:S41) -> 50 | W41: =E41-V41 -> 0 | X41: =J41*V41+L41 -> 24952500 | Y41: =K41+L41-X41 -> 0 | Z41: 46020 | AA41: =Z41 -> 46020 | AB41: =AA41+30 -> 46050 | AC41: =AA41+30 -> 46050 | AD41: Delivered | AE41: Blm Invoice
A42: =A41+1 -> 31 | B42: 5200996833 | C42: 46021 | D42: new barge landing facility | E42: 1 | H42: 1188000000 | I42: =H42*50% -> 594000000 | J42: =(I42*20%)/E42 -> 118800000 | K42: =(I42*20%)+F42 -> 118800000 | M42: =SUM(K42:L42) -> 118800000 | Y42: =K42+L42-X42 -> 118800000 | Z42: =C42+21 -> 46042 | AA42: =Z42+7 -> 46049 | AB42: =AA42+30 -> 46079 | AC42: =AA42+30 -> 46079 | AD42: Open
A43: =A42+1 -> 32 | B43: 520099xxxx | C43: 46021 | D43: KL Pipe Bracket | E43: 400 | G43: 548000 | H43: =E43*G43 -> 219200000 | I43: =H43*50% -> 109600000 | J43: =(I43*20%)/E43 -> 54800 | K43: =I43*20% -> 21920000 | M43: =SUM(K43:L43) -> 21920000 | Y43: =K43+L43-X43 -> 21920000 | Z43: =C43+21 -> 46042 | AA43: =Z43+7 -> 46049 | AB43: =AA43+30 -> 46079 | AC43: =AA43+30 -> 46079 | AD43: Open
B45: TOTAL MARGIN | H45: =SUM(H12:H43) -> 26489147200 | I45: =SUM(I12:I43) -> 13244573600 | K45: =SUM(K12:K43) -> 2658394470 | L45: =SUM(L12:L43) -> 132522000 | M45: =SUM(M12:M43) -> 2790916470 | X45: =SUM(X12:X43) -> 2457646470 | Y45: =SUM(Y12:Y43) -> 333270000
Y46: =X45+Y45-H65 -> 2790916470
E47: A | G47: B | H47: C | I47: D | J47: E | K47: F=A+B+C-D-E
E48: TGL | F48: Modal Setor Awal | G48: Margin | H48: Pencairan Modal | I48: Modal PO Baru | J48: Penarikan | K48: Dana Tersedia
E49: 45839 | F49: =SUM(I12:I14) -> 900000000 | G49: =SUM(X12:X14) -> 180000000 | K49: =F49+G49 -> 1080000000 | Y49: =SUM(I26:I29,AH26:AH29) -> 1224522000
E50: 45870 | F50: =SUM(I15:I18) -> 1125000000 | G50: =SUM(X15:X18) -> 225000000 | I50: =SUM(I19:I22) -> 1606174500 | K50: =K49+F50+G50+H50-I50-J50 -> 823825500
E51: 45901 | F51: 1426698600 | I51: =SUM(I23:I27) -> 2250524100 | K51: =K50+F51+G51+H51-I51 -> 0
E52: 45931 | I52: =I29+I28 -> 342500000 | K52: =K51+F52+G52+H52-I52 -> -342500000
E53: 45962 | G53: =SUM(M19:M28) -> 830880470 | I53: =-SUM(I19:I28)+SUM(I30:I40) -> 2335313900 | J53: 1105000000 | K53: =K52+F53+G53+H53-I53-J53 -> -2951933430
E54: 46007 | F54: 1300000000 | I54: =I41+I42+I43 -> 828362500 | K54: =K53+F54+G54+H54-I54-J54 -> -2480295930
E55: 46014 | F55: 250000000 | K55: =K54+F55+G55+H55-I55-J55 -> -2230295930
E56: 46015 | F56: 250000000 | K56: =K55+F56+G56+H56-I56-J56 -> -1980295930
E57: 46016 | F57: 250000000 | K57: =K56+F57+G57+H57-I57-J57 -> -1730295930
E58: 46017 | F58: 250000000 | K58: =K57+F58+G58+H58-I58-J58 -> -1480295930
E59: 46018 | F59: 250000000 | K59: =K58+F59+G59+H59-I59-J59 -> -1230295930
E60: 46019 | F60: 250000000 | K60: =K59+F60+G60+H60-I60-J60 -> -980295930
E61: 46020 | F61: 150000000 | K61: =K60+F61+G61+H61-I61-J61 -> -830295930
F62: =SUM(F49:F61) -> 6401698600 | G62: =SUM(G49:G54) -> 1235880470 | H62: =SUM(H49:H54) -> 0 | I62: =SUM(I49:I54) -> 7362875000 | J62: =SUM(J49:J54) -> 1105000000 | K62: =F62+G62+H62-I62-J62 -> -830295930
E64: Setor Modal Awal | F64: =F62 -> 6401698600 | I64: Asumsi
E65: Margin | F65: =SUM(M12:M27) -> 1235880470 | I65: Setor Modal | J65: =F62 -> 6401698600
E66: Modal PO baru | F66: =-I62 -> -7362875000 | G66: Baris 18-29 | I66: Margin | J66: =G62 -> 1235880470
E67: Penarikan | F67: =-J53 -> -1105000000 | I67: Penarikan Margin | J67: =-J53 -> -1105000000
E68: Dana Tersedia/Kurang | F68: =F64+F65+F66+F67 -> -830295930 | I68: PO Baru | J68: =-I62 -> -7362875000
I69: Kurang | J69: =J65+J66+J67+J68 -> -830295930
E70: PO & margin akan cair | F70: =SUM(I29:I40,M29:M40) -> 7923876000 | G70: Baris 18-29
I71: Margin yang akan diterima | J71: Jumlah | K71: Modal yang akan diterima
I72: 46023 | J72: =SUM(X29:X32,X35:X41) -> 1105716000
F73: 130000000 | I73: 46054 | J73: =SUM(X33) -> 116050000
I74: Margin yang akan diterima | J74: =SUM(J72:J73) -> 1221766000
I76: Belum Terkirim | J76: =Y45 -> 333270000
I77: Total Margin Yg Akan diterim | J77: =J74+J76 -> 1555036000

Sheet Summary V.4 (2)
B1: LIST INVESTASI
C3: Close
C4: Delivered
C5: Partial Delivery
C6: Open
C7: Margin Selisih | E7: =Detail!E2 -> 4 | G7: =Detail!F2 -> 5 | H7: =Detail!G2 -> 6 | I7: =Detail!H2 -> 7 | K7: =Detail!I2 -> 8
C8: Tidak aada di PO Tari
A10: NO | B10: No. PO | C10: Date | D10: Nama Barang | E10: =Detail!E3 -> Qty | F10: Harga Beli (only added if Margin is set) | G10: =Detail!F3 -> Harga | H10: Total PO | I10: Modal | J10: Margin Per Unit | K10: =Detail!I3 -> Margin | L10: Add Margin | M10: Total Margin | N10: Invoice /DO | U10: DO Total | V10: DO Outstanding | W10: Margin | X10: AR MARGIN | Y10: Del Time | Z10: Invoice date | AA10: Initial Payment Date | AB10: adjusting TOP 60 Days | AC10: Status | AD10: Notes | AF10: Tari | AG10: Total Margin TARI | AH10: Selisih
N11: Jul | O11: Aug | P11: Sep | Q11: Oct | R11: Nov | S11: Dec | T11: Add Margin (by Agreement) | AD11: Notes
A12: 1 | B12: 5200954145 | C12: =VLOOKUP($B12,Detail!$B$4:$Q$21,2,0) -> 45839 | D12: Top Frame 800 | E12: =SUMIF(Detail!$B$4:$B$21,'Summary V.4 (2)'!$B12,Detail!$E$4:$E$21) -> 2 | G12: =VLOOKUP($B12,Detail!$B$4:$Q$21,5,0) -> 225000000 | H12: =E12*G12 -> 450000000 | I12: =SUMIF(Detail!$B$4:$B$21,'Summary V.4 (2)'!B12,Detail!$H$4:$H$21) -> 225000000 | J12: =(I12*20%)/E12 -> 22500000 | K12: =I12*20% -> 45000000 | M12: =SUM(K12:L12) -> 45000000 | N12: =E12 -> 2 | U12: =SUM(N12:S12) -> 2 | V12: =E12-U12 -> 0 | W12: =J12*U12 -> 45000000 | X12: =K12-W12 -> 0 | Y12: 45861 | Z12: 45863 | AA12: 45894 | AC12: Close | AF12: =VLOOKUP(B12,investasi!$B$5:$G$18,6,0) -> 45000000 | AG12: =M12 -> 45000000 | AH12: =AF12-AG12 -> 0
A13: 2 | B13: 5200954149 | C13: =VLOOKUP($B13,Detail!$B$4:$Q$21,2,0) -> 45839 | D13: Top Frame 800 | E13: =SUMIF(Detail!$B$4:$B$21,'Summary V.4 (2)'!$B13,Detail!$E$4:$E$21) -> 3 | G13: =VLOOKUP($B13,Detail!$B$4:$Q$21,5,0) -> 225000000 | H13: =E13*G13 -> 675000000 | I13: =SUMIF(Detail!$B$4:$B$21,'Summary V.4 (2)'!B13,Detail!$H$4:$H$21) -> 337500000 | J13: =(I13*20%)/E13 -> 22500000 | K13: =I13*20% -> 67500000 | M13: =SUM(K13:L13) -> 67500000 | N13: =E13 -> 3 | U13: =SUM(N13:S13) -> 3 | V13: =E13-U13 -> 0 | W13: =J13*U13 -> 67500000 | X13: =K13-W13 -> 0 | Y13: 45861 | Z13: 45863 | AA13: 45894 | AC13: Close | AF13: =VLOOKUP(B13,investasi!$B$5:$G$18,6,0) -> 67500000 | AG13: =M13 -> 67500000 | AH13: =AF13-AG13 -> 0
A14: 3 | B14: 5200954160 | C14: =VLOOKUP($B14,Detail!$B$4:$Q$21,2,0) -> 45839 | D14: Top Frame 800 | E14: =SUMIF(Detail!$B$4:$B$21,'Summary V.4 (2)'!$B14,Detail!$E$4:$E$21) -> 3 | G14: =VLOOKUP($B14,Detail!$B$4:$Q$21,5,0) -> 225000000 | H14: =E14*G14 -> 675000000 | I14: =SUMIF(Detail!$B$4:$B$21,'Summary V.4 (2)'!B14,Detail!$H$4:$H$21) -> 337500000 | J14: =(I14*20%)/E14 -> 22500000 | K14: =I14*20% -> 67500000 | M14: =SUM(K14:L14) -> 67500000 | N14: =E14 -> 3 | U14: =SUM(N14:S14) -> 3 | V14: =E14-U14 -> 0 | W14: =J14*U14 -> 67500000 | X14: =K14-W14 -> 0 | Y14: 45861 | Z14: 45863 | AA14: 45894 | AC14: Close | AF14: =VLOOKUP(B14,investasi!$B$5:$G$18,6,0) -> 67500000 | AG14: =M14 -> 67500000 | AH14: =AF14-AG14 -> 0
A15: 4 | B15: 5200954165 | C15: =VLOOKUP($B15,Detail!$B$4:$Q$21,2,0) -> 45870 | D15: Top Frame 800 | E15: =SUMIF(Detail!$B$4:$B$21,'Summary V.4 (2)'!$B15,Detail!$E$4:$E$21) -> 3 | G15: =VLOOKUP($B15,Detail!$B$4:$Q$21,5,0) -> 225000000 | H15: =E15*G15 -> 675000000 | I15: =SUMIF(Detail!$B$4:$B$21,'Summary V.4 (2)'!B15,Detail!$H$4:$H$21) -> 337500000 | J15: =(I15*20%)/E15 -> 22500000 | K15: =I15*20% -> 67500000 | M15: =SUM(K15:L15) -> 67500000 | O15: =E15 -> 3 | U15: =SUM(N15:S15) -> 3 | V15: =E15-U15 -> 0 | W15: =J15*U15 -> 67500000 | X15: =K15-W15 -> 0 | Y15: 45868 | Z15: 45873 | AA15: 45904 | AC15: Close | AF15: =VLOOKUP(B15,investasi!$B$5:$G$18,6,0) -> 67500000 | AG15: =M15 -> 67500000 | AH15: =AF15-AG15 -> 0
A16: 5 | B16: 5200954167 | C16: =VLOOKUP($B16,Detail!$B$4:$Q$21,2,0) -> 45870 | D16: Top Frame 800 | E16: =SUMIF(Detail!$B$4:$B$21,'Summary V.4 (2)'!$B16,Detail!$E$4:$E$21) -> 3 | G16: =VLOOKUP($B16,Detail!$B$4:$Q$21,5,0) -> 225000000 | H16: =E16*G16 -> 675000000 | I16: =SUMIF(Detail!$B$4:$B$21,'Summary V.4 (2)'!B16,Detail!$H$4:$H$21) -> 337500000 | J16: =(I16*20%)/E16 -> 22500000 | K16: =I16*20% -> 67500000 | M16: =SUM(K16:L16) -> 67500000 | O16: =E16 -> 3 | U16: =SUM(N16:S16) -> 3 | V16: =E16-U16 -> 0 | W16: =J16*U16 -> 67500000 | X16: =K16-W16 -> 0 | Y16: 45868 | Z16: 45873 | AA16: 45904 | AC16: Close | AF16: =VLOOKUP(B16,investasi!$B$5:$G$18,6,0) -> 67500000 | AG16: =M16 -> 67500000 | AH16: =AF16-AG16 -> 0
A17: 6 | B17: 5200954168 | C17: =VLOOKUP($B17,Detail!$B$4:$Q$21,2,0) -> 45870 | D17: Top Frame 800 | E17: =SUMIF(Detail!$B$4:$B$21,'Summary V.4 (2)'!$B17,Detail!$E$4:$E$21) -> 2 | G17: =VLOOKUP($B17,Detail!$B$4:$Q$21,5,0) -> 225000000 | H17: =E17*G17 -> 450000000 | I17: =SUMIF(Detail!$B$4:$B$21,'Summary V.4 (2)'!B17,Detail!$H$4:$H$21) -> 225000000 | J17: =(I17*20%)/E17 -> 22500000 | K17: =I17*20% -> 45000000 | M17: =SUM(K17:L17) -> 45000000 | O17: =E17 -> 2 | U17: =SUM(N17:S17) -> 2 | V17: =E17-U17 -> 0 | W17: =J17*U17 -> 45000000 | X17: =K17-W17 -> 0 | Y17: 45868 | Z17: 45873 | AA17: 45904 | AC17: Close | AF17: =VLOOKUP(B17,investasi!$B$5:$G$18,6,0) -> 45000000 | AG17: =M17 -> 45000000 | AH17: =AF17-AG17 -> 0
A18: 7 | B18: 5200954169 | C18: =VLOOKUP($B18,Detail!$B$4:$Q$21,2,0) -> 45870 | D18: Top Frame 800 | E18: =SUMIF(Detail!$B$4:$B$21,'Summary V.4 (2)'!$B18,Detail!$E$4:$E$21) -> 2 | G18: =VLOOKUP($B18,Detail!$B$4:$Q$21,5,0) -> 225000000 | H18: =E18*G18 -> 450000000 | I18: =SUMIF(Detail!$B$4:$B$21,'Summary V.4 (2)'!B18,Detail!$H$4:$H$21) -> 225000000 | J18: =(I18*20%)/E18 -> 22500000 | K18: =I18*20% -> 45000000 | M18: =SUM(K18:L18) -> 45000000 | O18: =E18 -> 2 | U18: =SUM(N18:S18) -> 2 | V18: =E18-U18 -> 0 | W18: =J18*U18 -> 45000000 | X18: =K18-W18 -> 0 | Y18: 45868 | Z18: 45873 | AA18: 45904 | AC18: Close | AF18: =VLOOKUP(B18,investasi!$B$5:$G$18,6,0) -> 45000000 | AG18: =M18 -> 45000000 | AH18: =AF18-AG18 -> 0
A19: 8 | B19: 5200777098 | C19: =VLOOKUP($B19,Detail!$B$4:$Q$25,2,0) -> 45877 | D19: DVAR 3771-B0-20D-PPC Statcom Steel Support | E19: =SUMIF(Detail!$B$4:$B$25,'Summary V.4 (2)'!$B19,Detail!$E$4:$E$25) -> 1 | G19: =VLOOKUP($B19,Detail!$B$4:$Q$25,5,0) -> 1149199000 | H19: =E19*G19 -> 1149199000 | I19: =SUMIF(Detail!$B$4:$B$25,'Summary V.4 (2)'!B19,Detail!$H$4:$H$25) -> 574599500 | J19: =(I19*20%)/E19 -> 114919900 | K19: =I19*20% -> 114919900 | M19: =SUM(K19:L19) -> 114919900 | O19: 0 | P19: 1 | U19: =SUM(N19:S19) -> 1 | V19: =E19-U19 -> 0 | W19: =J19*U19 -> 114919900 | X19: =K19-W19 -> 0 | Y19: 45930 | Z19: =Y19+7 -> 45937 | AA19: =Z19+30 -> 45967 | AB19: =Z19+60 -> 45997 | AC19: Close | AF19: =VLOOKUP(B19,investasi!$B$5:$G$18,6,0) -> 57248700 | AG19: =M19 -> 114919900 | AH19: =AF19-AG19 -> -57671200 | AI19: Selisih di unit Qty, di catatan pak mushafa 2 unit(1 sudah terbayar , 1 unit belum terbayar ), dicatatan TARI 1 Unit
A20: 9 | B20: 5200776987 | C20: =VLOOKUP($B20,Detail!$B$4:$Q$25,2,0) -> 45877 | D20: Top Frame 800 | E20: =SUMIF(Detail!$B$4:$B$25,'Summary V.4 (2)'!$B20,Detail!$E$4:$E$25) -> 2 | G20: =VLOOKUP($B20,Detail!$B$4:$Q$25,5,0) -> 225000000 | H20: =E20*G20 -> 450000000 | I20: =SUMIF(Detail!$B$4:$B$25,'Summary V.4 (2)'!B20,Detail!$H$4:$H$25) -> 225000000 | J20: =(I20*20%)/E20 -> 22500000 | K20: =I20*20% -> 45000000 | M20: =SUM(K20:L20) -> 45000000 | O20: 0 | P20: 2 | U20: =SUM(N20:S20) -> 2 | V20: =E20-U20 -> 0 | W20: =J20*U20 -> 45000000 | X20: =K20-W20 -> 0 | Y20: 45923 | Z20: =Y20+7 -> 45930 | AA20: =Z20+30 -> 45960 | AB20: =Z20+60 -> 45990 | AC20: Close | AF20: =VLOOKUP(B20,investasi!$B$5:$G$18,6,0) -> 45000000 | AG20: =M20 -> 45000000 | AH20: =AF20-AG20 -> 0
A21: 10 | B21: 5200777132 | C21: =VLOOKUP($B21,Detail!$B$4:$Q$110,2,0) -> 45880 | D21: Leser Barrier MK 01-F3004973 | E21: 20 | G21: =VLOOKUP($B21,Detail!$B$4:$Q$25,5,0) -> 40457500 | H21: =E21*G21 -> 809150000 | I21: =H21*50% -> 404575000 | J21: =(I21*13%)/E21 -> 2629737.5 | K21: =I21*13% -> 52594750 | M21: =SUM(K21:L21) -> 52594750 | O21: 0 | Q21: 20 | U21: =SUM(N21:S21) -> 20 | V21: =E21-U21 -> 0 | W21: =J21*U21 -> 52594750 | X21: =K21-W21 -> 0 | Y21: 45922 | Z21: =Y21+7 -> 45929 | AA21: =Z21+30 -> 45959 | AB21: =Z21+60 -> 45989 | AC21: Close | AF21: =VLOOKUP(B21,investasi!$B$5:$G$18,6,0) -> 52594750 | AG21: =M21 -> 52594750 | AH21: =AF21-AG21 -> 0
A22: 11 | B22: =Detail!$B$45 -> 5200972695 | C22: =Detail!$C$45 -> 45891 | D22: Tangki | E22: 8 | F22: 75000000 | G22: 100500000 | H22: =E22*G22 -> 804000000 | I22: =H22*50% -> 402000000 | J22: 12750000 | K22: =E22*J22 -> 102000000 | M22: =SUM(K22:L22) -> 102000000 | O22: 0 | P22: 8 | T22: Margin was arranged 25mil/ea | U22: =SUM(N22:S22) -> 8 | V22: =E22-U22 -> 0 | W22: =J22*U22 -> 102000000 | X22: =K22-W22 -> 0 | Y22: 45925 | Z22: =Y22+7 -> 45932 | AA22: =Z22+30 -> 45962 | AB22: =Z22+60 -> 45992 | AC22: Close | AF22: =VLOOKUP(B22,investasi!$B$5:$G$18,6,0) -> 80400000 | AG22: =M22 -> 102000000 | AH22: =AF22-AG22 -> -21600000 | AI22: Selisih margin
A23: 12 | B23: =Detail!B53 -> 5200777558 | C23: 45897 | D23: Top Frame 2630 | E23: 1 | G23: =Detail!F53 -> 685000000 | H23: =E23*G23 -> 685000000 | I23: =H23*50% -> 342500000 | J23: =(I23*20%)/E23 -> 68500000 | K23: =I23*20% -> 68500000 | M23: =SUM(K23:L23) -> 68500000 | P23: 1 | U23: =SUM(N23:S23) -> 1 | V23: =E23-U23 -> 0 | W23: =J23*U23 -> 68500000 | X23: =K23-W23 -> 0 | Y23: 45923 | Z23: =Y23+7 -> 45930 | AA23: =Z23+30 -> 45960 | AB23: =Z23+60 -> 45990 | AC23: Close | AF23: =VLOOKUP(B23,investasi!$B$5:$G$18,6,0) -> 68500000 | AG23: =M23 -> 68500000 | AH23: =AF23-AG23 -> 0
A24: 13 | B24: =Detail!B54 -> 5200777559 | C24: 45901 | D24: Top Frame 800 | E24: 2 | G24: =Detail!F54 -> 225000000 | H24: =E24*G24 -> 450000000 | I24: =H24*50% -> 225000000 | J24: =(I24*20%)/E24 -> 22500000 | K24: =I24*20% -> 45000000 | M24: =SUM(K24:L24) -> 45000000 | P24: 2 | U24: =SUM(N24:S24) -> 2 | V24: =E24-U24 -> 0 | W24: =J24*U24 -> 45000000 | X24: =K24-W24 -> 0 | Y24: 45925 | Z24: =Y24+7 -> 45932 | AA24: =Z24+30 -> 45962 | AB24: =Z24+60 -> 45992 | AC24: Close | AF24: =VLOOKUP(B24,investasi!$B$5:$G$18,6,0) -> 45000000 | AG24: =M24 -> 45000000 | AH24: =AF24-AG24 -> 0
A25: 14 | B25: =Detail!$B$56 -> 5200777758 | C25: 45909 | D25: Pipe Spool | E25: 1 | G25: =Detail!F56 -> 2231048200 | H25: =E25*G25 -> 2231048200 | I25: =H25*50% -> 1115524100 | J25: =(I25*20%)/E25 -> 223104820 | K25: =I25*20% -> 223104820 | M25: =SUM(K25:L25) -> 223104820 | P25: 1 | U25: =SUM(N25:S25) -> 1 | V25: =E25-U25 -> 0 | W25: =J25*U25 -> 223104820 | X25: =K25-W25 -> 0 | Y25: 45930 | Z25: =Y25+7 -> 45937 | AA25: =Z25+30 -> 45967 | AB25: =Z25+60 -> 45997 | AC25: Close | AF25: =VLOOKUP(B25,investasi!$B$5:$G$18,6,0) -> 223104820 | AG25: =M25 -> 223104820 | AH25: =AF25-AG25 -> 0
A26: 15 | B26: =Detail!$B$58 -> 5200778319 | C26: 45909 | D26: =Detail!$D$58 -> Top Frame 800 | E26: 2 | G26: =Detail!$F$58 -> 225000000 | H26: =E26*G26 -> 450000000 | I26: =H26*50% -> 225000000 | J26: =(I26*20%)/E26 -> 22500000 | K26: =I26*20% -> 45000000 | M26: =SUM(K26:L26) -> 45000000 | P26: 2 | U26: =SUM(N26:S26) -> 2 | V26: =E26-U26 -> 0 | W26: =J26*U26 -> 45000000 | X26: =K26-W26 -> 0 | Y26: 45940 | Z26: =Y26+7 -> 45947 | AA26: =Z26+30 -> 45977 | AB26: =Z26+60 -> 46007 | AC26: Close | AF26: =VLOOKUP(B26,investasi!$B$23:$G$26,6,0) -> 45000000 | AG26: =M26 -> 45000000 | AH26: =AF26-AG26 -> 0
A27: 16 | B27: 5200778328 | C27: 45915 | D27: Top Frame 2630 | E27: 1 | G27: =Detail!F59 -> 685000000 | H27: =E27*G27 -> 685000000 | I27: =H27*50% -> 342500000 | J27: =(I27*20%)/E27 -> 68500000 | K27: =(I27*20%)+F27 -> 68500000 | L27: 66261000 | M27: =SUM(K27:L27) -> 134761000 | P27: 1 | U27: =SUM(N27:S27) -> 1 | V27: =E27-U27 -> 0 | W27: =J27*U27+L27 -> 134761000 | X27: =K27+L27-W27 -> 0 | Y27: 45940 | Z27: =Y27+7 -> 45947 | AA27: =Z27+30 -> 45977 | AB27: =Z27+60 -> 46007 | AC27: Close | AF27: =VLOOKUP(B27,investasi!$B$23:$G$26,6,0)+investasi!I24 -> 134761000 | AG27: =M27 -> 134761000 | AH27: =AF27-AG27 -> 0
U28: =SUM(N28:S28) -> 0 | AC28: Close
A29: 18 | B29: =Detail!B60 -> 5200779815 | C29: 45965 | D29: Top Frame 2630 | E29: 1 | G29: =Detail!F60 -> 685000000 | H29: =E29*G29 -> 685000000 | I29: =H29*50% -> 342500000 | J29: =(I29*20%)/E29 -> 68500000 | K29: =(I29*20%)+F29 -> 68500000 | L29: 66261000 | M29: =SUM(K29:L29) -> 134761000 | R29: 1 | U29: =SUM(N29:S29) -> 1 | V29: =E29-U29 -> 0 | W29: =J29*U29+L29 -> 134761000 | X29: =K29+L29-W29 -> 0 | Y29: 45989 | Z29: 46008 | AA29: =Z29+30 -> 46038 | AB29: =Z29+60 -> 46068 | AC29: Delivered | AF29: =VLOOKUP(B29,investasi!$B$23:$G$26,6,0)+investasi!I26 -> 134761000 | AG29: =M29 -> 134761000 | AH29: =AF29-AG29 -> 0
A30: =A29+1 -> 19 | B30: 5200988854 | C30: 45977 | D30: Trench Grade | E30: 150 | G30: 4990500 | H30: =E30*G30 -> 748575000 | I30: =H30*50% -> 374287500 | J30: =(I30*20%)/E30 -> 499050 | K30: =(I30*20%)+F30 -> 74857500 | M30: =SUM(K30:L30) -> 74857500 | R30: 150 | U30: =SUM(N30:S30) -> 150 | V30: =E30-U30 -> 0 | W30: =J30*U30+L30 -> 74857500 | X30: =K30+L30-W30 -> 0 | Y30: 45989 | Z30: 46008 | AA30: =Z30+30 -> 46038 | AB30: =Z30+60 -> 46068 | AC30: Delivered
A31: =A30+1 -> 20 | B31: 5200989664 | C31: 45977 | D31: Grating Ditch | E31: 100 | G31: 21100000 | H31: =E31*G31 -> 2110000000 | I31: =H31*50% -> 1055000000 | J31: =(I31*20%)/E31 -> 2110000 | K31: =(I31*20%)+F31 -> 211000000 | M31: =SUM(K31:L31) -> 211000000 | U31: =SUM(N31:S31) -> 0 | X31: =K31+L31-W31 -> 211000000 | AC31: Open
